Workbook

Sheet 工程研发事业部人员名单
A1: 序号 | B1: 姓名 | C1: 胸卡号 | D1: 专业室
A2: =ROW()-1 -> 1 | B2: 毛磊凯 | C2: 51184 | D2: 办公室
A3: =ROW()-1 -> 2 | B3: 刘杰 | C3: 17242 | D3: 办公室
A4: =ROW()-1 -> 3 | B4: 宋凯（总体） | C4: 22260 | D4: 办公室
A5: =ROW()-1 -> 4 | B5: 张继斌 | C5: 17243 | D5: 总体室
A6: =ROW()-1 -> 5 | B6: 赵婷 | C6: 50702 | D6: 总体室
A7: =ROW()-1 -> 6 | B7: 刘聪 | C7: 52018 | D7: 总体室
A8: =ROW()-1 -> 7 | B8: 刘全 | C8: 50874 | D8: 总体室
A9: =ROW()-1 -> 8 | B9: 秦超 | C9: 51591 | D9: 总体室
A10: =ROW()-1 -> 9 | B10: 尤宏良 | C10: 18550 | D10: 总体室
A11: =ROW()-1 -> 10 | B11: 任璐璐 | C11: 50032 | D11: 总体室
A12: =ROW()-1 -> 11 | B12: 赵长辉 | C12: 17725 | D12: 总体室
A13: =ROW()-1 -> 12 | B13: 刘成 | C13: 51860 | D13: 总体室
... A118: =ROW()-1 -> 117 | B118: 林树德 | C118: 51202 | D118: 综合技术室
A119: =ROW()-1 -> 118 | B119: 孙红军 | C119: 02501 | D119: 综合技术室
A120: =ROW()-1 -> 119 | B120: 陈志禹 | C120: 17787 | D120: 综合技术室
A121: =ROW()-1 -> 120 | B121: 王琛 | C121: 22291 | D121: 综合技术室
A122: =ROW()-1 -> 121 | B122: 王勇 | C122: 51226 | D122: 综合技术室
A123: =ROW()-1 -> 122 | B123: 潘英 | C123: 50864 | D123: 综合技术室
A124: =ROW()-1 -> 123 | B124: 杨琼 | C124: 26828 | D124: 综合技术室
A125: =ROW()-1 -> 124 | B125: 宋建毅 | C125: 27100 | D125: 综合技术室
A126: =ROW()-1 -> 125 | B126: 孙盘滔 | C126: 50686 | D126: 综合技术室
A127: =ROW()-1 -> 126 | B127: 吕冬兰 | C127: 51160 | D127: 综合技术室
A128: =ROW()-1 -> 127 | B128: 刘红双 | C128: 51151 | D128: 综合技术室
A129: =ROW()-1 -> 128 | B129: 李其鹏 | C129: 51429 | D129: 综合技术室
A130: =ROW()-1 -> 129 | B130: 王超 | C130: 26621 | D130: 联络工程室
A131: =ROW()-1 -> 130 | B131: 崔明慧 | C131: 14901 | D131: 联络工程室
... A165: =ROW()-1 -> 164 | B165: 王瑞龙 | C165: 26654 | D165: 联络工程室

Sheet 项目简称
A1: CR929设计（2022年上飞院）
A2: CR929设计（2022年复材中心）
A3: C919设计（2020年上飞院）
A4: C919设计（2021年上飞院）
A5: C919设计（2022年上飞院）
A6: C919设计（2020年复材中心）
A7: CR929设计（2021年上飞院）
A8: CR929设计（2021年复材中心）
A9: ARJ21基本型设计（2020年上飞院）
A10: ARJ21货运型设计（2021年上飞院）
A11: ARJ上飞装备
A12: 1号设计（2022年KTB）
... A23: 临时工程支持

Sheet X月项目工时
A1: 序号 | B1: 姓名 | C1: 胸卡号 | D1: 专业室 | E1: 项目简称 | F1: 个人原始项目工时之和/h | G1: 第一年跨专业原始项目工时/h | H1: 第二年跨专业原始项目工时/h | I1: 沈阳工时/h | J1: 市外出差工时/h | K1: 专业 | L1: 工作包 | M1: 主要工作任务 （请简要说明每项设计任务、工时及所属任务通知单编号） 例：序号.工作包-任务通知单编号-设计任务-工时 | N1: 订单号 | O1: 是否国际 | Q1: 行标签 | R1: 最大值项:个人原始项目工时之和/h | S1: 胸卡号 | T1: 专业室 | U1: 项目简称 | V1: 订单号
A2: =ROW()-1 -> 1 | B2: 徐丽娜 | C2: =IFERROR(VLOOKUP(B2,[66]工程研发事业部人员名单!B:D,2,0),"") -> 50079 | D2: =IFERROR(VLOOKUP(B2,[66]工程研发事业部人员名单!B:D,3,0),"") -> 工程项目室 /适航工程室 | E2: 项目开发与管控 | F2: =G2+H2+I2+J2 -> 70 | I2: 70 | K2: PMO | L2: 项目管理 | M2: 8号设计（2025年）： 1.上报项目月工时。 2.统计每月工时发生汇总，差旅发生费用，成本归集。 3.内部及涉密信息导入导出。 4.审签出差报销。 5.跟踪8-1.1、8-1.2项目回款状态，提醒客户启动第三笔回款申请。 6.组织8-1.3项目减重合同中期评审报告及PPT的准备，组织客户预评审技术报告。 7.完成8-1.3项目减重合同及技术协议的签订。 8.准备8-1.3项目减重合同及技术协议外带及对外提供手续。 9.组织准备8-1.3项目减重合同免税申报材料（技术方案）。 10.组织陕飞某项目舱门、后机身设计外包技术方案的编制、参加其评审会。 | N2: =VLOOKUP(E2,订单号!B:C,2,0) -> #N/A | O2: =VLOOKUP(C2,领导干部!B:B,1,0) -> #N/A | Q2: 柴宝 | R2: 210 | S2: {=VLOOKUP(Q2&R2,IF({1,0},$B$2:$B$330&$F$2:$F$330,$C$2:$C$330),2,)} -> 51944 | T2: {=VLOOKUP(Q2&R2,IF({1,0},$B$2:$B$330&$F$2:$F$330,$D$2:$D$330),2,)} -> 强度室 | U2: {=VLOOKUP(Q2&R2,IF({1,0},$B$2:$B$330&$F$2:$F$330,$E$2:$E$330),2,)} -> C929设计（2025年上飞院） | V2: {=VLOOKUP(Q2&R2,IF({1,0},$B$2:$B$330&$F$2:$F$330,$N$2:$N$330),2,)} -> YZ40000415
A3: =ROW()-1 -> 2 | B3: 徐丽娜 | C3: =IFERROR(VLOOKUP(B3,[66]工程研发事业部人员名单!B:D,2,0),"") -> 50079 | D3: =IFERROR(VLOOKUP(B3,[66]工程研发事业部人员名单!B:D,3,0),"") -> 工程项目室 /适航工程室 | E3: 项目开发与管控 | F3: =G3+H3+I3+J3 -> 50 | I3: 50 | K3: PMO | L3: 项目管理 | M3: C919基本型设计（2025年上飞院）： 1.上报项目月工时。 2.统计每月工时发生汇总，差旅发生费用，成本归集。 3.审签出差报销。 4.交付物存储地址建立。 5.编制并跟踪任务分解计划，协调处理项目进展问题。 6.协调项目人力资源。 7.与客户沟通项目任务清单、推动项目CSDB录入文件计划及存在的问题、损伤容限报告编制计划进展。 8.与客户沟通项目合同签订情况。 9.编制文件审签封面并组织实施。 | N3: =VLOOKUP(E3,订单号!B:C,2,0) -> #N/A | O3: =VLOOKUP(C3,领导干部!B:B,1,0) -> #N/A | Q3: 陈杰 | R3: 155 | S3: {=VLOOKUP(Q3&R3,IF({1,0},$B$2:$B$330&$F$2:$F$330,$C$2:$C$330),2,)} -> 25600 | T3: {=VLOOKUP(Q3&R3,IF({1,0},$B$2:$B$330&$F$2:$F$330,$D$2:$D$330),2,)} -> 结构二室 | U3: {=VLOOKUP(Q3&R3,IF({1,0},$B$2:$B$330&$F$2:$F$330,$E$2:$E$330),2,)} -> WH1项目结构强度综合 | V3: {=VLOOKUP(Q3&R3,IF({1,0},$B$2:$B$330&$F$2:$F$330,$N$2:$N$330),2,)} -> YZ-RD202428
A4: =ROW()-1 -> 3 | B4: 耿璐璐 | C4: =IFERROR(VLOOKUP(B4,[66]工程研发事业部人员名单!B:D,2,0),"") -> 51405 | D4: =IFERROR(VLOOKUP(B4,[66]工程研发事业部人员名单!B:D,3,0),"") -> 工程项目室 /适航工程室 | E4: 项目开发与管控 | F4: =G4+H4+I4+J4 -> 115 | I4: 115 | K4: PMO | L4: 项目管理 | M4: 1）1号-1.4设计：跟进合同进展情况； 2）C919YJTD：跟进项目进展，协调后机身工时认定，跟进合同立项情况等； 3）11号设计：跟进合同签订流程，完成两轮电子采购平台报价，编写合同文本、谈判记录及报价单； 4）完成集成研发业务域设计评审流程图、绩效指标表、流程清单等编制； 5）完成事业部驾驶舱PPT更新及业务场景需求数据表填写； 6）完成PMA流程梳理及可行性分析ppt，协助完成PMA件研制与取证费用预算； 7）机房/涉密台账管理，资产明细表更新，完成二季度纸质秘密载体台账/光磁介质秘密载体台账上报，内部载体移交。 | N4: =VLOOKUP(E4,订单号!B:C,2,0) -> #N/A | O4: =VLOOKUP(C4,领导干部!B:B,1,0) -> #N/A | Q4: 陈坤 | R4: 140 | S4: {=VLOOKUP(Q4&R4,IF({1,0},$B$2:$B$330&$F$2:$F$330,$C$2:$C$330),2,)} -> 51576 | T4: {=VLOOKUP(Q4&R4,IF({1,0},$B$2:$B$330&$F$2:$F$330,$D$2:$D$330),2,)} -> 联络工程室 | U4: {=VLOOKUP(Q4&R4,IF({1,0},$B$2:$B$330&$F$2:$F$330,$E$2:$E$330),2,)} -> 工程支持 | V4: {=VLOOKUP(Q4&R4,IF({1,0},$B$2:$B$330&$F$2:$F$330,$N$2:$N$330),2,)} -> 10502
A5: =ROW()-1 -> 4 | B5: 石荣荣 | C5: =IFERROR(VLOOKUP(B5,[66]工程研发事业部人员名单!B:D,2,0),"") -> 51166 | D5: =IFERROR(VLOOKUP(B5,[66]工程研发事业部人员名单!B:D,3,0),"") -> 工程项目室 /适航工程室 | E5: 项目开发与管控 | F5: =G5+H5+I5+J5 -> 150 | I5: 150 | K5: PMO | L5: 项目管理 | M5: 参加项目总师例会并作会议概要; 沟通协调我方和沈阳所工作衔接和人员衔接工作,协调已经入所人员安装软件解决电脑问题等工作; 梳理项目退所人员名单,组织填写退所手续,梳理退所所需机器号和key信息及收集蓝色工作证; 解决办公环境、生活(饭卡喝咖啡)等问题 完成6号-5项目，通过沈阳所结构部门内部预验收，组织完成项目交付物的准备及签字盖章 完成6号-5项目，通过沈阳所项目验收，并根据项目主管意见，组织完成项目交付物的整改及签字盖章 完成我公司在沈阳所供应商管理系统内资格解冻协调工作，并准备供应商整改资料 | N5: =VLOOKUP(E5,订单号!B:C,2,0) -> #N/A | O5: =VLOOKUP(C5,领导干部!B:B,1,0) -> #N/A | Q5: 陈磊 | R5: 170 | S5: {=VLOOKUP(Q5&R5,IF({1,0},$B$2:$B$330&$F$2:$F$330,$C$2:$C$330),2,)} -> 52180 | T5: {=VLOOKUP(Q5&R5,IF({1,0},$B$2:$B$330&$F$2:$F$330,$D$2:$D$330),2,)} -> 结构一室 | U5: {=VLOOKUP(Q5&R5,IF({1,0},$B$2:$B$330&$F$2:$F$330,$E$2:$E$330),2,)} -> C929设计（2025年上飞院） | V5: {=VLOOKUP(Q5&R5,IF({1,0},$B$2:$B$330&$F$2:$F$330,$N$2:$N$330),2,)} -> YZ40000415
A6: =ROW()-1 -> 5 | B6: 夏新鑫 | C6: =IFERROR(VLOOKUP(B6,[66]工程研发事业部人员名单!B:D,2,0),"") -> 50876 | D6: =IFERROR(VLOOKUP(B6,[66]工程研发事业部人员名单!B:D,3,0),"") -> 工程项目室 /适航工程室 | E6: 项目开发与管控 | F6: =G6+H6+I6+J6 -> 58 | I6: 58 | K6: PMO | L6: 项目管理 | M6: 完成商飞上岗培训框架协议合同签订；组织参加C929舱门周例会、月度汇报会；组织更新结构、强度专业用检查单等 | N6: =VLOOKUP(E6,订单号!B:C,2,0) -> #N/A | O6: =VLOOKUP(C6,领导干部!B:B,1,0) -> #N/A | Q6: 陈瑞东 | R6: 220 | S6: {=VLOOKUP(Q6&R6,IF({1,0},$B$2:$B$330&$F$2:$F$330,$C$2:$C$330),2,)} -> 51181 | T6: {=VLOOKUP(Q6&R6,IF({1,0},$B$2:$B$330&$F$2:$F$330,$D$2:$D$330),2,)} -> 强度室 | U6: {=VLOOKUP(Q6&R6,IF({1,0},$B$2:$B$330&$F$2:$F$330,$E$2:$E$330),2,)} -> C929设计（2025年上飞院） | V6: {=VLOOKUP(Q6&R6,IF({1,0},$B$2:$B$330&$F$2:$F$330,$N$2:$N$330),2,)} -> YZ40000415
A7: =ROW()-1 -> 6 | B7: 夏新鑫 | C7: =IFERROR(VLOOKUP(B7,[66]工程研发事业部人员名单!B:D,2,0),"") -> 50876 | D7: =IFERROR(VLOOKUP(B7,[66]工程研发事业部人员名单!B:D,3,0),"") -> 工程项目室 /适航工程室 | E7: 项目开发与管控 | F7: =G7+H7+I7+J7 -> 60 | I7: 60 | K7: PMO | L7: 项目管理 | M7: 组织参加C929垂尾、平尾周例会；完成复材中心验收评审补充工作并开具发票；沟通对接复材中心年度工作计划；组织更新结构、强度专业用检查单等 | N7: =VLOOKUP(E7,订单号!B:C,2,0) -> #N/A | O7: =VLOOKUP(C7,领导干部!B:B,1,0) -> #N/A | Q7: 晨曦 | R7: 98 | S7: {=VLOOKUP(Q7&R7,IF({1,0},$B$2:$B$330&$F$2:$F$330,$C$2:$C$330),2,)} -> 50030 | T7: {=VLOOKUP(Q7&R7,IF({1,0},$B$2:$B$330&$F$2:$F$330,$D$2:$D$330),2,)} -> 强度室 | U7: {=VLOOKUP(Q7&R7,IF({1,0},$B$2:$B$330&$F$2:$F$330,$E$2:$E$330),2,)} -> C919基本型设计（2025年上飞院） | V7: {=VLOOKUP(Q7&R7,IF({1,0},$B$2:$B$330&$F$2:$F$330,$N$2:$N$330),2,)} -> YZ40000419
A8: =ROW()-1 -> 7 | B8: 夏新鑫 | C8: =IFERROR(VLOOKUP(B8,[66]工程研发事业部人员名单!B:D,2,0),"") -> 50876 | D8: =IFERROR(VLOOKUP(B8,[66]工程研发事业部人员名单!B:D,3,0),"") -> 工程项目室 /适航工程室 | E8: 项目开发与管控 | F8: =G8+H8+I8+J8 -> 10 | I8: 10 | K8: PMO | L8: 项目管理 | M8: 沟通合同、设计输入、工作电脑等 | N8: =VLOOKUP(E8,订单号!B:C,2,0) -> #N/A | O8: =VLOOKUP(C8,领导干部!B:B,1,0) -> #N/A | Q8: 褚永鑫 | R8: 189 | S8: {=VLOOKUP(Q8&R8,IF({1,0},$B$2:$B$330&$F$2:$F$330,$C$2:$C$330),2,)} -> 22253 | T8: {=VLOOKUP(Q8&R8,IF({1,0},$B$2:$B$330&$F$2:$F$330,$D$2:$D$330),2,)} -> 联络工程室 | U8: {=VLOOKUP(Q8&R8,IF({1,0},$B$2:$B$330&$F$2:$F$330,$E$2:$E$330),2,)} -> 工程支持 | V8: {=VLOOKUP(Q8&R8,IF({1,0},$B$2:$B$330&$F$2:$F$330,$N$2:$N$330),2,)} -> 10502
A9: =ROW()-1 -> 8 | B9: 费天行 | C9: =IFERROR(VLOOKUP(B9,[66]工程研发事业部人员名单!B:D,2,0),"") -> 52570 | D9: =IFERROR(VLOOKUP(B9,[66]工程研发事业部人员名单!B:D,3,0),"") -> 工程项目室 /适航工程室 | E9: 项目开发与管控 | F9: =G9+H9+I9+J9 -> 30 | I9: 30 | K9: PMO | L9: 项目管理 | M9: 1.与甲方讨论商定技术协议的文本，项目的工作条目与工时量，跟踪进展 2.实时更新输入清单，记录工作交流过程 | N9: =VLOOKUP(E9,订单号!B:C,2,0) -> #N/A | O9: =VLOOKUP(C9,领导干部!B:B,1,0) -> #N/A | Q9: 丛家勇 | R9: 235 | S9: {=VLOOKUP(Q9&R9,IF({1,0},$B$2:$B$330&$F$2:$F$330,$C$2:$C$330),2,)} -> 50281 | T9: {=VLOOKUP(Q9&R9,IF({1,0},$B$2:$B$330&$F$2:$F$330,$D$2:$D$330),2,)} -> 结构一室 | U9: {=VLOOKUP(Q9&R9,IF({1,0},$B$2:$B$330&$F$2:$F$330,$E$2:$E$330),2,)} -> C929设计（2025年上飞院） | V9: {=VLOOKUP(Q9&R9,IF({1,0},$B$2:$B$330&$F$2:$F$330,$N$2:$N$330),2,)} -> YZ40000415
A10: =ROW()-1 -> 9 | B10: 费天行 | C10: =IFERROR(VLOOKUP(B10,[66]工程研发事业部人员名单!B:D,2,0),"") -> 52570 | D10: =IFERROR(VLOOKUP(B10,[66]工程研发事业部人员名单!B:D,3,0),"") -> 工程项目室 /适航工程室 | E10: 项目开发与管控 | F10: =G10+H10+I10+J10 -> 10 | I10: 10 | K10: PMO | L10: 项目管理 | M10: 1.跟踪甲方合同签订情况，项目进展 2.整理并和甲方确认结构识别工作量，形成验收单 | N10: =VLOOKUP(E10,订单号!B:C,2,0) -> #N/A | O10: =VLOOKUP(C10,领导干部!B:B,1,0) -> #N/A | Q10: 董晓莉 | R10: 155 | S10: {=VLOOKUP(Q10&R10,IF({1,0},$B$2:$B$330&$F$2:$F$330,$C$2:$C$330),2,)} -> 51211 | T10: {=VLOOKUP(Q10&R10,IF({1,0},$B$2:$B$330&$F$2:$F$330,$D$2:$D$330),2,)} -> 结构一室 | U10: {=VLOOKUP(Q10&R10,IF({1,0},$B$2:$B$330&$F$2:$F$330,$E$2:$E$330),2,)} -> WH1项目结构强度综合 | V10: {=VLOOKUP(Q10&R10,IF({1,0},$B$2:$B$330&$F$2:$F$330,$N$2:$N$330),2,)} -> YZ-RD202428
A11: =ROW()-1 -> 10 | B11: 徐丽娜 | C11: =IFERROR(VLOOKUP(B11,[66]工程研发事业部人员名单!B:D,2,0),"") -> 50079 | D11: =IFERROR(VLOOKUP(B11,[66]工程研发事业部人员名单!B:D,3,0),"") -> 工程项目室 /适航工程室 | E11: WH1项目总体/系统/适航等其它专业 | F11: =G11+H11+I11+J11 -> 30 | I11: 30 | K11: 适航 | M11: 无人机： 1.学习《高风险货运固定翼无人机系统适航标准》,审定基础（CB）初步梳理审核方法，梳理TP500型、UY-100 、翼龙-2气象型无人专用条件,梳理HY1701-HY1913章节 地址：\\192.168.10.140\newnas\data\yanfadata\WH1项目结构强度综合\05 其他工作包\14=适航管理\6月 | N11: =VLOOKUP(E11,订单号!B:C,2,0) -> YZ-RD202428 | O11: =VLOOKUP(C11,领导干部!B:B,1,0) -> #N/A | Q11: 杜洪雨 | R11: 220 | S11: {=VLOOKUP(Q11&R11,IF({1,0},$B$2:$B$330&$F$2:$F$330,$C$2:$C$330),2,)} -> 51170 | T11: {=VLOOKUP(Q11&R11,IF({1,0},$B$2:$B$330&$F$2:$F$330,$D$2:$D$330),2,)} -> 结构二室 | U11: {=VLOOKUP(Q11&R11,IF({1,0},$B$2:$B$330&$F$2:$F$330,$E$2:$E$330),2,)} -> C929设计（2025年上飞院） | V11: {=VLOOKUP(Q11&R11,IF({1,0},$B$2:$B$330&$F$2:$F$330,$N$2:$N$330),2,)} -> YZ40000415
A12: =ROW()-1 -> 11 | B12: 夏新鑫 | C12: =IFERROR(VLOOKUP(B12,[66]工程研发事业部人员名单!B:D,2,0),"") -> 50876 | D12: =IFERROR(VLOOKUP(B12,[66]工程研发事业部人员名单!B:D,3,0),"") -> 工程项目室 /适航工程室 | E12: WH1项目总体/系统/适航等其它专业 | F12: =G12+H12+I12+J12 -> 32 | I12: 32 | K12: 适航 | M12: 适航审定基础学习，交付物地址： \\192.168.10.140\newnas\data\yanfadata\WH1项目结构强度综合\05 其他工作包\14=适航管理\6月 | N12: =VLOOKUP(E12,订单号!B:C,2,0) -> YZ-RD202428 | O12: =VLOOKUP(C12,领导干部!B:B,1,0) -> #N/A | Q12: 付强 | R12: 164.88 | S12: {=VLOOKUP(Q12&R12,IF({1,0},$B$2:$B$330&$F$2:$F$330,$C$2:$C$330),2,)} -> 25549 | T12: {=VLOOKUP(Q12&R12,IF({1,0},$B$2:$B$330&$F$2:$F$330,$D$2:$D$330),2,)} -> 联络工程室 | U12: {=VLOOKUP(Q12&R12,IF({1,0},$B$2:$B$330&$F$2:$F$330,$E$2:$E$330),2,)} -> 工程支持 | V12: {=VLOOKUP(Q12&R12,IF({1,0},$B$2:$B$330&$F$2:$F$330,$N$2:$N$330),2,)} -> 10502
A13: =ROW()-1 -> 12 | B13: 石荣荣 | C13: =IFERROR(VLOOKUP(B13,[66]工程研发事业部人员名单!B:D,2,0),"") -> 51166 | D13: =IFERROR(VLOOKUP(B13,[66]工程研发事业部人员名单!B:D,3,0),"") -> 工程项目室 /适航工程室 | E13: WH1项目总体/系统/适航等其它专业 | F13: =G13+H13+I13+J13 -> 57 | I13: 57 | K13: 适航 | M13: 梳理适航条款，参加适航讨论会交付物在公共区\\192.168.10.140\newnas\data\yanfadata\WH1项目结构强度综合\05 其他工作包\14=适航管理\6月 | N13: =VLOOKUP(E13,订单号!B:C,2,0) -> YZ-RD202428 | O13: =VLOOKUP(C13,领导干部!B:B,1,0) -> #N/A | Q13: 付泉铭 | R13: 200 | S13: {=VLOOKUP(Q13&R13,IF({1,0},$B$2:$B$330&$F$2:$F$330,$C$2:$C$330),2,)} -> 51555 | T13: {=VLOOKUP(Q13&R13,IF({1,0},$B$2:$B$330&$F$2:$F$330,$D$2:$D$330),2,)} -> 联络工程室 | U13: {=VLOOKUP(Q13&R13,IF({1,0},$B$2:$B$330&$F$2:$F$330,$E$2:$E$330),2,)} -> SIA无人机设计-2 | V13: {=VLOOKUP(Q13&R13,IF({1,0},$B$2:$B$330&$F$2:$F$330,$N$2:$N$330),2,)} -> YZ40000422
A14: =ROW()-1 -> 13 | B14: 费天行 | C14: =IFERROR(VLOOKUP(B14,[66]工程研发事业部人员名单!B:D,2,0),"") -> 52570 | D14: =IFERROR(VLOOKUP(B14,[66]工程研发事业部人员名单!B:D,3,0),"") -> 工程项目室 /适航工程室 | E14: WH1项目总体/系统/适航等其它专业 | F14: =G14+H14+I14+J14 -> 60 | I14: 60 | K14: 适航 | M14: 讨论并编写审定基础，补充无人机专用条件与条款负责人专业，交付物已经放 \\192.168.10.140\newnas\data\yanfadata\WH1项目结构强度综合\05 其他工作包\14=适航管理\6月 | N14: =VLOOKUP(E14,订单号!B:C,2,0) -> YZ-RD202428 | O14: =VLOOKUP(C14,领导干部!B:B,1,0) -> #N/A | Q14: 付容容 | R14: 190 | S14: {=VLOOKUP(Q14&R14,IF({1,0},$B$2:$B$330&$F$2:$F$330,$C$2:$C$330),2,)} -> 51183 | T14: {=VLOOKUP(Q14&R14,IF({1,0},$B$2:$B$330&$F$2:$F$330,$D$2:$D$330),2,)} -> 结构一室 | U14: {=VLOOKUP(Q14&R14,IF({1,0},$B$2:$B$330&$F$2:$F$330,$E$2:$E$330),2,)} -> C929设计（2025年上飞院） | V14: {=VLOOKUP(Q14&R14,IF({1,0},$B$2:$B$330&$F$2:$F$330,$N$2:$N$330),2,)} -> YZ40000415
A15: =ROW()-1 -> 14 | B15: 耿璐璐 | C15: =IFERROR(VLOOKUP(B15,[66]工程研发事业部人员名单!B:D,2,0),"") -> 51405 | D15: =IFERROR(VLOOKUP(B15,[66]工程研发事业部人员名单!B:D,3,0),"") -> 工程项目室 /适航工程室 | E15: WH1项目总体/系统/适航等其它专业 | F15: =G15+H15+I15+J15 -> 30 | I15: 30 | K15: 适航 | M15: 大型固定翼货运无人机系统适航审定基础梳理，燃油、滑油、进排气系统适航条款研究，参加讨论会；适航学习交付物存放地址： \\192.168.10.140\newnas\data\yanfadata\WH1项目结构强度综合\05 其他工作包\14=适航管理 | N15: =VLOOKUP(E15,订单号!B:C,2,0) -> YZ-RD202428 | O15: =VLOOKUP(C15,领导干部!B:B,1,0) -> #N/A | Q15: 高秉芳 | R15: 166.68 | S15: {=VLOOKUP(Q15&R15,IF({1,0},$B$2:$B$330&$F$2:$F$330,$C$2:$C$330),2,)} -> 26688 | T15: {=VLOOKUP(Q15&R15,IF({1,0},$B$2:$B$330&$F$2:$F$330,$D$2:$D$330),2,)} -> 联络工程室 | U15: {=VLOOKUP(Q15&R15,IF({1,0},$B$2:$B$330&$F$2:$F$330,$E$2:$E$330),2,)} -> 工程支持 | V15: {=VLOOKUP(Q15&R15,IF({1,0},$B$2:$B$330&$F$2:$F$330,$N$2:$N$330),2,)} -> 10502
A16: =ROW()-1 -> 15 | B16: 吕冬兰 | C16: =IFERROR(VLOOKUP(B16,[66]工程研发事业部人员名单!B:D,2,0),"") -> 51160 | D16: =IFERROR(VLOOKUP(B16,[66]工程研发事业部人员名单!B:D,3,0),"") -> 综合技术室 | E16: 重点工作任务 | F16: =G16+H16+I16+J16 -> 15 | I16: 15 | K16: 材料及工艺 | L16: 贯彻民用航空高质量发展三年行动方案任务 | M16: 联系供应链和质量部获取试验项目报价，联系物流中心获取质保单和理化试验报告及库存量核实，联系采购部门询问材料价格，计算原材料价格 | N16: =VLOOKUP(E16,订单号!B:C,2,0) -> 0 | O16: =VLOOKUP(C16,领导干部!B:B,1,0) -> #N/A | Q16: 高奇 | R16: 157 | S16: {=VLOOKUP(Q16&R16,IF({1,0},$B$2:$B$330&$F$2:$F$330,$C$2:$C$330),2,)} -> 17732 | T16: {=VLOOKUP(Q16&R16,IF({1,0},$B$2:$B$330&$F$2:$F$330,$D$2:$D$330),2,)} -> 联络工程室 | U16: {=VLOOKUP(Q16&R16,IF({1,0},$B$2:$B$330&$F$2:$F$330,$E$2:$E$330),2,)} -> 工程支持 | V16: {=VLOOKUP(Q16&R16,IF({1,0},$B$2:$B$330&$F$2:$F$330,$N$2:$N$330),2,)} -> 10502
A17: =ROW()-1 -> 16 | B17: 朱海 | C17: =IFERROR(VLOOKUP(B17,[66]工程研发事业部人员名单!B:D,2,0),"") -> 52232 | D17: =IFERROR(VLOOKUP(B17,[66]工程研发事业部人员名单!B:D,3,0),"") -> 结构二室 | E17: 重点工作任务 | F17: =G17+H17+I17+J17 -> 48 | I17: 48 | K17: 结构 | L17: 贯彻民用航空高质量发展三年行动方案任务 | M17: 1.学习CATIA逆向工程曲面设计方法； 2.搜寻B737零件图纸。 | N17: =VLOOKUP(E17,订单号!B:C,2,0) -> 0 | O17: =VLOOKUP(C17,领导干部!B:B,1,0) -> #N/A | Q17: 葛春生 | R17: 120 | S17: {=VLOOKUP(Q17&R17,IF({1,0},$B$2:$B$330&$F$2:$F$330,$C$2:$C$330),2,)} -> 51410 | T17: {=VLOOKUP(Q17&R17,IF({1,0},$B$2:$B$330&$F$2:$F$330,$D$2:$D$330),2,)} -> 结构一室 | U17: {=VLOOKUP(Q17&R17,IF({1,0},$B$2:$B$330&$F$2:$F$330,$E$2:$E$330),2,)} -> WH1项目结构强度综合 | V17: {=VLOOKUP(Q17&R17,IF({1,0},$B$2:$B$330&$F$2:$F$330,$N$2:$N$330),2,)} -> YZ-RD202428
A18: =ROW()-1 -> 17 | B18: 孙永光 | C18: =IFERROR(VLOOKUP(B18,[66]工程研发事业部人员名单!B:D,2,0),"") -> 25601 | D18: =IFERROR(VLOOKUP(B18,[66]工程研发事业部人员名单!B:D,3,0),"") -> 联络工程室 | E18: 重点工作任务 | F18: =G18+H18+I18+J18 -> 48 | I18: 48 | K18: 结构 | L18: 贯彻民用航空高质量发展三年行动方案任务 | M18: 1.学习CATIA逆向工程曲面设计方法； 2.搜寻B737零件图纸。 | N18: =VLOOKUP(E18,订单号!B:C,2,0) -> 0 | O18: =VLOOKUP(C18,领导干部!B:B,1,0) -> #N/A | Q18: 耿璐璐 | R18: 115 | S18: {=VLOOKUP(Q18&R18,IF({1,0},$B$2:$B$330&$F$2:$F$330,$C$2:$C$330),2,)} -> 51405 | T18: {=VLOOKUP(Q18&R18,IF({1,0},$B$2:$B$330&$F$2:$F$330,$D$2:$D$330),2,)} -> 工程项目室 /适航工程室 | U18: {=VLOOKUP(Q18&R18,IF({1,0},$B$2:$B$330&$F$2:$F$330,$E$2:$E$330),2,)} -> 项目开发与管控 | V18: {=VLOOKUP(Q18&R18,IF({1,0},$B$2:$B$330&$F$2:$F$330,$N$2:$N$330),2,)} -> #N/A
A19: =ROW()-1 -> 18 | B19: 王健 | C19: =IFERROR(VLOOKUP(B19,[66]工程研发事业部人员名单!B:D,2,0),"") -> 51784 | D19: =IFERROR(VLOOKUP(B19,[66]工程研发事业部人员名单!B:D,3,0),"") -> 结构一室 | E19: 重点工作任务 | F19: =G19+H19+I19+J19 -> 7.5 | I19: 7.5 | K19: 结构 | L19: 贯彻民用航空高质量发展三年行动方案任务 | M19: 1、参加PMA取证讨论会； 2、协助完成PMA件费用测算。 | N19: =VLOOKUP(E19,订单号!B:C,2,0) -> 0 | O19: =VLOOKUP(C19,领导干部!B:B,1,0) -> #N/A | Q19: 郭静 | R19: 150.2 | S19: {=VLOOKUP(Q19&R19,IF({1,0},$B$2:$B$330&$F$2:$F$330,$C$2:$C$330),2,)} -> 50027 | T19: {=VLOOKUP(Q19&R19,IF({1,0},$B$2:$B$330&$F$2:$F$330,$D$2:$D$330),2,)} -> 联络工程室 | U19: {=VLOOKUP(Q19&R19,IF({1,0},$B$2:$B$330&$F$2:$F$330,$E$2:$E$330),2,)} -> 工程支持 | V19: {=VLOOKUP(Q19&R19,IF({1,0},$B$2:$B$330&$F$2:$F$330,$N$2:$N$330),2,)} -> 10502
A20: =ROW()-1 -> 19 | B20: 魏士礼 | C20: =IFERROR(VLOOKUP(B20,[66]工程研发事业部人员名单!B:D,2,0),"") -> 22294 | D20: =IFERROR(VLOOKUP(B20,[66]工程研发事业部人员名单!B:D,3,0),"") -> 结构一室 | E20: 8号-1.3设计 | F20: =G20+H20+I20+J20 -> 10 | I20: 10 | K20: 结构 | L20: 8号垂尾优化设计 | M20: 8-1.3垂尾中期评审报告和交付物优化 | N20: =VLOOKUP(E20,订单号!B:C,2,0) -> YZ40000414 | O20: =VLOOKUP(C20,领导干部!B:B,1,0) -> #N/A | Q20: 郭晓庆 | R20: 220 | S20: {=VLOOKUP(Q20&R20,IF({1,0},$B$2:$B$330&$F$2:$F$330,$C$2:$C$330),2,)} -> 50275 | T20: {=VLOOKUP(Q20&R20,IF({1,0},$B$2:$B$330&$F$2:$F$330,$D$2:$D$330),2,)} -> 结构一室 | U20: {=VLOOKUP(Q20&R20,IF({1,0},$B$2:$B$330&$F$2:$F$330,$E$2:$E$330),2,)} -> C929设计（2025年上飞院） | V20: {=VLOOKUP(Q20&R20,IF({1,0},$B$2:$B$330&$F$2:$F$330,$N$2:$N$330),2,)} -> YZ40000415
A21: =ROW()-1 -> 20 | B21: 杨春 | C21: =IFERROR(VLOOKUP(B21,[66]工程研发事业部人员名单!B:D,2,0),"") -> 51624 | D21: =IFERROR(VLOOKUP(B21,[66]工程研发事业部人员名单!B:D,3,0),"") -> 结构一室 | E21: 8号-1.3设计 | F21: =G21+H21+I21+J21 -> 2 | I21: 2 | K21: 结构 | L21: 8号垂尾优化设计 | M21: 8-1.3垂尾中期评审报告优化和交付物校对 | N21: =VLOOKUP(E21,订单号!B:C,2,0) -> YZ40000414 | O21: =VLOOKUP(C21,领导干部!B:B,1,0) -> #N/A | Q21: 何续斌 | R21: 190 | S21: {=VLOOKUP(Q21&R21,IF({1,0},$B$2:$B$330&$F$2:$F$330,$C$2:$C$330),2,)} -> 50871 | T21: {=VLOOKUP(Q21&R21,IF({1,0},$B$2:$B$330&$F$2:$F$330,$D$2:$D$330),2,)} -> 强度室 | U21: {=VLOOKUP(Q21&R21,IF({1,0},$B$2:$B$330&$F$2:$F$330,$E$2:$E$330),2,)} -> WH1项目结构强度综合 | V21: {=VLOOKUP(Q21&R21,IF({1,0},$B$2:$B$330&$F$2:$F$330,$N$2:$N$330),2,)} -> YZ-RD202428
A22: =ROW()-1 -> 21 | B22: 孟祥瑞 | C22: =IFERROR(VLOOKUP(B22,[66]工程研发事业部人员名单!B:D,2,0),"") -> 51615 | D22: =IFERROR(VLOOKUP(B22,[66]工程研发事业部人员名单!B:D,3,0),"") -> 结构一室 | E22: 8号-1.3设计 | F22: =G22+H22+I22+J22 -> 2 | I22: 2 | K22: 结构 | L22: 8号垂尾优化设计 | M22: 8-1.3垂尾中期评审报告优化和交付物校对 | N22: =VLOOKUP(E22,订单号!B:C,2,0) -> YZ40000414 | O22: =VLOOKUP(C22,领导干部!B:B,1,0) -> #N/A | Q22: 霍东旭 | R22: 180 | S22: {=VLOOKUP(Q22&R22,IF({1,0},$B$2:$B$330&$F$2:$F$330,$C$2:$C$330),2,)} -> 51941 | T22: {=VLOOKUP(Q22&R22,IF({1,0},$B$2:$B$330&$F$2:$F$330,$D$2:$D$330),2,)} -> 联络工程室 | U22: {=VLOOKUP(Q22&R22,IF({1,0},$B$2:$B$330&$F$2:$F$330,$E$2:$E$330),2,)} -> C919高原型设计（2025年上飞院） | V22: {=VLOOKUP(Q22&R22,IF({1,0},$B$2:$B$330&$F$2:$F$330,$N$2:$N$330),2,)} -> YZ40000417
A23: =ROW()-1 -> 22 | B23: 马岩 | C23: =IFERROR(VLOOKUP(B23,[66]工程研发事业部人员名单!B:D,2,0),"") -> 50730 | D23: =IFERROR(VLOOKUP(B23,[66]工程研发事业部人员名单!B:D,3,0),"") -> 结构一室 | E23: 8号-1.3设计 | F23: =G23+H23+I23+J23 -> 25 | J23: 25 | K23: 结构 | L23: 8号垂尾优化设计 | M23: 8号舱门及减重合同： 1.出差去汉中送减重合同 2.协助陕飞解决复材舱门问题、登机门安装调整问题 3.协助陕飞处理试验规划相关问题 | N23: =VLOOKUP(E23,订单号!B:C,2,0) -> YZ40000414 | O23: =VLOOKUP(C23,领导干部!B:B,1,0) -> #N/A | Q23: 纪可 | R23: 190 | S23: {=VLOOKUP(Q23&R23,IF({1,0},$B$2:$B$330&$F$2:$F$330,$C$2:$C$330),2,)} -> 26689 | T23: {=VLOOKUP(Q23&R23,IF({1,0},$B$2:$B$330&$F$2:$F$330,$D$2:$D$330),2,)} -> 强度室 | U23: {=VLOOKUP(Q23&R23,IF({1,0},$B$2:$B$330&$F$2:$F$330,$E$2:$E$330),2,)} -> C929设计（2025年上飞院） | V23: {=VLOOKUP(Q23&R23,IF({1,0},$B$2:$B$330&$F$2:$F$330,$N$2:$N$330),2,)} -> YZ40000415
A24: =ROW()-1 -> 23 | B24: 郑石 | C24: =IFERROR(VLOOKUP(B24,[66]工程研发事业部人员名单!B:D,2,0),"") -> 26766 | D24: =IFERROR(VLOOKUP(B24,[66]工程研发事业部人员名单!B:D,3,0),"") -> 强度室 | E24: C919YJTD设计 | F24: =G24+H24+I24+J24 -> 60 | I24: 60 | K24: 强度 | L24: 垂尾 | M24: 1.垂尾虚拟试验件根部接头垂向载荷对比分析，肋剖面载荷对比分析 2.垂尾试验件73框位置两种优化方案与原DFEM模型的垂向根部载荷对比 | N24: =VLOOKUP(E24,订单号!B:C,2,0) -> YZ40000410 | O24: =VLOOKUP(C24,领导干部!B:B,1,0) -> #N/A | Q24: 贾永亮 | R24: 180 | S24: {=VLOOKUP(Q24&R24,IF({1,0},$B$2:$B$330&$F$2:$F$330,$C$2:$C$330),2,)} -> 52131 | T24: {=VLOOKUP(Q24&R24,IF({1,0},$B$2:$B$330&$F$2:$F$330,$D$2:$D$330),2,)} -> 结构二室 | U24: {=VLOOKUP(Q24&R24,IF({1,0},$B$2:$B$330&$F$2:$F$330,$E$2:$E$330),2,)} -> C929设计（2025年上飞院） | V24: {=VLOOKUP(Q24&R24,IF({1,0},$B$2:$B$330&$F$2:$F$330,$N$2:$N$330),2,)} -> YZ40000415
A25: =ROW()-1 -> 24 | B25: 晨曦 | C25: =IFERROR(VLOOKUP(B25,[66]工程研发事业部人员名单!B:D,2,0),"") -> 50030 | D25: =IFERROR(VLOOKUP(B25,[66]工程研发事业部人员名单!B:D,3,0),"") -> 强度室 | E25: C919YJTD设计 | F25: =G25+H25+I25+J25 -> 92 | I25: 92 | K25: 强度 | L25: 垂尾 | M25: 1.垂尾根部试验件细节有限元模型建模 2.垂尾根部试验件加载、边界约束、试算。根部接头载荷对比与问题分析。 3.垂尾虚拟试验件方案二有限元模型修改与试算。 | N25: =VLOOKUP(E25,订单号!B:C,2,0) -> YZ40000410 | O25: =VLOOKUP(C25,领导干部!B:B,1,0) -> #N/A | Q25: 焦凯 | R25: 170 | S25: {=VLOOKUP(Q25&R25,IF({1,0},$B$2:$B$330&$F$2:$F$330,$C$2:$C$330),2,)} -> 52342 | T25: {=VLOOKUP(Q25&R25,IF({1,0},$B$2:$B$330&$F$2:$F$330,$D$2:$D$330),2,)} -> 强度室 | U25: {=VLOOKUP(Q25&R25,IF({1,0},$B$2:$B$330&$F$2:$F$330,$E$2:$E$330),2,)} -> WH1项目结构强度综合 | V25: {=VLOOKUP(Q25&R25,IF({1,0},$B$2:$B$330&$F$2:$F$330,$N$2:$N$330),2,)} -> YZ-RD202428
A26: =ROW()-1 -> 25 | B26: 郑石 | C26: =IFERROR(VLOOKUP(B26,[66]工程研发事业部人员名单!B:D,2,0),"") -> 26766 | D26: =IFERROR(VLOOKUP(B26,[66]工程研发事业部人员名单!B:D,3,0),"") -> 强度室 | E26: C919YJTD设计 | F26: =G26+H26+I26+J26 -> 20 | I26: 20 | K26: 强度 | L26: 后机身 | M26: 919后机身许用值更新，协调任务分配，校核分析结果，汇总裕度变化情况 | N26: =VLOOKUP(E26,订单号!B:C,2,0) -> YZ40000410 | O26: =VLOOKUP(C26,领导干部!B:B,1,0) -> #N/A | Q26: 靳海丰 | R26: 200 | S26: {=VLOOKUP(Q26&R26,IF({1,0},$B$2:$B$330&$F$2:$F$330,$C$2:$C$330),2,)} -> 51158 | T26: {=VLOOKUP(Q26&R26,IF({1,0},$B$2:$B$330&$F$2:$F$330,$D$2:$D$330),2,)} -> 强度室 | U26: {=VLOOKUP(Q26&R26,IF({1,0},$B$2:$B$330&$F$2:$F$330,$E$2:$E$330),2,)} -> C929设计（2025年上飞院） | V26: {=VLOOKUP(Q26&R26,IF({1,0},$B$2:$B$330&$F$2:$F$330,$N$2:$N$330),2,)} -> YZ40000415
A27: =ROW()-1 -> 26 | B27: 祝堃 | C27: =IFERROR(VLOOKUP(B27,[66]工程研发事业部人员名单!B:D,2,0),"") -> 52256 | D27: =IFERROR(VLOOKUP(B27,[66]工程研发事业部人员名单!B:D,3,0),"") -> 强度室 | E27: C919YJTD设计 | F27: =G27+H27+I27+J27 -> 10 | I27: 10 | K27: 强度 | L27: 后机身 | M27: 919后机身泄压报告前后段对接、后机身与中后机身对接、77-78框部分工具与报告内容校对 | N27: =VLOOKUP(E27,订单号!B:C,2,0) -> YZ40000410 | O27: =VLOOKUP(C27,领导干部!B:B,1,0) -> #N/A | Q27: 康霞 | R27: 125 | S27: {=VLOOKUP(Q27&R27,IF({1,0},$B$2:$B$330&$F$2:$F$330,$C$2:$C$330),2,)} -> 52132 | T27: {=VLOOKUP(Q27&R27,IF({1,0},$B$2:$B$330&$F$2:$F$330,$D$2:$D$330),2,)} -> 结构二室 | U27: {=VLOOKUP(Q27&R27,IF({1,0},$B$2:$B$330&$F$2:$F$330,$E$2:$E$330),2,)} -> SIA无人机设计-2 | V27: {=VLOOKUP(Q27&R27,IF({1,0},$B$2:$B$330&$F$2:$F$330,$N$2:$N$330),2,)} -> YZ40000422
A28: =ROW()-1 -> 27 | B28: 张文静 | C28: =IFERROR(VLOOKUP(B28,[66]工程研发事业部人员名单!B:D,2,0),"") -> 22259 | D28: =IFERROR(VLOOKUP(B28,[66]工程研发事业部人员名单!B:D,3,0),"") -> 强度室 | E28: C919YJTD设计 | F28: =G28+H28+I28+J28 -> 15 | I28: 15 | K28: 强度 | L28: 后机身 | M28: 919泄压报告球面框、平尾开口加强梁和74-76框部分工具与报告内容校核 | N28: =VLOOKUP(E28,订单号!B:C,2,0) -> YZ40000410 | O28: =VLOOKUP(C28,领导干部!B:B,1,0) -> #N/A | Q28: 康志明 | R28: 190 | S28: {=VLOOKUP(Q28&R28,IF({1,0},$B$2:$B$330&$F$2:$F$330,$C$2:$C$330),2,)} -> 25765 | T28: {=VLOOKUP(Q28&R28,IF({1,0},$B$2:$B$330&$F$2:$F$330,$D$2:$D$330),2,)} -> 结构一室 | U28: {=VLOOKUP(Q28&R28,IF({1,0},$B$2:$B$330&$F$2:$F$330,$E$2:$E$330),2,)} -> C929设计（2025年上飞院） | V28: {=VLOOKUP(Q28&R28,IF({1,0},$B$2:$B$330&$F$2:$F$330,$N$2:$N$330),2,)} -> YZ40000415
A29: =ROW()-1 -> 28 | B29: 刘媛媛 | C29: =IFERROR(VLOOKUP(B29,[66]工程研发事业部人员名单!B:D,2,0),"") -> 51385 | D29: =IFERROR(VLOOKUP(B29,[66]工程研发事业部人员名单!B:D,3,0),"") -> 系统室 | E29: C919YJTD设计 | F29: =G29+H29+I29+J29 -> 17.5 | I29: 17.5 | K29: 强度 | L29: 后机身 | M29: 919后机身许用值更新，77-78框拉压剪许用值受影响工具更新；挤压许用值受影响工具更新 | N29: =VLOOKUP(E29,订单号!B:C,2,0) -> YZ40000410 | O29: =VLOOKUP(C29,领导干部!B:B,1,0) -> #N/A | Q29: 李爱环 | R29: 200 | S29: {=VLOOKUP(Q29&R29,IF({1,0},$B$2:$B$330&$F$2:$F$330,$C$2:$C$330),2,)} -> 50726 | T29: {=VLOOKUP(Q29&R29,IF({1,0},$B$2:$B$330&$F$2:$F$330,$D$2:$D$330),2,)} -> 强度室 | U29: {=VLOOKUP(Q29&R29,IF({1,0},$B$2:$B$330&$F$2:$F$330,$E$2:$E$330),2,)} -> C929设计（2025年上飞院） | V29: {=VLOOKUP(Q29&R29,IF({1,0},$B$2:$B$330&$F$2:$F$330,$N$2:$N$330),2,)} -> YZ40000415
A30: =ROW()-1 -> 29 | B30: 宋凯 | C30: =IFERROR(VLOOKUP(B30,[66]工程研发事业部人员名单!B:D,2,0),"") -> 51951 | D30: =IFERROR(VLOOKUP(B30,[66]工程研发事业部人员名单!B:D,3,0),"") -> 系统室 | E30: C919YJTD设计 | F30: =G30+H30+I30+J30 -> 20 | I30: 20 | K30: 强度 | L30: 后机身 | M30: 919后机身许用值更新，74-76框拉压剪、拉脱和层间、挤压等许用值受影响的工具更新 | N30: =VLOOKUP(E30,订单号!B:C,2,0) -> YZ40000410 | O30: =VLOOKUP(C30,领导干部!B:B,1,0) -> #N/A | Q30: 李金鹰 | R30: 180 | S30: {=VLOOKUP(Q30&R30,IF({1,0},$B$2:$B$330&$F$2:$F$330,$C$2:$C$330),2,)} -> 51227 | T30: {=VLOOKUP(Q30&R30,IF({1,0},$B$2:$B$330&$F$2:$F$330,$D$2:$D$330),2,)} -> 结构一室 | U30: {=VLOOKUP(Q30&R30,IF({1,0},$B$2:$B$330&$F$2:$F$330,$E$2:$E$330),2,)} -> C929设计（2025年上飞院） | V30: {=VLOOKUP(Q30&R30,IF({1,0},$B$2:$B$330&$F$2:$F$330,$N$2:$N$330),2,)} -> YZ40000415
A31: =ROW()-1 -> 30 | B31: 任斌 | C31: =IFERROR(VLOOKUP(B31,[66]工程研发事业部人员名单!B:D,2,0),"") -> 51517 | D31: =IFERROR(VLOOKUP(B31,[66]工程研发事业部人员名单!B:D,3,0),"") -> 系统室 | E31: C919YJTD设计 | F31: =G31+H31+I31+J31 -> 6 | I31: 6 | K31: 强度 | L31: 后机身 | M31: 919后机身许用值更新，前后段对接和平尾开口加强梁结构挤压许用值受影响的工具更新 | N31: =VLOOKUP(E31,订单号!B:C,2,0) -> YZ40000410 | O31: =VLOOKUP(C31,领导干部!B:B,1,0) -> #N/A | Q31: 李其鹏 | R31: 70 | S31: {=VLOOKUP(Q31&R31,IF({1,0},$B$2:$B$330&$F$2:$F$330,$C$2:$C$330),2,)} -> 51429 | T31: {=VLOOKUP(Q31&R31,IF({1,0},$B$2:$B$330&$F$2:$F$330,$D$2:$D$330),2,)} -> 综合技术室 | U31: {=VLOOKUP(Q31&R31,IF({1,0},$B$2:$B$330&$F$2:$F$330,$E$2:$E$330),2,)} -> WH1项目结构强度综合 | V31: {=VLOOKUP(Q31&R31,IF({1,0},$B$2:$B$330&$F$2:$F$330,$N$2:$N$330),2,)} -> YZ-RD202428
A32: =ROW()-1 -> 31 | B32: 夏雷 | C32: =IFERROR(VLOOKUP(B32,[66]工程研发事业部人员名单!B:D,2,0),"") -> 52587 | D32: =IFERROR(VLOOKUP(B32,[66]工程研发事业部人员名单!B:D,3,0),"") -> 系统室 | E32: C919YJTD设计 | F32: =G32+H32+I32+J32 -> 20 | I32: 20 | K32: 强度 | L32: 后机身 | M32: 919后机身许用值更新，前段壁板拉压剪、拉脱和层间、挤压等许用值受影响的工具更新 | N32: =VLOOKUP(E32,订单号!B:C,2,0) -> YZ40000410 | O32: =VLOOKUP(C32,领导干部!B:B,1,0) -> #N/A | Q32: 李森 | R32: 135 | S32: {=VLOOKUP(Q32&R32,IF({1,0},$B$2:$B$330&$F$2:$F$330,$C$2:$C$330),2,)} -> 17238 | T32: {=VLOOKUP(Q32&R32,IF({1,0},$B$2:$B$330&$F$2:$F$330,$D$2:$D$330),2,)} -> 结构二室 | U32: {=VLOOKUP(Q32&R32,IF({1,0},$B$2:$B$330&$F$2:$F$330,$E$2:$E$330),2,)} -> WH1项目结构强度综合 | V32: {=VLOOKUP(Q32&R32,IF({1,0},$B$2:$B$330&$F$2:$F$330,$N$2:$N$330),2,)} -> YZ-RD202428
A33: =ROW()-1 -> 32 | B33: 赵子维 | C33: =IFERROR(VLOOKUP(B33,[66]工程研发事业部人员名单!B:D,2,0),"") -> 52585 | D33: =IFERROR(VLOOKUP(B33,[66]工程研发事业部人员名单!B:D,3,0),"") -> 系统室 | E33: C919YJTD设计 | F33: =G33+H33+I33+J33 -> 5.5 | I33: 5.5 | K33: 强度 | L33: 后机身 | M33: 919后机身许用值更新，平尾开口加强梁结构挤压许用值更新受影响工具更新 | N33: =VLOOKUP(E33,订单号!B:C,2,0) -> YZ40000410 | O33: =VLOOKUP(C33,领导干部!B:B,1,0) -> #N/A | Q33: 李守玺 | R33: 210 | S33: {=VLOOKUP(Q33&R33,IF({1,0},$B$2:$B$330&$F$2:$F$330,$C$2:$C$330),2,)} -> 25763 | T33: {=VLOOKUP(Q33&R33,IF({1,0},$B$2:$B$330&$F$2:$F$330,$D$2:$D$330),2,)} -> 结构一室 | U33: {=VLOOKUP(Q33&R33,IF({1,0},$B$2:$B$330&$F$2:$F$330,$E$2:$E$330),2,)} -> SIA无人机设计-2 | V33: {=VLOOKUP(Q33&R33,IF({1,0},$B$2:$B$330&$F$2:$F$330,$N$2:$N$330),2,)} -> YZ40000422
A34: =ROW()-1 -> 33 | B34: 魏春生 | C34: =IFERROR(VLOOKUP(B34,[66]工程研发事业部人员名单!B:D,2,0),"") -> 51389 | D34: =IFERROR(VLOOKUP(B34,[66]工程研发事业部人员名单!B:D,3,0),"") -> 系统室 | E34: C919YJTD设计 | F34: =G34+H34+I34+J34 -> 5.5 | I34: 5.5 | K34: 强度 | L34: 后机身 | M34: 919后机身许用值更新，后机身与中后机身对接挤压许用值更新受影响工具更新 | N34: =VLOOKUP(E34,订单号!B:C,2,0) -> YZ40000410 | O34: =VLOOKUP(C34,领导干部!B:B,1,0) -> #N/A | Q34: 李湘芝 | R34: 168.05 | S34: {=VLOOKUP(Q34&R34,IF({1,0},$B$2:$B$330&$F$2:$F$330,$C$2:$C$330),2,)} -> 50019 | T34: {=VLOOKUP(Q34&R34,IF({1,0},$B$2:$B$330&$F$2:$F$330,$D$2:$D$330),2,)} -> 联络工程室 | U34: {=VLOOKUP(Q34&R34,IF({1,0},$B$2:$B$330&$F$2:$F$330,$E$2:$E$330),2,)} -> 工程支持 | V34: {=VLOOKUP(Q34&R34,IF({1,0},$B$2:$B$330&$F$2:$F$330,$N$2:$N$330),2,)} -> 10502
A35: =ROW()-1 -> 34 | B35: 赵艳秦 | C35: =IFERROR(VLOOKUP(B35,[66]工程研发事业部人员名单!B:D,2,0),"") -> 50022 | D35: =IFERROR(VLOOKUP(B35,[66]工程研发事业部人员名单!B:D,3,0),"") -> 结构二室 | E35: C919YJTD设计 | F35: =G35+H35+I35+J35 -> 210 | I35: 210 | K35: 结构 | L35: 后机身/垂尾 | M35: 后机身组件P产数模注释更改，共计27个组件，多个零件设计更改，3个实验组件更改；垂尾新增加框根部试验件，PT20垂尾试验组件设计更改 | N35: =VLOOKUP(E35,订单号!B:C,2,0) -> YZ40000410 | O35: =VLOOKUP(C35,领导干部!B:B,1,0) -> #N/A | Q35: 李妍 | R35: 120 | S35: {=VLOOKUP(Q35&R35,IF({1,0},$B$2:$B$330&$F$2:$F$330,$C$2:$C$330),2,)} -> 51435 | T35: {=VLOOKUP(Q35&R35,IF({1,0},$B$2:$B$330&$F$2:$F$330,$D$2:$D$330),2,)} -> 系统室 | U35: {=VLOOKUP(Q35&R35,IF({1,0},$B$2:$B$330&$F$2:$F$330,$E$2:$E$330),2,)} -> C919基本型设计（2025年上飞院） | V35: {=VLOOKUP(Q35&R35,IF({1,0},$B$2:$B$330&$F$2:$F$330,$N$2:$N$330),2,)} -> YZ40000419
... A63: =ROW()-1 -> 62 | B63: 赵婷 | C63: =IFERROR(VLOOKUP(B63,[66]工程研发事业部人员名单!B:D,2,0),"") -> 50702 | D63: =IFERROR(VLOOKUP(B63,[66]工程研发事业部人员名单!B:D,3,0),"") -> 总体室 | E63: C919基本型设计（2025年上飞院） | F63: =G63+H63+I63+J63 -> 52 | I63: 52 | K63: 强度 | L63: C919手册2025年 | M63: 26份报告手册文件对比 | N63: =VLOOKUP(E63,订单号!B:C,2,0) -> YZ40000419 | O63: =VLOOKUP(C63,领导干部!B:B,1,0) -> #N/A | Q63: 孟玲俊 | R63: 120 | S63: {=VLOOKUP(Q63&R63,IF({1,0},$B$2:$B$330&$F$2:$F$330,$C$2:$C$330),2,)} -> 22298 | T63: {=VLOOKUP(Q63&R63,IF({1,0},$B$2:$B$330&$F$2:$F$330,$D$2:$D$330),2,)} -> 结构二室 | U63: {=VLOOKUP(Q63&R63,IF({1,0},$B$2:$B$330&$F$2:$F$330,$E$2:$E$330),2,)} -> C929设计（2025年上飞院） | V63: {=VLOOKUP(Q63&R63,IF({1,0},$B$2:$B$330&$F$2:$F$330,$N$2:$N$330),2,)} -> YZ40000415
A64: =ROW()-1 -> 63 | B64: 吴晓莉 | C64: =IFERROR(VLOOKUP(B64,[66]工程研发事业部人员名单!B:D,2,0),"") -> 50872 | D64: =IFERROR(VLOOKUP(B64,[66]工程研发事业部人员名单!B:D,3,0),"") -> 系统室 | E64: C919手册优化（2025年复材中心） | F64: =G64+H64+I64+J64 -> 91 | I64: 91 | K64: 系统 | M64: 1.1 CSDB三方线上会议一次-2h 1.2 CSDB三方线线上会议，问题梳理及对解答的整理-2h 1.3 CSDB内部培训会议一次-2h 2.1 梳理自己45份文件的警戒、警戒、警示、注意命令，并删除同类项，识别相似项并就近标记-2h 2.2 梳理复材组（5人合并后）的警戒、警戒、警示、注意命令，并删除同类项，识别相似项并就近标记-2h 2.3 梳理金属组和复材组的警戒、警戒、警示、注意命令，并删除同类项，识别相似项并就近标记，提交给上飞院，作为资源库录入的输入-2h 3 按录入操作具体情况，更新录入样例两份PPT-2h 4.1 与上飞院、金属组沟通图片库命名事项及具体问题讨论-8h 4.2 组织对Arbortext IsoDraw 7.3版本的转化，降为7.2版本-1h 4.3 6月份复材中心预计陆续发放87份文件，统计87份文件对应信息及对应人员，方便个人进行识别，下载自己相关8份已发布文件，并对图片进行版本识别，确认是7.2版本，7.3版本的继续转化成7.2版本-8h 4.4 按上飞院刘馨阳的要求，更改word文件中的图号，重新生成一版更改后的word文件，作为录入的基础（涉及重命名的文件20份）-16h 4.5 识别复材允许损伤的共用图，并标记-4h 4.6 统计金属复材共用SNS信息，与金属共同确认流水号的起始信息-2h 4.7 按上飞院刘馨阳的要求，一个SNS中进行流水编号的原则，对自己负责的45份文件进行流水编号（初步编号），并填写名称、格式、在文中位置等相关信息，共计338项信息统计-24 5.开展录入工作完成14份文件的录入（图片除外）-14h | N64: =VLOOKUP(E64,订单号!B:C,2,0) -> YZ40000416 | O64: =VLOOKUP(C64,领导干部!B:B,1,0) -> #N/A | Q64: 孟维宇 | R64: 210 | S64: {=VLOOKUP(Q64&R64,IF({1,0},$B$2:$B$330&$F$2:$F$330,$C$2:$C$330),2,)} -> 50722 | T64: {=VLOOKUP(Q64&R64,IF({1,0},$B$2:$B$330&$F$2:$F$330,$D$2:$D$330),2,)} -> 强度室 | U64: {=VLOOKUP(Q64&R64,IF({1,0},$B$2:$B$330&$F$2:$F$330,$E$2:$E$330),2,)} -> C929设计（2025年上飞院） | V64: {=VLOOKUP(Q64&R64,IF({1,0},$B$2:$B$330&$F$2:$F$330,$N$2:$N$330),2,)} -> YZ40000415
A65: =ROW()-1 -> 64 | B65: 魏春生 | C65: =IFERROR(VLOOKUP(B65,[66]工程研发事业部人员名单!B:D,2,0),"") -> 51389 | D65: =IFERROR(VLOOKUP(B65,[66]工程研发事业部人员名单!B:D,3,0),"") -> 系统室 | E65: C919手册优化（2025年复材中心） | F65: =G65+H65+I65+J65 -> 62 | I65: 62 | K65: 系统 | M65: 1.CSDB三方线线上会议，问题梳理及对解答的整理-2h 2.CSDB内部培训会议一次-2h 3.梳理自己27份文件的警戒、警戒、警示、注意命令，并删除同类项，识别相似项并就近标记-1h； 4.开展文件录入工作，完成16份文件的录入（图片除外）-8h； 5.完成12份文件的图片与ISO文件对比一致性-8h； 6.更改12份文件中的图号，重新生成一版更改后的word文件，作为录入的基础-8h； 7.识别复材允许损伤的共用图，并标记-3h； 8.一个SNS中进行流水编号的原则，对自己负责的27份文件进行流水编号（初步编号），并填写名称、格式、在文中位置等相关信息-15h； 9.完成12份技术文件中ISO图片增加热点的工作-15h | N65: =VLOOKUP(E65,订单号!B:C,2,0) -> YZ40000416 | O65: =VLOOKUP(C65,领导干部!B:B,1,0) -> #N/A | Q65: 孟祥瑞 | R65: 200 | S65: {=VLOOKUP(Q65&R65,IF({1,0},$B$2:$B$330&$F$2:$F$330,$C$2:$C$330),2,)} -> 51615 | T65: {=VLOOKUP(Q65&R65,IF({1,0},$B$2:$B$330&$F$2:$F$330,$D$2:$D$330),2,)} -> 结构一室 | U65: {=VLOOKUP(Q65&R65,IF({1,0},$B$2:$B$330&$F$2:$F$330,$E$2:$E$330),2,)} -> C929设计（2025年上飞院） | V65: {=VLOOKUP(Q65&R65,IF({1,0},$B$2:$B$330&$F$2:$F$330,$N$2:$N$330),2,)} -> YZ40000415
A66: =ROW()-1 -> 65 | B66: 赵子维 | C66: =IFERROR(VLOOKUP(B66,[66]工程研发事业部人员名单!B:D,2,0),"") -> 52585 | D66: =IFERROR(VLOOKUP(B66,[66]工程研发事业部人员名单!B:D,3,0),"") -> 系统室 | E66: C919手册优化（2025年复材中心） | F66: =G66+H66+I66+J66 -> 65 | I66: 65 | K66: 系统 | M66: 1.CSDB三方线线上会议，问题梳理及对解答的整理-2h 2.CSDB内部培训会议一次-2h 3.梳理自己48份文件的警戒、警戒、警示、注意命令，并删除同类项，识别相似项并就近标记-2h； 4.开展文件录入工作，完成21份文件的录入（图片除外）-9h； 5.Arbortext IsoDraw 7.3版本的转化，降为7.2版本-1h 6.完成21份文件的图片与ISO文件对比一致性-9h； 7.更改9份文件中的图号，重新生成一版更改后的word文件，作为录入的基础-8h； 8.识别复材允许损伤的共用图，并标记-3h； 9.一个SNS中进行流水编号的原则，对自己负责的48份文件进行流水编号（初步编号），并填写名称、格式、在文中位置等相关信息-17h； 10.完成9份技术文件中ISO图片增加热点的工作-12h | N66: =VLOOKUP(E66,订单号!B:C,2,0) -> YZ40000416 | O66: =VLOOKUP(C66,领导干部!B:B,1,0) -> #N/A | Q66: 牛福春 | R66: 155 | S66: {=VLOOKUP(Q66&R66,IF({1,0},$B$2:$B$330&$F$2:$F$330,$C$2:$C$330),2,)} -> 50710 | T66: {=VLOOKUP(Q66&R66,IF({1,0},$B$2:$B$330&$F$2:$F$330,$D$2:$D$330),2,)} -> 结构二室 | U66: {=VLOOKUP(Q66&R66,IF({1,0},$B$2:$B$330&$F$2:$F$330,$E$2:$E$330),2,)} -> WH1项目结构强度综合 | V66: {=VLOOKUP(Q66&R66,IF({1,0},$B$2:$B$330&$F$2:$F$330,$N$2:$N$330),2,)} -> YZ-RD202428
A67: =ROW()-1 -> 66 | B67: 夏雷 | C67: =IFERROR(VLOOKUP(B67,[66]工程研发事业部人员名单!B:D,2,0),"") -> 52587 | D67: =IFERROR(VLOOKUP(B67,[66]工程研发事业部人员名单!B:D,3,0),"") -> 系统室 | E67: C919手册优化（2025年复材中心） | F67: =G67+H67+I67+J67 -> 62 | I67: 62 | K67: 系统 | M67: 1.CSDB三方线线上会议，问题梳理及对解答的整理-2h 2.CSDB内部培训会议一次-2h 3.梳理自己42份文件的警戒、警戒、警示、注意命令，并删除同类项，识别相似项并就近标记-1h； 4.开展文件录入工作，完成16份文件的录入（图片除外）-8h； 5.完成42份文件的图片与ISO文件对比一致性-8h； 6.更改10份文件中的图号，重新生成一版更改后的word文件，作为录入的基础-8h； 7.识别复材允许损伤的共用图，并标记-3h； 8.一个SNS中进行流水编号的原则，对自己负责的42份文件进行流水编号（初步编号），并填写名称、格式、在文中位置等相关信息-17h； 9.完成12份技术文件中ISO图片增加热点的工作-13h | N67: =VLOOKUP(E67,订单号!B:C,2,0) -> YZ40000416 | O67: =VLOOKUP(C67,领导干部!B:B,1,0) -> #N/A | Q67: 牛建庄 | R67: 194 | S67: {=VLOOKUP(Q67&R67,IF({1,0},$B$2:$B$330&$F$2:$F$330,$C$2:$C$330),2,)} -> 17090 | T67: {=VLOOKUP(Q67&R67,IF({1,0},$B$2:$B$330&$F$2:$F$330,$D$2:$D$330),2,)} -> 联络工程室 | U67: {=VLOOKUP(Q67&R67,IF({1,0},$B$2:$B$330&$F$2:$F$330,$E$2:$E$330),2,)} -> 工程支持 | V67: {=VLOOKUP(Q67&R67,IF({1,0},$B$2:$B$330&$F$2:$F$330,$N$2:$N$330),2,)} -> 10502
A68: =ROW()-1 -> 67 | B68: 刘媛媛 | C68: =IFERROR(VLOOKUP(B68,[66]工程研发事业部人员名单!B:D,2,0),"") -> 51385 | D68: =IFERROR(VLOOKUP(B68,[66]工程研发事业部人员名单!B:D,3,0),"") -> 系统室 | E68: C919手册优化（2025年复材中心） | F68: =G68+H68+I68+J68 -> 59 | I68: 59 | K68: 系统 | M68: 1.CSDB三方线线上会议，问题梳理及对解答的整理-2h 2.CSDB内部培训会议一次-2h 3.梳理自己40份文件的警戒、警戒、警示、注意命令，并删除同类项，识别相似项并就近标记-1h； 4.开展文件录入工作，完成22份文件的录入（图片除外）-8h； 5.完成40份文件的图片与ISO文件对比一致性-8h； 6.更改17份文件中的图号，重新生成一版更改后的word文件，作为录入的基础-8h； 7.识别复材允许损伤的共用图，并标记-3h； 8.一个SNS中进行流水编号的原则，对自己负责的40份文件进行流水编号（初步编号），并填写名称、格式、在文中位置等相关信息-17h； 9.完成9份技术文件中ISO图片增加热点的工作-10h | N68: =VLOOKUP(E68,订单号!B:C,2,0) -> YZ40000416 | O68: =VLOOKUP(C68,领导干部!B:B,1,0) -> #N/A | Q68: 潘英 | R68: 120 | S68: {=VLOOKUP(Q68&R68,IF({1,0},$B$2:$B$330&$F$2:$F$330,$C$2:$C$330),2,)} -> 50864 | T68: {=VLOOKUP(Q68&R68,IF({1,0},$B$2:$B$330&$F$2:$F$330,$D$2:$D$330),2,)} -> 综合技术室 | U68: {=VLOOKUP(Q68&R68,IF({1,0},$B$2:$B$330&$F$2:$F$330,$E$2:$E$330),2,)} -> C919高原型设计（2025年上飞院） | V68: {=VLOOKUP(Q68&R68,IF({1,0},$B$2:$B$330&$F$2:$F$330,$N$2:$N$330),2,)} -> YZ40000417
A69: =ROW()-1 -> 68 | B69: 王琛 | C69: =IFERROR(VLOOKUP(B69,[66]工程研发事业部人员名单!B:D,2,0),"") -> 22291 | D69: =IFERROR(VLOOKUP(B69,[66]工程研发事业部人员名单!B:D,3,0),"") -> 综合技术室 | E69: C919高原型设计（2025年上飞院） | F69: =G69+H69+I69+J69 -> 200 | I69: 200 | K69: 其他 | M69: 1、编制： C919-A-53-40-08-01A-04CA-A 机身-中机身-隔框-结构识别 C919-A-53-40-71-01A-04CA-A 机身-中机身-前部整流罩面板-结构识别 C919-A-53-40-71-04A-04CA-A 机身-中机身-后部整流罩面板-结构识别 C919-A-57-54-70-01A-04CA-A 机翼-襟翼机构-滑轨-结构识别 2、校对： C919-A-57-41-01-02A-04CA-A 机翼-固定前缘-下壁板蒙皮-结构识别 C919-A-57-41-02-01A-04CA-A 机翼-固定前缘-主结构-结构识别 C919-A-57-42-02-01A-04CA-A 机翼-缝翼-主结构-结构识别 3、发现基本型错误，反馈给甲方 4、与甲方就高原型结构识别输入所需内容、工作协调沟通等 | N69: =VLOOKUP(E69,订单号!B:C,2,0) -> YZ40000417 | O69: =VLOOKUP(C69,领导干部!B:B,1,0) -> #N/A | Q69: 秦超 | R69: 140 | S69: {=VLOOKUP(Q69&R69,IF({1,0},$B$2:$B$330&$F$2:$F$330,$C$2:$C$330),2,)} -> 51591 | T69: {=VLOOKUP(Q69&R69,IF({1,0},$B$2:$B$330&$F$2:$F$330,$D$2:$D$330),2,)} -> 总体室 | U69: {=VLOOKUP(Q69&R69,IF({1,0},$B$2:$B$330&$F$2:$F$330,$E$2:$E$330),2,)} -> C919基本型设计（2025年上飞院） | V69: {=VLOOKUP(Q69&R69,IF({1,0},$B$2:$B$330&$F$2:$F$330,$N$2:$N$330),2,)} -> YZ40000419
A70: =ROW()-1 -> 69 | B70: 费天行 | C70: =IFERROR(VLOOKUP(B70,[66]工程研发事业部人员名单!B:D,2,0),"") -> 52570 | D70: =IFERROR(VLOOKUP(B70,[66]工程研发事业部人员名单!B:D,3,0),"") -> 工程项目室 /适航工程室 | E70: C919高原型设计（2025年上飞院） | F70: =G70+H70+I70+J70 -> 100 | I70: 100 | K70: 其他 | M70: 1、编制： C919-A-57-41-01-02A-04CA-A 机翼-固定前缘-下壁板蒙皮-结构识别 C919-A-57-41-02-01A-04CA-A 机翼-固定前缘-主结构-结构识别 C919-A-57-42-02-01A-04CA-A 机翼-缝翼-主结构-结构识别 2、校对： C919-A-53-40-01-01A-04CA-A 机身-中机身-蒙皮-结构识别 C919-A-53-40-03-01A-04CA-A 机身-中机身-长桁-结构识别 C919-A-57-42-01-01A-04CA-A 机翼-缝翼-蒙皮-结构识别 | N70: =VLOOKUP(E70,订单号!B:C,2,0) -> YZ40000417 | O70: =VLOOKUP(C70,领导干部!B:B,1,0) -> #N/A | Q70: 曲汝文 | R70: 170 | S70: {=VLOOKUP(Q70&R70,IF({1,0},$B$2:$B$330&$F$2:$F$330,$C$2:$C$330),2,)} -> 52133 | T70: {=VLOOKUP(Q70&R70,IF({1,0},$B$2:$B$330&$F$2:$F$330,$D$2:$D$330),2,)} -> 结构一室 | U70: {=VLOOKUP(Q70&R70,IF({1,0},$B$2:$B$330&$F$2:$F$330,$E$2:$E$330),2,)} -> C929设计（2025年上飞院） | V70: {=VLOOKUP(Q70&R70,IF({1,0},$B$2:$B$330&$F$2:$F$330,$N$2:$N$330),2,)} -> YZ40000415
A71: =ROW()-1 -> 70 | B71: 潘英 | C71: =IFERROR(VLOOKUP(B71,[66]工程研发事业部人员名单!B:D,2,0),"") -> 50864 | D71: =IFERROR(VLOOKUP(B71,[66]工程研发事业部人员名单!B:D,3,0),"") -> 综合技术室 | E71: C919高原型设计（2025年上飞院） | F71: =G71+H71+I71+J71 -> 120 | I71: 120 | K71: 其他 | M71: 1、编制： C919-A-53-40-01-01A-04CA-A 机身-中机身-蒙皮-结构识别 C919-A-53-40-03-01A-04CA-A 机身-中机身-长桁-结构识别 C919-A-57-42-01-01A-04CA-A 机翼-缝翼-蒙皮-结构识别 2、校对： C919-A-53-40-08-01A-04CA-A 机身-中机身-隔框-结构识别 C919-A-53-40-71-01A-04CA-A 机身-中机身-前部整流罩面板-结构识别 C919-A-53-40-71-04A-04CA-A 机身-中机身-后部整流罩面板-结构识别 C919-A-57-54-70-01A-04CA-A 机翼-襟翼机构-滑轨-结构识别 | N71: =VLOOKUP(E71,订单号!B:C,2,0) -> YZ40000417 | O71: =VLOOKUP(C71,领导干部!B:B,1,0) -> #N/A | Q71: 任斌 | R71: 110 | S71: {=VLOOKUP(Q71&R71,IF({1,0},$B$2:$B$330&$F$2:$F$330,$C$2:$C$330),2,)} -> 51517 | T71: {=VLOOKUP(Q71&R71,IF({1,0},$B$2:$B$330&$F$2:$F$330,$D$2:$D$330),2,)} -> 系统室 | U71: {=VLOOKUP(Q71&R71,IF({1,0},$B$2:$B$330&$F$2:$F$330,$E$2:$E$330),2,)} -> C929设计（2025年上飞院） | V71: {=VLOOKUP(Q71&R71,IF({1,0},$B$2:$B$330&$F$2:$F$330,$N$2:$N$330),2,)} -> YZ40000415
A72: =ROW()-1 -> 71 | B72: 张刚 | C72: =IFERROR(VLOOKUP(B72,[66]工程研发事业部人员名单!B:D,2,0),"") -> 50278 | D72: =IFERROR(VLOOKUP(B72,[66]工程研发事业部人员名单!B:D,3,0),"") -> 结构二室 | E72: C919高原型设计（2025年上飞院） | F72: =G72+H72+I72+J72 -> 230 | I72: 230 | K72: 结构 | M72: 1）高原型后货舱门口框后移货前/后边框X-STOP结构设计更改（前后边框止动块、门周蒙皮及纵向加强件）； 2）高原型高原型FR66环向对接接头行李支架详细设计更改； 3）高原型FR50\FR52\FR62\FR64框行李支架设计更改（接头更改、框剪切角片、轴承装配、紧固件排布、MBD标注）； 4）高原型后货舱门口框上纵梁设计更改； 5）高原型中后机身行李支架与主结构共铆复查及校对，共439项； 6）高原型中后机身轻量化模型创建（后段及总装配）。 | N72: =VLOOKUP(E72,订单号!B:C,2,0) -> YZ40000417 | O72: =VLOOKUP(C72,领导干部!B:B,1,0) -> #N/A | Q72: 任璐璐 | R72: 115 | S72: {=VLOOKUP(Q72&R72,IF({1,0},$B$2:$B$330&$F$2:$F$330,$C$2:$C$330),2,)} -> 50032 | T72: {=VLOOKUP(Q72&R72,IF({1,0},$B$2:$B$330&$F$2:$F$330,$D$2:$D$330),2,)} -> 总体室 | U72: {=VLOOKUP(Q72&R72,IF({1,0},$B$2:$B$330&$F$2:$F$330,$E$2:$E$330),2,)} -> 重点工作任务 | V72: {=VLOOKUP(Q72&R72,IF({1,0},$B$2:$B$330&$F$2:$F$330,$N$2:$N$330),2,)} -> 0
A73: =ROW()-1 -> 72 | B73: 霍东旭 | C73: =IFERROR(VLOOKUP(B73,[66]工程研发事业部人员名单!B:D,2,0),"") -> 51941 | D73: =IFERROR(VLOOKUP(B73,[66]工程研发事业部人员名单!B:D,3,0),"") -> 联络工程室 | E73: C919高原型设计（2025年上飞院） | F73: =G73+H73+I73+J73 -> 180 | I73: 180 | K73: 结构 | M73: 1）高原型中后机身精细建模钉线整理（共31个框位）； 2）高原型中后机身行李支架与主结构共铆复查及校对，共439项； 3）高原型中后机身轻量化模型创建（前段）； 4）高原型中后机身等直段角片相似性设计更改； 5）基本型FR49-FR50起吊框设计更改。 | N73: =VLOOKUP(E73,订单号!B:C,2,0) -> YZ40000417 | O73: =VLOOKUP(C73,领导干部!B:B,1,0) -> #N/A | Q73: 石荣荣 | R73: 150 | S73: {=VLOOKUP(Q73&R73,IF({1,0},$B$2:$B$330&$F$2:$F$330,$C$2:$C$330),2,)} -> 51166 | T73: {=VLOOKUP(Q73&R73,IF({1,0},$B$2:$B$330&$F$2:$F$330,$D$2:$D$330),2,)} -> 工程项目室 /适航工程室 | U73: {=VLOOKUP(Q73&R73,IF({1,0},$B$2:$B$330&$F$2:$F$330,$E$2:$E$330),2,)} -> 项目开发与管控 | V73: {=VLOOKUP(Q73&R73,IF({1,0},$B$2:$B$330&$F$2:$F$330,$N$2:$N$330),2,)} -> #N/A
A74: =ROW()-1 -> 73 | B74: 张继斌 | C74: =IFERROR(VLOOKUP(B74,[66]工程研发事业部人员名单!B:D,2,0),"") -> 17243 | D74: =IFERROR(VLOOKUP(B74,[66]工程研发事业部人员名单!B:D,3,0),"") -> 总体室 | E74: C919手册优化（2025年复材中心） | F74: =G74+H74+I74+J74 -> 100 | I74: 100 | K74: 其他 | M74: 编制九份 | N74: =VLOOKUP(E74,订单号!B:C,2,0) -> YZ40000416 | O74: =VLOOKUP(C74,领导干部!B:B,1,0) -> #N/A | Q74: 宋建毅 | R74: 195 | S74: {=VLOOKUP(Q74&R74,IF({1,0},$B$2:$B$330&$F$2:$F$330,$C$2:$C$330),2,)} -> 27100 | T74: {=VLOOKUP(Q74&R74,IF({1,0},$B$2:$B$330&$F$2:$F$330,$D$2:$D$330),2,)} -> 综合技术室 | U74: {=VLOOKUP(Q74&R74,IF({1,0},$B$2:$B$330&$F$2:$F$330,$E$2:$E$330),2,)} -> WH1项目总体/系统/适航等其它专业 | V74: {=VLOOKUP(Q74&R74,IF({1,0},$B$2:$B$330&$F$2:$F$330,$N$2:$N$330),2,)} -> YZ-RD202428
A75: =ROW()-1 -> 74 | B75: 赵长辉 | C75: =IFERROR(VLOOKUP(B75,[66]工程研发事业部人员名单!B:D,2,0),"") -> 17725 | D75: =IFERROR(VLOOKUP(B75,[66]工程研发事业部人员名单!B:D,3,0),"") -> 总体室 | E75: 巡飞无人机课题 | F75: =G75+H75+I75+J75 -> 120 | I75: 120 | L75: 巡飞无人机 | M75: （1）复材翼面及机加外协加工跟进和协调，试验台外协加工工作跟进和协调； （2）总体设计总结和总体设计报告文件更新； （3）技术外协结题准备工作和结题PPT文件修改； （4）气动发射架和气动发射筒技术条件文件修改，设计接口问题处理； （5）无人机试飞标准规范文件学习研究，试飞任务书和试飞大纲文件编制； （6）课题中期评审PPT文件编制 | N75: =VLOOKUP(E75,订单号!B:C,2,0) -> YZ40000403 | O75: =VLOOKUP(C75,领导干部!B:B,1,0) -> #N/A | Q75: 宋凯 | R75: 80 | S75: {=VLOOKUP(Q75&R75,IF({1,0},$B$2:$B$330&$F$2:$F$330,$C$2:$C$330),2,)} -> 51951 | T75: {=VLOOKUP(Q75&R75,IF({1,0},$B$2:$B$330&$F$2:$F$330,$D$2:$D$330),2,)} -> 系统室 | U75: {=VLOOKUP(Q75&R75,IF({1,0},$B$2:$B$330&$F$2:$F$330,$E$2:$E$330),2,)} -> 培训工作 | V75: {=VLOOKUP(Q75&R75,IF({1,0},$B$2:$B$330&$F$2:$F$330,$N$2:$N$330),2,)} -> 0
A76: =ROW()-1 -> 75 | B76: 乔志斌 | C76: =IFERROR(VLOOKUP(B76,[66]工程研发事业部人员名单!B:D,2,0),"") -> 53422 | D76: =IFERROR(VLOOKUP(B76,[66]工程研发事业部人员名单!B:D,3,0),"") -> 强度室 | E76: 巡飞无人机课题 | F76: =G76+H76+I76+J76 -> 30 | I76: 30 | L76: 巡飞无人机 | M76: 1） 结题材料收集整理。 2） 完成巡飞无人机定常拉升有限元模型搭建。 3） 完成西工大结题评审相关事宜。 4） 完成西工大技术服务协议与振鹭试飞服务协议（第一笔）预算申报。 5） 沈航1名学生毕业论文内容审核与修改。 | N76: =VLOOKUP(E76,订单号!B:C,2,0) -> YZ40000403 | O76: =VLOOKUP(C76,领导干部!B:B,1,0) -> #N/A | Q76: 孙盘滔 | R76: 100 | S76: {=VLOOKUP(Q76&R76,IF({1,0},$B$2:$B$330&$F$2:$F$330,$C$2:$C$330),2,)} -> 50686 | T76: {=VLOOKUP(Q76&R76,IF({1,0},$B$2:$B$330&$F$2:$F$330,$D$2:$D$330),2,)} -> 综合技术室 | U76: {=VLOOKUP(Q76&R76,IF({1,0},$B$2:$B$330&$F$2:$F$330,$E$2:$E$330),2,)} -> 工程支持 | V76: {=VLOOKUP(Q76&R76,IF({1,0},$B$2:$B$330&$F$2:$F$330,$N$2:$N$330),2,)} -> 10502
A77: =ROW()-1 -> 76 | B77: 秦超 | C77: =IFERROR(VLOOKUP(B77,[66]工程研发事业部人员名单!B:D,2,0),"") -> 51591 | D77: =IFERROR(VLOOKUP(B77,[66]工程研发事业部人员名单!B:D,3,0),"") -> 总体室 | E77: 巡飞无人机课题 | F77: =G77+H77+I77+J77 -> 7 | I77: 7 | L77: 巡飞无人机 | M77: 1、一种新型的无人机动力系统测试平台专利编制； | N77: =VLOOKUP(E77,订单号!B:C,2,0) -> YZ40000403 | O77: =VLOOKUP(C77,领导干部!B:B,1,0) -> #N/A | Q77: 孙永光 | R77: 130 | S77: {=VLOOKUP(Q77&R77,IF({1,0},$B$2:$B$330&$F$2:$F$330,$C$2:$C$330),2,)} -> 25601 | T77: {=VLOOKUP(Q77&R77,IF({1,0},$B$2:$B$330&$F$2:$F$330,$D$2:$D$330),2,)} -> 联络工程室 | U77: {=VLOOKUP(Q77&R77,IF({1,0},$B$2:$B$330&$F$2:$F$330,$E$2:$E$330),2,)} -> C919YJTD设计 | V77: {=VLOOKUP(Q77&R77,IF({1,0},$B$2:$B$330&$F$2:$F$330,$N$2:$N$330),2,)} -> YZ40000410
A78: =ROW()-1 -> 77 | B78: 朱海 | C78: =IFERROR(VLOOKUP(B78,[66]工程研发事业部人员名单!B:D,2,0),"") -> 52232 | D78: =IFERROR(VLOOKUP(B78,[66]工程研发事业部人员名单!B:D,3,0),"") -> 结构二室 | E78: 巡飞无人机课题 | F78: =G78+H78+I78+J78 -> 7 | I78: 7 | L78: 巡飞无人机 | M78: 1） 巡飞无人机数模整理； 2） 更改结构设计报告。 | N78: =VLOOKUP(E78,订单号!B:C,2,0) -> YZ40000403 | O78: =VLOOKUP(C78,领导干部!B:B,1,0) -> #N/A | Q78: 塔拉 | R78: 180 | S78: {=VLOOKUP(Q78&R78,IF({1,0},$B$2:$B$330&$F$2:$F$330,$C$2:$C$330),2,)} -> 25548 | T78: {=VLOOKUP(Q78&R78,IF({1,0},$B$2:$B$330&$F$2:$F$330,$D$2:$D$330),2,)} -> 结构一室 | U78: {=VLOOKUP(Q78&R78,IF({1,0},$B$2:$B$330&$F$2:$F$330,$E$2:$E$330),2,)} -> C929设计（2025年上飞院） | V78: {=VLOOKUP(Q78&R78,IF({1,0},$B$2:$B$330&$F$2:$F$330,$N$2:$N$330),2,)} -> YZ40000415
A79: =ROW()-1 -> 78 | B79: 赵婷 | C79: =IFERROR(VLOOKUP(B79,[66]工程研发事业部人员名单!B:D,2,0),"") -> 50702 | D79: =IFERROR(VLOOKUP(B79,[66]工程研发事业部人员名单!B:D,3,0),"") -> 总体室 | E79: 党建工作 | F79: =G79+H79+I79+J79 -> 8 | I79: 8 | N79: =VLOOKUP(E79,订单号!B:C,2,0) -> 0 | O79: =VLOOKUP(C79,领导干部!B:B,1,0) -> #N/A | Q79: 万方 | R79: 190 | S79: {=VLOOKUP(Q79&R79,IF({1,0},$B$2:$B$330&$F$2:$F$330,$C$2:$C$330),2,)} -> 51387 | T79: {=VLOOKUP(Q79&R79,IF({1,0},$B$2:$B$330&$F$2:$F$330,$D$2:$D$330),2,)} -> 系统室 | U79: {=VLOOKUP(Q79&R79,IF({1,0},$B$2:$B$330&$F$2:$F$330,$E$2:$E$330),2,)} -> C919基本型设计（2025年上飞院） | V79: {=VLOOKUP(Q79&R79,IF({1,0},$B$2:$B$330&$F$2:$F$330,$N$2:$N$330),2,)} -> YZ40000419
A80: =ROW()-1 -> 79 | B80: 任斌 | C80: =IFERROR(VLOOKUP(B80,[66]工程研发事业部人员名单!B:D,2,0),"") -> 51517 | D80: =IFERROR(VLOOKUP(B80,[66]工程研发事业部人员名单!B:D,3,0),"") -> 系统室 | E80: 党建工作 | F80: =G80+H80+I80+J80 -> 8 | I80: 8 | N80: =VLOOKUP(E80,订单号!B:C,2,0) -> 0 | O80: =VLOOKUP(C80,领导干部!B:B,1,0) -> #N/A | Q80: 王超 | R80: 4.8 | S80: {=VLOOKUP(Q80&R80,IF({1,0},$B$2:$B$330&$F$2:$F$330,$C$2:$C$330),2,)} -> 26621 | T80: {=VLOOKUP(Q80&R80,IF({1,0},$B$2:$B$330&$F$2:$F$330,$D$2:$D$330),2,)} -> 联络工程室 | U80: {=VLOOKUP(Q80&R80,IF({1,0},$B$2:$B$330&$F$2:$F$330,$E$2:$E$330),2,)} -> 培训工作 | V80: {=VLOOKUP(Q80&R80,IF({1,0},$B$2:$B$330&$F$2:$F$330,$N$2:$N$330),2,)} -> 0
A81: =ROW()-1 -> 80 | B81: 李妍 | C81: =IFERROR(VLOOKUP(B81,[66]工程研发事业部人员名单!B:D,2,0),"") -> 51435 | D81: =IFERROR(VLOOKUP(B81,[66]工程研发事业部人员名单!B:D,3,0),"") -> 系统室 | E81: 党建工作 | F81: =G81+H81+I81+J81 -> 12 | I81: 12 | N81: =VLOOKUP(E81,订单号!B:C,2,0) -> 0 | O81: =VLOOKUP(C81,领导干部!B:B,1,0) -> #N/A | Q81: 王琛 | R81: 200 | S81: {=VLOOKUP(Q81&R81,IF({1,0},$B$2:$B$330&$F$2:$F$330,$C$2:$C$330),2,)} -> 22291 | T81: {=VLOOKUP(Q81&R81,IF({1,0},$B$2:$B$330&$F$2:$F$330,$D$2:$D$330),2,)} -> 综合技术室 | U81: {=VLOOKUP(Q81&R81,IF({1,0},$B$2:$B$330&$F$2:$F$330,$E$2:$E$330),2,)} -> C919高原型设计（2025年上飞院） | V81: {=VLOOKUP(Q81&R81,IF({1,0},$B$2:$B$330&$F$2:$F$330,$N$2:$N$330),2,)} -> YZ40000417
A82: =ROW()-1 -> 81 | B82: 李其鹏 | C82: =IFERROR(VLOOKUP(B82,[66]工程研发事业部人员名单!B:D,2,0),"") -> 51429 | D82: =IFERROR(VLOOKUP(B82,[66]工程研发事业部人员名单!B:D,3,0),"") -> 综合技术室 | E82: 党建工作 | F82: =G82+H82+I82+J82 -> 13 | I82: 13 | N82: =VLOOKUP(E82,订单号!B:C,2,0) -> 0 | O82: =VLOOKUP(C82,领导干部!B:B,1,0) -> #N/A | Q82: 王呈呈 | R82: 190 | S82: {=VLOOKUP(Q82&R82,IF({1,0},$B$2:$B$330&$F$2:$F$330,$C$2:$C$330),2,)} -> 51196 | T82: {=VLOOKUP(Q82&R82,IF({1,0},$B$2:$B$330&$F$2:$F$330,$D$2:$D$330),2,)} -> 强度室 | U82: {=VLOOKUP(Q82&R82,IF({1,0},$B$2:$B$330&$F$2:$F$330,$E$2:$E$330),2,)} -> WH1项目结构强度综合 | V82: {=VLOOKUP(Q82&R82,IF({1,0},$B$2:$B$330&$F$2:$F$330,$N$2:$N$330),2,)} -> YZ-RD202428
A83: =ROW()-1 -> 82 | B83: 丛家勇 | C83: =IFERROR(VLOOKUP(B83,[66]工程研发事业部人员名单!B:D,2,0),"") -> 50281 | D83: =IFERROR(VLOOKUP(B83,[66]工程研发事业部人员名单!B:D,3,0),"") -> 结构一室 | E83: 党建工作 | F83: =G83+H83+I83+J83 -> 9.5 | I83: 9.5 | L83: 党建工作 | M83: 1、协助组织主题党日活动，参加支委会，1.5小时； 2、记录支委会会议，1小时； 3、迎接党建检查，党建资料准备，6小时； 4、记录主题党日，1小时。 | N83: =VLOOKUP(E83,订单号!B:C,2,0) -> 0 | O83: =VLOOKUP(C83,领导干部!B:B,1,0) -> #N/A | Q83: 王川 | R83: 139 | S83: {=VLOOKUP(Q83&R83,IF({1,0},$B$2:$B$330&$F$2:$F$330,$C$2:$C$330),2,)} -> 22250 | T83: {=VLOOKUP(Q83&R83,IF({1,0},$B$2:$B$330&$F$2:$F$330,$D$2:$D$330),2,)} -> 联络工程室 | U83: {=VLOOKUP(Q83&R83,IF({1,0},$B$2:$B$330&$F$2:$F$330,$E$2:$E$330),2,)} -> 工程支持 | V83: {=VLOOKUP(Q83&R83,IF({1,0},$B$2:$B$330&$F$2:$F$330,$N$2:$N$330),2,)} -> 10502
A84: =ROW()-1 -> 83 | B84: 葛春生 | C84: =IFERROR(VLOOKUP(B84,[66]工程研发事业部人员名单!B:D,2,0),"") -> 51410 | D84: =IFERROR(VLOOKUP(B84,[66]工程研发事业部人员名单!B:D,3,0),"") -> 结构一室 | E84: 党建工作 | F84: =G84+H84+I84+J84 -> 4.5 | I84: 4.5 | L84: 党建工作 | M84: 1、准备党小组会议资料1小时，召开党小组会1小时。 2、全体党员二季度积分统计，2小时； 3、入党积极分子考察并记录考察意见，0.5小时。 | N84: =VLOOKUP(E84,订单号!B:C,2,0) -> 0 | O84: =VLOOKUP(C84,领导干部!B:B,1,0) -> #N/A | Q84: 王大昱 | R84: 4.8 | S84: {=VLOOKUP(Q84&R84,IF({1,0},$B$2:$B$330&$F$2:$F$330,$C$2:$C$330),2,)} -> 51162 | T84: {=VLOOKUP(Q84&R84,IF({1,0},$B$2:$B$330&$F$2:$F$330,$D$2:$D$330),2,)} -> 工程项目室 /适航工程室 | U84: {=VLOOKUP(Q84&R84,IF({1,0},$B$2:$B$330&$F$2:$F$330,$E$2:$E$330),2,)} -> 培训工作 | V84: {=VLOOKUP(Q84&R84,IF({1,0},$B$2:$B$330&$F$2:$F$330,$N$2:$N$330),2,)} -> 0
A85: =ROW()-1 -> 84 | B85: 刘金晶 | C85: =IFERROR(VLOOKUP(B85,[66]工程研发事业部人员名单!B:D,2,0),"") -> 51641 | D85: =IFERROR(VLOOKUP(B85,[66]工程研发事业部人员名单!B:D,3,0),"") -> 结构二室 | E85: 党建工作 | F85: =G85+H85+I85+J85 -> 2 | I85: 2 | L85: 党建工作 | M85: 1、记录党员大会，2小时。 | N85: =VLOOKUP(E85,订单号!B:C,2,0) -> 0 | O85: =VLOOKUP(C85,领导干部!B:B,1,0) -> #N/A | Q85: 王健 | R85: 115 | S85: {=VLOOKUP(Q85&R85,IF({1,0},$B$2:$B$330&$F$2:$F$330,$C$2:$C$330),2,)} -> 51784 | T85: {=VLOOKUP(Q85&R85,IF({1,0},$B$2:$B$330&$F$2:$F$330,$D$2:$D$330),2,)} -> 结构一室 | U85: {=VLOOKUP(Q85&R85,IF({1,0},$B$2:$B$330&$F$2:$F$330,$E$2:$E$330),2,)} -> C929设计（2025年上飞院） | V85: {=VLOOKUP(Q85&R85,IF({1,0},$B$2:$B$330&$F$2:$F$330,$N$2:$N$330),2,)} -> YZ40000415
A86: =ROW()-1 -> 85 | B86: 孟力华 | C86: =IFERROR(VLOOKUP(B86,[66]工程研发事业部人员名单!B:D,2,0),"") -> 51234 | D86: =IFERROR(VLOOKUP(B86,[66]工程研发事业部人员名单!B:D,3,0),"") -> 结构二室 | E86: 党建工作 | F86: =G86+H86+I86+J86 -> 3 | I86: 3 | L86: 党建工作 | M86: 1、准备党小组会议资料1小时，召开党小组会1小时； 2、统计党小组党员积分1小时。 | N86: =VLOOKUP(E86,订单号!B:C,2,0) -> 0 | O86: =VLOOKUP(C86,领导干部!B:B,1,0) -> #N/A | Q86: 王立庆 | R86: 157.51 | S86: {=VLOOKUP(Q86&R86,IF({1,0},$B$2:$B$330&$F$2:$F$330,$C$2:$C$330),2,)} -> 27106 | T86: {=VLOOKUP(Q86&R86,IF({1,0},$B$2:$B$330&$F$2:$F$330,$D$2:$D$330),2,)} -> 联络工程室 | U86: {=VLOOKUP(Q86&R86,IF({1,0},$B$2:$B$330&$F$2:$F$330,$E$2:$E$330),2,)} -> 工程支持 | V86: {=VLOOKUP(Q86&R86,IF({1,0},$B$2:$B$330&$F$2:$F$330,$N$2:$N$330),2,)} -> 10502
A87: =ROW()-1 -> 86 | B87: 魏士礼 | C87: =IFERROR(VLOOKUP(B87,[66]工程研发事业部人员名单!B:D,2,0),"") -> 22294 | D87: =IFERROR(VLOOKUP(B87,[66]工程研发事业部人员名单!B:D,3,0),"") -> 结构一室 | E87: 党建工作 | F87: =G87+H87+I87+J87 -> 1 | I87: 1 | L87: 党建工作 | M87: 记录第一党小组会议记录，1小时。 | N87: =VLOOKUP(E87,订单号!B:C,2,0) -> 0 | O87: =VLOOKUP(C87,领导干部!B:B,1,0) -> #N/A | Q87: 王连斌 | R87: 151.48 | S87: {=VLOOKUP(Q87&R87,IF({1,0},$B$2:$B$330&$F$2:$F$330,$C$2:$C$330),2,)} -> 51396 | T87: {=VLOOKUP(Q87&R87,IF({1,0},$B$2:$B$330&$F$2:$F$330,$D$2:$D$330),2,)} -> 联络工程室 | U87: {=VLOOKUP(Q87&R87,IF({1,0},$B$2:$B$330&$F$2:$F$330,$E$2:$E$330),2,)} -> 工程支持 | V87: {=VLOOKUP(Q87&R87,IF({1,0},$B$2:$B$330&$F$2:$F$330,$N$2:$N$330),2,)} -> 10502
A88: =ROW()-1 -> 87 | B88: 罗贵骞 | C88: =IFERROR(VLOOKUP(B88,[66]工程研发事业部人员名单!B:D,2,0),"") -> 51186 | D88: =IFERROR(VLOOKUP(B88,[66]工程研发事业部人员名单!B:D,3,0),"") -> 结构二室 | E88: 党建工作 | F88: =G88+H88+I88+J88 -> 1 | I88: 1 | L88: 党建工作 | M88: 记录第二党小组会议记录，1小时。 | N88: =VLOOKUP(E88,订单号!B:C,2,0) -> 0 | O88: =VLOOKUP(C88,领导干部!B:B,1,0) -> #N/A | Q88: 王瑞龙 | R88: 180 | S88: {=VLOOKUP(Q88&R88,IF({1,0},$B$2:$B$330&$F$2:$F$330,$C$2:$C$330),2,)} -> 26654 | T88: {=VLOOKUP(Q88&R88,IF({1,0},$B$2:$B$330&$F$2:$F$330,$D$2:$D$330),2,)} -> 联络工程室 | U88: {=VLOOKUP(Q88&R88,IF({1,0},$B$2:$B$330&$F$2:$F$330,$E$2:$E$330),2,)} -> SIA无人机设计-2 | V88: {=VLOOKUP(Q88&R88,IF({1,0},$B$2:$B$330&$F$2:$F$330,$N$2:$N$330),2,)} -> YZ40000422
A89: =ROW()-1 -> 88 | B89: 赵莉 | C89: =IFERROR(VLOOKUP(B89,[66]工程研发事业部人员名单!B:D,2,0),"") -> 50065 | D89: =IFERROR(VLOOKUP(B89,[66]工程研发事业部人员名单!B:D,3,0),"") -> 结构二室 | E89: 党建工作 | F89: =G89+H89+I89+J89 -> 2 | I89: 2 | L89: 党建工作 | M89: 记录党课学习内容，2小时。 | N89: =VLOOKUP(E89,订单号!B:C,2,0) -> 0 | O89: =VLOOKUP(C89,领导干部!B:B,1,0) -> #N/A | Q89: 王世清 | R89: 160.638 | S89: {=VLOOKUP(Q89&R89,IF({1,0},$B$2:$B$330&$F$2:$F$330,$C$2:$C$330),2,)} -> 50317 | T89: {=VLOOKUP(Q89&R89,IF({1,0},$B$2:$B$330&$F$2:$F$330,$D$2:$D$330),2,)} -> 联络工程室 | U89: {=VLOOKUP(Q89&R89,IF({1,0},$B$2:$B$330&$F$2:$F$330,$E$2:$E$330),2,)} -> 工程支持 | V89: {=VLOOKUP(Q89&R89,IF({1,0},$B$2:$B$330&$F$2:$F$330,$N$2:$N$330),2,)} -> 10502
A90: =ROW()-1 -> 89 | B90: 王世清 | C90: =IFERROR(VLOOKUP(B90,[66]工程研发事业部人员名单!B:D,2,0),"") -> 50317 | D90: =IFERROR(VLOOKUP(B90,[66]工程研发事业部人员名单!B:D,3,0),"") -> 联络工程室 | E90: 党建工作 | F90: =G90+H90+I90+J90 -> 15 | I90: 15 | M90: 见原表 | N90: =VLOOKUP(E90,订单号!B:C,2,0) -> 0 | O90: =VLOOKUP(C90,领导干部!B:B,1,0) -> #N/A | Q90: 王岩 | R90: 170 | S90: {=VLOOKUP(Q90&R90,IF({1,0},$B$2:$B$330&$F$2:$F$330,$C$2:$C$330),2,)} -> 51175 | T90: {=VLOOKUP(Q90&R90,IF({1,0},$B$2:$B$330&$F$2:$F$330,$D$2:$D$330),2,)} -> 强度室 | U90: {=VLOOKUP(Q90&R90,IF({1,0},$B$2:$B$330&$F$2:$F$330,$E$2:$E$330),2,)} -> C929设计（2025年上飞院） | V90: {=VLOOKUP(Q90&R90,IF({1,0},$B$2:$B$330&$F$2:$F$330,$N$2:$N$330),2,)} -> YZ40000415
A91: =ROW()-1 -> 90 | B91: 姚庆丰 | C91: =IFERROR(VLOOKUP(B91,[66]工程研发事业部人员名单!B:D,2,0),"") -> 18672 | D91: =IFERROR(VLOOKUP(B91,[66]工程研发事业部人员名单!B:D,3,0),"") -> 联络工程室 | E91: 党建工作 | F91: =G91+H91+I91+J91 -> 9.5 | I91: 9.5 | M91: 见原表 | N91: =VLOOKUP(E91,订单号!B:C,2,0) -> 0 | O91: =VLOOKUP(C91,领导干部!B:B,1,0) -> #N/A | Q91: 王艺霖 | R91: 180 | S91: {=VLOOKUP(Q91&R91,IF({1,0},$B$2:$B$330&$F$2:$F$330,$C$2:$C$330),2,)} -> 25762 | T91: {=VLOOKUP(Q91&R91,IF({1,0},$B$2:$B$330&$F$2:$F$330,$D$2:$D$330),2,)} -> 结构二室 | U91: {=VLOOKUP(Q91&R91,IF({1,0},$B$2:$B$330&$F$2:$F$330,$E$2:$E$330),2,)} -> C929设计（2025年上飞院） | V91: {=VLOOKUP(Q91&R91,IF({1,0},$B$2:$B$330&$F$2:$F$330,$N$2:$N$330),2,)} -> YZ40000415
A92: =ROW()-1 -> 91 | B92: 马雪菲 | C92: =IFERROR(VLOOKUP(B92,[66]工程研发事业部人员名单!B:D,2,0),"") -> 52560 | D92: =IFERROR(VLOOKUP(B92,[66]工程研发事业部人员名单!B:D,3,0),"") -> 强度室 | E92: 党建工作 | F92: =G92+H92+I92+J92 -> 5 | I92: 5 | M92: 见原表 | N92: =VLOOKUP(E92,订单号!B:C,2,0) -> 0 | O92: =VLOOKUP(C92,领导干部!B:B,1,0) -> #N/A | Q92: 王勇 | R92: 80 | S92: {=VLOOKUP(Q92&R92,IF({1,0},$B$2:$B$330&$F$2:$F$330,$C$2:$C$330),2,)} -> 51226 | T92: {=VLOOKUP(Q92&R92,IF({1,0},$B$2:$B$330&$F$2:$F$330,$D$2:$D$330),2,)} -> 综合技术室 | U92: {=VLOOKUP(Q92&R92,IF({1,0},$B$2:$B$330&$F$2:$F$330,$E$2:$E$330),2,)} -> 工程支持 | V92: {=VLOOKUP(Q92&R92,IF({1,0},$B$2:$B$330&$F$2:$F$330,$N$2:$N$330),2,)} -> 10502
A93: =ROW()-1 -> 92 | B93: 夏新鑫 | C93: =IFERROR(VLOOKUP(B93,[66]工程研发事业部人员名单!B:D,2,0),"") -> 50876 | D93: =IFERROR(VLOOKUP(B93,[66]工程研发事业部人员名单!B:D,3,0),"") -> 工程项目室 /适航工程室 | E93: 党建工作 | F93: =G93+H93+I93+J93 -> 2 | I93: 2 | M93: 见原表 | N93: =VLOOKUP(E93,订单号!B:C,2,0) -> 0 | O93: =VLOOKUP(C93,领导干部!B:B,1,0) -> #N/A | Q93: 王哲 | R93: 155 | S93: {=VLOOKUP(Q93&R93,IF({1,0},$B$2:$B$330&$F$2:$F$330,$C$2:$C$330),2,)} -> 25071 | T93: {=VLOOKUP(Q93&R93,IF({1,0},$B$2:$B$330&$F$2:$F$330,$D$2:$D$330),2,)} -> 结构一室 | U93: {=VLOOKUP(Q93&R93,IF({1,0},$B$2:$B$330&$F$2:$F$330,$E$2:$E$330),2,)} -> WH1项目结构强度综合 | V93: {=VLOOKUP(Q93&R93,IF({1,0},$B$2:$B$330&$F$2:$F$330,$N$2:$N$330),2,)} -> YZ-RD202428
A94: =ROW()-1 -> 93 | B94: 张继斌 | C94: =IFERROR(VLOOKUP(B94,[66]工程研发事业部人员名单!B:D,2,0),"") -> 17243 | D94: =IFERROR(VLOOKUP(B94,[66]工程研发事业部人员名单!B:D,3,0),"") -> 总体室 | E94: 培训工作 | F94: =G94+H94+I94+J94 -> 4.8 | I94: 4.8 | M94: 培训：飞机减重设计方法及零件的优化设计方法培训 | N94: =VLOOKUP(E94,订单号!B:C,2,0) -> 0 | O94: =VLOOKUP(C94,领导干部!B:B,1,0) -> #N/A | Q94: 韦杰琼 | R94: 155 | S94: {=VLOOKUP(Q94&R94,IF({1,0},$B$2:$B$330&$F$2:$F$330,$C$2:$C$330),2,)} -> 25599 | T94: {=VLOOKUP(Q94&R94,IF({1,0},$B$2:$B$330&$F$2:$F$330,$D$2:$D$330),2,)} -> 联络工程室 | U94: {=VLOOKUP(Q94&R94,IF({1,0},$B$2:$B$330&$F$2:$F$330,$E$2:$E$330),2,)} -> WH1项目结构强度综合 | V94: {=VLOOKUP(Q94&R94,IF({1,0},$B$2:$B$330&$F$2:$F$330,$N$2:$N$330),2,)} -> YZ-RD202428
A95: =ROW()-1 -> 94 | B95: 赵长辉 | C95: =IFERROR(VLOOKUP(B95,[66]工程研发事业部人员名单!B:D,2,0),"") -> 17725 | D95: =IFERROR(VLOOKUP(B95,[66]工程研发事业部人员名单!B:D,3,0),"") -> 总体室 | E95: 培训工作 | F95: =G95+H95+I95+J95 -> 4.8 | I95: 4.8 | M95: 培训：巡飞无人机试验台架设计培训 | N95: =VLOOKUP(E95,订单号!B:C,2,0) -> 0 | O95: =VLOOKUP(C95,领导干部!B:B,1,0) -> #N/A | Q95: 魏春生 | R95: 62 | S95: {=VLOOKUP(Q95&R95,IF({1,0},$B$2:$B$330&$F$2:$F$330,$C$2:$C$330),2,)} -> 51389 | T95: {=VLOOKUP(Q95&R95,IF({1,0},$B$2:$B$330&$F$2:$F$330,$D$2:$D$330),2,)} -> 系统室 | U95: {=VLOOKUP(Q95&R95,IF({1,0},$B$2:$B$330&$F$2:$F$330,$E$2:$E$330),2,)} -> C919手册优化（2025年复材中心） | V95: {=VLOOKUP(Q95&R95,IF({1,0},$B$2:$B$330&$F$2:$F$330,$N$2:$N$330),2,)} -> YZ40000416
A96: =ROW()-1 -> 95 | B96: 赵婷 | C96: =IFERROR(VLOOKUP(B96,[66]工程研发事业部人员名单!B:D,2,0),"") -> 50702 | D96: =IFERROR(VLOOKUP(B96,[66]工程研发事业部人员名单!B:D,3,0),"") -> 总体室 | E96: 培训工作 | F96: =G96+H96+I96+J96 -> 2.4 | I96: 2.4 | M96: 培训：翼载及推重比在方案设计初期的计算选定培训 | N96: =VLOOKUP(E96,订单号!B:C,2,0) -> 0 | O96: =VLOOKUP(C96,领导干部!B:B,1,0) -> #N/A | Q96: 魏士礼 | R96: 200 | S96: {=VLOOKUP(Q96&R96,IF({1,0},$B$2:$B$330&$F$2:$F$330,$C$2:$C$330),2,)} -> 22294 | T96: {=VLOOKUP(Q96&R96,IF({1,0},$B$2:$B$330&$F$2:$F$330,$D$2:$D$330),2,)} -> 结构一室 | U96: {=VLOOKUP(Q96&R96,IF({1,0},$B$2:$B$330&$F$2:$F$330,$E$2:$E$330),2,)} -> WH1项目结构强度综合 | V96: {=VLOOKUP(Q96&R96,IF({1,0},$B$2:$B$330&$F$2:$F$330,$N$2:$N$330),2,)} -> YZ-RD202428
A97: =ROW()-1 -> 96 | B97: 尤宏良 | C97: =IFERROR(VLOOKUP(B97,[66]工程研发事业部人员名单!B:D,2,0),"") -> 18550 | D97: =IFERROR(VLOOKUP(B97,[66]工程研发事业部人员名单!B:D,3,0),"") -> 总体室 | E97: 培训工作 | F97: =G97+H97+I97+J97 -> 9.6 | I97: 9.6 | M97: 培训：飞机总体参数初步确定培训、飞机总体初步布局培训 | N97: =VLOOKUP(E97,订单号!B:C,2,0) -> 0 | O97: =VLOOKUP(C97,领导干部!B:B,1,0) -> #N/A | Q97: 吴晓莉 | R97: 91 | S97: {=VLOOKUP(Q97&R97,IF({1,0},$B$2:$B$330&$F$2:$F$330,$C$2:$C$330),2,)} -> 50872 | T97: {=VLOOKUP(Q97&R97,IF({1,0},$B$2:$B$330&$F$2:$F$330,$D$2:$D$330),2,)} -> 系统室 | U97: {=VLOOKUP(Q97&R97,IF({1,0},$B$2:$B$330&$F$2:$F$330,$E$2:$E$330),2,)} -> C919手册优化（2025年复材中心） | V97: {=VLOOKUP(Q97&R97,IF({1,0},$B$2:$B$330&$F$2:$F$330,$N$2:$N$330),2,)} -> YZ40000416
A98: =ROW()-1 -> 97 | B98: 刘杰 | C98: =IFERROR(VLOOKUP(B98,[66]工程研发事业部人员名单!B:D,2,0),"") -> 17242 | D98: =IFERROR(VLOOKUP(B98,[66]工程研发事业部人员名单!B:D,3,0),"") -> 办公室 | E98: 培训工作 | F98: =G98+H98+I98+J98 -> 4.8 | I98: 4.8 | M98: 培训：民机设计和开发概要培训 | N98: =VLOOKUP(E98,订单号!B:C,2,0) -> 0 | O98: =VLOOKUP(C98,领导干部!B:B,1,0) -> 17242 | Q98: 夏新鑫 | R98: 60 | S98: {=VLOOKUP(Q98&R98,IF({1,0},$B$2:$B$330&$F$2:$F$330,$C$2:$C$330),2,)} -> 50876 | T98: {=VLOOKUP(Q98&R98,IF({1,0},$B$2:$B$330&$F$2:$F$330,$D$2:$D$330),2,)} -> 工程项目室 /适航工程室 | U98: {=VLOOKUP(Q98&R98,IF({1,0},$B$2:$B$330&$F$2:$F$330,$E$2:$E$330),2,)} -> 项目开发与管控 | V98: {=VLOOKUP(Q98&R98,IF({1,0},$B$2:$B$330&$F$2:$F$330,$N$2:$N$330),2,)} -> #N/A
A99: =ROW()-1 -> 98 | B99: 王大昱 | C99: =IFERROR(VLOOKUP(B99,[66]工程研发事业部人员名单!B:D,2,0),"") -> 51162 | D99: =IFERROR(VLOOKUP(B99,[66]工程研发事业部人员名单!B:D,3,0),"") -> 工程项目室 /适航工程室 | E99: 培训工作 | F99: =G99+H99+I99+J99 -> 4.8 | I99: 4.8 | M99: 培训：适航理念与中国适航法规体系基础培训 | N99: =VLOOKUP(E99,订单号!B:C,2,0) -> 0 | O99: =VLOOKUP(C99,领导干部!B:B,1,0) -> 51162 | Q99: 徐丹 | R99: 210 | S99: {=VLOOKUP(Q99&R99,IF({1,0},$B$2:$B$330&$F$2:$F$330,$C$2:$C$330),2,)} -> 51407 | T99: {=VLOOKUP(Q99&R99,IF({1,0},$B$2:$B$330&$F$2:$F$330,$D$2:$D$330),2,)} -> 结构二室 | U99: {=VLOOKUP(Q99&R99,IF({1,0},$B$2:$B$330&$F$2:$F$330,$E$2:$E$330),2,)} -> C929设计（2025年复材中心） | V99: {=VLOOKUP(Q99&R99,IF({1,0},$B$2:$B$330&$F$2:$F$330,$N$2:$N$330),2,)} -> YZ40000418
A100: =ROW()-1 -> 99 | B100: 夏新鑫 | C100: =IFERROR(VLOOKUP(B100,[66]工程研发事业部人员名单!B:D,2,0),"") -> 50876 | D100: =IFERROR(VLOOKUP(B100,[66]工程研发事业部人员名单!B:D,3,0),"") -> 工程项目室 /适航工程室 | E100: 培训工作 | F100: =G100+H100+I100+J100 -> 4.8 | I100: 4.8 | M100: 培训：机体结构可达性分析之AMM区域检查任务及人机仿真应用培训 | N100: =VLOOKUP(E100,订单号!B:C,2,0) -> 0 | O100: =VLOOKUP(C100,领导干部!B:B,1,0) -> #N/A | Q100: 徐君升 | R100: 190 | S100: {=VLOOKUP(Q100&R100,IF({1,0},$B$2:$B$330&$F$2:$F$330,$C$2:$C$330),2,)} -> 50716 | T100: {=VLOOKUP(Q100&R100,IF({1,0},$B$2:$B$330&$F$2:$F$330,$D$2:$D$330),2,)} -> 强度室 | U100: {=VLOOKUP(Q100&R100,IF({1,0},$B$2:$B$330&$F$2:$F$330,$E$2:$E$330),2,)} -> C929设计（2025年复材中心） | V100: {=VLOOKUP(Q100&R100,IF({1,0},$B$2:$B$330&$F$2:$F$330,$N$2:$N$330),2,)} -> YZ40000418
A101: =ROW()-1 -> 100 | B101: 刘洋 | C101: =IFERROR(VLOOKUP(B101,[66]工程研发事业部人员名单!B:D,2,0),"") -> 50709 | D101: =IFERROR(VLOOKUP(B101,[66]工程研发事业部人员名单!B:D,3,0),"") -> 系统室 | E101: 培训工作 | F101: =G101+H101+I101+J101 -> 3.6 | I101: 3.6 | M101: 培训：民用飞机EWIS安全性分析培训 | N101: =VLOOKUP(E101,订单号!B:C,2,0) -> 0 | O101: =VLOOKUP(C101,领导干部!B:B,1,0) -> 50709 | Q101: 徐丽娜 | R101: 70 | S101: {=VLOOKUP(Q101&R101,IF({1,0},$B$2:$B$330&$F$2:$F$330,$C$2:$C$330),2,)} -> 50079 | T101: {=VLOOKUP(Q101&R101,IF({1,0},$B$2:$B$330&$F$2:$F$330,$D$2:$D$330),2,)} -> 工程项目室 /适航工程室 | U101: {=VLOOKUP(Q101&R101,IF({1,0},$B$2:$B$330&$F$2:$F$330,$E$2:$E$330),2,)} -> 项目开发与管控 | V101: {=VLOOKUP(Q101&R101,IF({1,0},$B$2:$B$330&$F$2:$F$330,$N$2:$N$330),2,)} -> #N/A
... A120: =ROW()-1 -> 119 | B120: 李森 | C120: =IFERROR(VLOOKUP(B120,[66]工程研发事业部人员名单!B:D,2,0),"") -> 17238 | D120: =IFERROR(VLOOKUP(B120,[66]工程研发事业部人员名单!B:D,3,0),"") -> 结构二室 | E120: 培训工作 | F120: =G120+H120+I120+J120 -> 9.6 | I120: 9.6 | M120: 培训：曲面逆向建模技术培训 | N120: =VLOOKUP(E120,订单号!B:C,2,0) -> 0 | O120: =VLOOKUP(C120,领导干部!B:B,1,0) -> #N/A | Q120: 赵海 | R120: 157 | S120: {=VLOOKUP(Q120&R120,IF({1,0},$B$2:$B$330&$F$2:$F$330,$C$2:$C$330),2,)} -> 50323 | T120: {=VLOOKUP(Q120&R120,IF({1,0},$B$2:$B$330&$F$2:$F$330,$D$2:$D$330),2,)} -> 联络工程室 | U120: {=VLOOKUP(Q120&R120,IF({1,0},$B$2:$B$330&$F$2:$F$330,$E$2:$E$330),2,)} -> 工程支持 | V120: {=VLOOKUP(Q120&R120,IF({1,0},$B$2:$B$330&$F$2:$F$330,$N$2:$N$330),2,)} -> 10502
A121: =ROW()-1 -> 120 | B121: 徐君升 | C121: =IFERROR(VLOOKUP(B121,[66]工程研发事业部人员名单!B:D,2,0),"") -> 50716 | D121: =IFERROR(VLOOKUP(B121,[66]工程研发事业部人员名单!B:D,3,0),"") -> 强度室 | E121: 重点工作任务 | F121: =G121+H121+I121+J121 -> 5 | I121: 5 | K121: 强度 | M121: 编制S-技术文件疲劳及损伤容限分析流程 编制S-技术文件结构疲劳载荷谱编制流程 校对S-技术文件静强度分析流程 校对S-技术文件舱门结构强度分析流程 | N121: =VLOOKUP(E121,订单号!B:C,2,0) -> 0 | O121: =VLOOKUP(C121,领导干部!B:B,1,0) -> #N/A | Q121: 赵莉 | R121: 190 | S121: {=VLOOKUP(Q121&R121,IF({1,0},$B$2:$B$330&$F$2:$F$330,$C$2:$C$330),2,)} -> 50065 | T121: {=VLOOKUP(Q121&R121,IF({1,0},$B$2:$B$330&$F$2:$F$330,$D$2:$D$330),2,)} -> 结构二室 | U121: {=VLOOKUP(Q121&R121,IF({1,0},$B$2:$B$330&$F$2:$F$330,$E$2:$E$330),2,)} -> C929设计（2025年复材中心） | V121: {=VLOOKUP(Q121&R121,IF({1,0},$B$2:$B$330&$F$2:$F$330,$N$2:$N$330),2,)} -> YZ40000418
A122: =ROW()-1 -> 121 | B122: 李忠霖 | C122: =IFERROR(VLOOKUP(B122,[66]工程研发事业部人员名单!B:D,2,0),"") -> 23524 | D122: =IFERROR(VLOOKUP(B122,[66]工程研发事业部人员名单!B:D,3,0),"") -> 强度室 | E122: 重点工作任务 | F122: =G122+H122+I122+J122 -> 15 | I122: 15 | K122: 强度 | M122: 校对审核修改全部27份S-技术文件 | N122: =VLOOKUP(E122,订单号!B:C,2,0) -> 0 | O122: =VLOOKUP(C122,领导干部!B:B,1,0) -> #N/A | Q122: 赵书凯 | R122: 160 | S122: {=VLOOKUP(Q122&R122,IF({1,0},$B$2:$B$330&$F$2:$F$330,$C$2:$C$330),2,)} -> 50832 | T122: {=VLOOKUP(Q122&R122,IF({1,0},$B$2:$B$330&$F$2:$F$330,$D$2:$D$330),2,)} -> 联络工程室 | U122: {=VLOOKUP(Q122&R122,IF({1,0},$B$2:$B$330&$F$2:$F$330,$E$2:$E$330),2,)} -> 工程支持 | V122: {=VLOOKUP(Q122&R122,IF({1,0},$B$2:$B$330&$F$2:$F$330,$N$2:$N$330),2,)} -> 10502
A123: =ROW()-1 -> 122 | B123: 靳海丰 | C123: =IFERROR(VLOOKUP(B123,[66]工程研发事业部人员名单!B:D,2,0),"") -> 51158 | D123: =IFERROR(VLOOKUP(B123,[66]工程研发事业部人员名单!B:D,3,0),"") -> 强度室 | E123: 重点工作任务 | F123: =G123+H123+I123+J123 -> 2.5 | I123: 2.5 | K123: 强度 | M123: 编制S-2023GD-0002 舱门结构强度分析流程 校对S-2024GD-0002 结构疲劳载荷谱编制流程 | N123: =VLOOKUP(E123,订单号!B:C,2,0) -> 0 | O123: =VLOOKUP(C123,领导干部!B:B,1,0) -> #N/A | Q123: 赵婷 | R123: 112 | S123: {=VLOOKUP(Q123&R123,IF({1,0},$B$2:$B$330&$F$2:$F$330,$C$2:$C$330),2,)} -> 50702 | T123: {=VLOOKUP(Q123&R123,IF({1,0},$B$2:$B$330&$F$2:$F$330,$D$2:$D$330),2,)} -> 总体室 | U123: {=VLOOKUP(Q123&R123,IF({1,0},$B$2:$B$330&$F$2:$F$330,$E$2:$E$330),2,)} -> WH1项目总体/系统/适航等其它专业 | V123: {=VLOOKUP(Q123&R123,IF({1,0},$B$2:$B$330&$F$2:$F$330,$N$2:$N$330),2,)} -> YZ-RD202428
A124: =ROW()-1 -> 123 | B124: 陈诗春 | C124: =IFERROR(VLOOKUP(B124,[66]工程研发事业部人员名单!B:D,2,0),"") -> 52153 | D124: =IFERROR(VLOOKUP(B124,[66]工程研发事业部人员名单!B:D,3,0),"") -> 强度室 | E124: 重点工作任务 | F124: =G124+H124+I124+J124 -> 12 | I124: 12 | K124: 强度 | M124: 编制S-2027GD-0008强度试验数据有效性分析要求及分析方法 编制S-2027GD-0009试验前质量检查管理规定 编制S-2027GD-0010试验件验收管理规定 编制S-2027GD-0011试验界面控制数据集（TICD）的编写要求 编制S-2027GD-0012试验技术协调单的管理规定 校对四份技术文件 | N124: =VLOOKUP(E124,订单号!B:C,2,0) -> 0 | O124: =VLOOKUP(C124,领导干部!B:B,1,0) -> #N/A | Q124: 赵艳秦 | R124: 210 | S124: {=VLOOKUP(Q124&R124,IF({1,0},$B$2:$B$330&$F$2:$F$330,$C$2:$C$330),2,)} -> 50022 | T124: {=VLOOKUP(Q124&R124,IF({1,0},$B$2:$B$330&$F$2:$F$330,$D$2:$D$330),2,)} -> 结构二室 | U124: {=VLOOKUP(Q124&R124,IF({1,0},$B$2:$B$330&$F$2:$F$330,$E$2:$E$330),2,)} -> C919YJTD设计 | V124: {=VLOOKUP(Q124&R124,IF({1,0},$B$2:$B$330&$F$2:$F$330,$N$2:$N$330),2,)} -> YZ40000410
A125: =ROW()-1 -> 124 | B125: 乔志斌 | C125: =IFERROR(VLOOKUP(B125,[66]工程研发事业部人员名单!B:D,2,0),"") -> 53422 | D125: =IFERROR(VLOOKUP(B125,[66]工程研发事业部人员名单!B:D,3,0),"") -> 强度室 | E125: 重点工作任务 | F125: =G125+H125+I125+J125 -> 5.5 | I125: 5.5 | K125: 强度 | M125: 编制两份、校对三份 | N125: =VLOOKUP(E125,订单号!B:C,2,0) -> 0 | O125: =VLOOKUP(C125,领导干部!B:B,1,0) -> #N/A | Q125: 赵永利 | R125: 100 | S125: {=VLOOKUP(Q125&R125,IF({1,0},$B$2:$B$330&$F$2:$F$330,$C$2:$C$330),2,)} -> 28161 | T125: {=VLOOKUP(Q125&R125,IF({1,0},$B$2:$B$330&$F$2:$F$330,$D$2:$D$330),2,)} -> 强度室 | U125: {=VLOOKUP(Q125&R125,IF({1,0},$B$2:$B$330&$F$2:$F$330,$E$2:$E$330),2,)} -> WH1项目结构强度综合 | V125: {=VLOOKUP(Q125&R125,IF({1,0},$B$2:$B$330&$F$2:$F$330,$N$2:$N$330),2,)} -> YZ-RD202428
A126: =ROW()-1 -> 125 | B126: 孟维宇 | C126: =IFERROR(VLOOKUP(B126,[66]工程研发事业部人员名单!B:D,2,0),"") -> 50722 | D126: =IFERROR(VLOOKUP(B126,[66]工程研发事业部人员名单!B:D,3,0),"") -> 强度室 | E126: 重点工作任务 | F126: =G126+H126+I126+J126 -> 0.5 | I126: 0.5 | K126: 强度 | M126: 校对一份 | N126: =VLOOKUP(E126,订单号!B:C,2,0) -> 0 | O126: =VLOOKUP(C126,领导干部!B:B,1,0) -> #N/A | Q126: 赵长辉 | R126: 120 | S126: {=VLOOKUP(Q126&R126,IF({1,0},$B$2:$B$330&$F$2:$F$330,$C$2:$C$330),2,)} -> 17725 | T126: {=VLOOKUP(Q126&R126,IF({1,0},$B$2:$B$330&$F$2:$F$330,$D$2:$D$330),2,)} -> 总体室 | U126: {=VLOOKUP(Q126&R126,IF({1,0},$B$2:$B$330&$F$2:$F$330,$E$2:$E$330),2,)} -> 巡飞无人机课题 | V126: {=VLOOKUP(Q126&R126,IF({1,0},$B$2:$B$330&$F$2:$F$330,$N$2:$N$330),2,)} -> YZ40000403
A127: =ROW()-1 -> 126 | B127: 王岩 | C127: =IFERROR(VLOOKUP(B127,[66]工程研发事业部人员名单!B:D,2,0),"") -> 51175 | D127: =IFERROR(VLOOKUP(B127,[66]工程研发事业部人员名单!B:D,3,0),"") -> 强度室 | E127: 重点工作任务 | F127: =G127+H127+I127+J127 -> 5 | I127: 5 | K127: 强度 | M127: 编制两份、校对两份 | N127: =VLOOKUP(E127,订单号!B:C,2,0) -> 0 | O127: =VLOOKUP(C127,领导干部!B:B,1,0) -> #N/A | Q127: 郑石 | R127: 131 | S127: {=VLOOKUP(Q127&R127,IF({1,0},$B$2:$B$330&$F$2:$F$330,$C$2:$C$330),2,)} -> 26766 | T127: {=VLOOKUP(Q127&R127,IF({1,0},$B$2:$B$330&$F$2:$F$330,$D$2:$D$330),2,)} -> 强度室 | U127: {=VLOOKUP(Q127&R127,IF({1,0},$B$2:$B$330&$F$2:$F$330,$E$2:$E$330),2,)} -> C919基本型设计（2025年上飞院） | V127: {=VLOOKUP(Q127&R127,IF({1,0},$B$2:$B$330&$F$2:$F$330,$N$2:$N$330),2,)} -> YZ40000419
A128: =ROW()-1 -> 127 | B128: 刘曦 | C128: =IFERROR(VLOOKUP(B128,[66]工程研发事业部人员名单!B:D,2,0),"") -> 52130 | D128: =IFERROR(VLOOKUP(B128,[66]工程研发事业部人员名单!B:D,3,0),"") -> 强度室 | E128: 重点工作任务 | F128: =G128+H128+I128+J128 -> 4.5 | I128: 4.5 | K128: 强度 | M128: 编制两份、校对一份 | N128: =VLOOKUP(E128,订单号!B:C,2,0) -> 0 | O128: =VLOOKUP(C128,领导干部!B:B,1,0) -> #N/A | Q128: 支晗 | R128: 243 | S128: {=VLOOKUP(Q128&R128,IF({1,0},$B$2:$B$330&$F$2:$F$330,$C$2:$C$330),2,)} -> 51589 | T128: {=VLOOKUP(Q128&R128,IF({1,0},$B$2:$B$330&$F$2:$F$330,$D$2:$D$330),2,)} -> 强度室 | U128: {=VLOOKUP(Q128&R128,IF({1,0},$B$2:$B$330&$F$2:$F$330,$E$2:$E$330),2,)} -> C919基本型设计（2025年上飞院） | V128: {=VLOOKUP(Q128&R128,IF({1,0},$B$2:$B$330&$F$2:$F$330,$N$2:$N$330),2,)} -> YZ40000419
A129: =ROW()-1 -> 128 | B129: 朱照泽 | C129: =IFERROR(VLOOKUP(B129,[66]工程研发事业部人员名单!B:D,2,0),"") -> 51763 | D129: =IFERROR(VLOOKUP(B129,[66]工程研发事业部人员名单!B:D,3,0),"") -> 强度室 | E129: 重点工作任务 | F129: =G129+H129+I129+J129 -> 0.5 | I129: 0.5 | K129: 强度 | M129: 校对一份 | N129: =VLOOKUP(E129,订单号!B:C,2,0) -> 0 | O129: =VLOOKUP(C129,领导干部!B:B,1,0) -> #N/A | Q129: 周弘扬 | R129: 180 | S129: {=VLOOKUP(Q129&R129,IF({1,0},$B$2:$B$330&$F$2:$F$330,$C$2:$C$330),2,)} -> #N/A | T129: {=VLOOKUP(Q129&R129,IF({1,0},$B$2:$B$330&$F$2:$F$330,$D$2:$D$330),2,)} -> #N/A | U129: {=VLOOKUP(Q129&R129,IF({1,0},$B$2:$B$330&$F$2:$F$330,$E$2:$E$330),2,)} -> #N/A | V129: {=VLOOKUP(Q129&R129,IF({1,0},$B$2:$B$330&$F$2:$F$330,$N$2:$N$330),2,)} -> #N/A
A130: =ROW()-1 -> 129 | B130: 张铎耀 | C130: =IFERROR(VLOOKUP(B130,[66]工程研发事业部人员名单!B:D,2,0),"") -> 52581 | D130: =IFERROR(VLOOKUP(B130,[66]工程研发事业部人员名单!B:D,3,0),"") -> 强度室 | E130: 重点工作任务 | F130: =G130+H130+I130+J130 -> 14 | I130: 14 | K130: 强度 | M130: 编制6份，校对5份 | N130: =VLOOKUP(E130,订单号!B:C,2,0) -> 0 | O130: =VLOOKUP(C130,领导干部!B:B,1,0) -> #N/A | Q130: 周莫普 | R130: 210 | S130: {=VLOOKUP(Q130&R130,IF({1,0},$B$2:$B$330&$F$2:$F$330,$C$2:$C$330),2,)} -> #N/A | T130: {=VLOOKUP(Q130&R130,IF({1,0},$B$2:$B$330&$F$2:$F$330,$D$2:$D$330),2,)} -> #N/A | U130: {=VLOOKUP(Q130&R130,IF({1,0},$B$2:$B$330&$F$2:$F$330,$E$2:$E$330),2,)} -> #N/A | V130: {=VLOOKUP(Q130&R130,IF({1,0},$B$2:$B$330&$F$2:$F$330,$N$2:$N$330),2,)} -> #N/A
A131: =ROW()-1 -> 130 | B131: 纪可 | C131: =IFERROR(VLOOKUP(B131,[66]工程研发事业部人员名单!B:D,2,0),"") -> 26689 | D131: =IFERROR(VLOOKUP(B131,[66]工程研发事业部人员名单!B:D,3,0),"") -> 强度室 | E131: 重点工作任务 | F131: =G131+H131+I131+J131 -> 6 | I131: 6 | K131: 强度 | M131: 编制S-2025GD-0010 机构强度分析流程 编制S-2025GD-0011 舱门机构强度分析流程 编制S-2025GD-0012 机构强度分析报告的编写要求 | N131: =VLOOKUP(E131,订单号!B:C,2,0) -> 0 | O131: =VLOOKUP(C131,领导干部!B:B,1,0) -> #N/A | Q131: 周天一 | R131: 170 | S131: {=VLOOKUP(Q131&R131,IF({1,0},$B$2:$B$330&$F$2:$F$330,$C$2:$C$330),2,)} -> #N/A | T131: {=VLOOKUP(Q131&R131,IF({1,0},$B$2:$B$330&$F$2:$F$330,$D$2:$D$330),2,)} -> #N/A | U131: {=VLOOKUP(Q131&R131,IF({1,0},$B$2:$B$330&$F$2:$F$330,$E$2:$E$330),2,)} -> #N/A | V131: {=VLOOKUP(Q131&R131,IF({1,0},$B$2:$B$330&$F$2:$F$330,$N$2:$N$330),2,)} -> #N/A
A132: =ROW()-1 -> 131 | B132: 朱海 | C132: =IFERROR(VLOOKUP(B132,[66]工程研发事业部人员名单!B:D,2,0),"") -> 52232 | D132: =IFERROR(VLOOKUP(B132,[66]工程研发事业部人员名单!B:D,3,0),"") -> 结构二室 | E132: 重点工作任务 | F132: =G132+H132+I132+J132 -> 100 | I132: 100 | M132: 1.换号S-文件《数据集成熟度管理规定》等31份文件，完成100%（更换31份文件编号，更新每份文件内容，更新对应PPT内容） | N132: =VLOOKUP(E132,订单号!B:C,2,0) -> 0 | O132: =VLOOKUP(C132,领导干部!B:B,1,0) -> #N/A | Q132: 朱海 | R132: 100 | S132: {=VLOOKUP(Q132&R132,IF({1,0},$B$2:$B$330&$F$2:$F$330,$C$2:$C$330),2,)} -> 52232 | T132: {=VLOOKUP(Q132&R132,IF({1,0},$B$2:$B$330&$F$2:$F$330,$D$2:$D$330),2,)} -> 结构二室 | U132: {=VLOOKUP(Q132&R132,IF({1,0},$B$2:$B$330&$F$2:$F$330,$E$2:$E$330),2,)} -> 重点工作任务 | V132: {=VLOOKUP(Q132&R132,IF({1,0},$B$2:$B$330&$F$2:$F$330,$N$2:$N$330),2,)} -> 0
A133: =ROW()-1 -> 132 | B133: 吴晓莉 | C133: =IFERROR(VLOOKUP(B133,[66]工程研发事业部人员名单!B:D,2,0),"") -> 50872 | D133: =IFERROR(VLOOKUP(B133,[66]工程研发事业部人员名单!B:D,3,0),"") -> 系统室 | E133: 重点工作任务 | F133: =G133+H133+I133+J133 -> 17 | I133: 17 | M133: 1.S-文件，5份换号、换模版、正文内容引用更改等-5h 2.S-文件，1份换号、换模版、正文内容引用更改，正文内容补充及修改等-10h 3.S-文件，校对3份-2h | N133: =VLOOKUP(E133,订单号!B:C,2,0) -> 0 | O133: =VLOOKUP(C133,领导干部!B:B,1,0) -> #N/A | Q133: 朱照泽 | R133: 210 | S133: {=VLOOKUP(Q133&R133,IF({1,0},$B$2:$B$330&$F$2:$F$330,$C$2:$C$330),2,)} -> #N/A | T133: {=VLOOKUP(Q133&R133,IF({1,0},$B$2:$B$330&$F$2:$F$330,$D$2:$D$330),2,)} -> #N/A | U133: {=VLOOKUP(Q133&R133,IF({1,0},$B$2:$B$330&$F$2:$F$330,$E$2:$E$330),2,)} -> #N/A | V133: {=VLOOKUP(Q133&R133,IF({1,0},$B$2:$B$330&$F$2:$F$330,$N$2:$N$330),2,)} -> #N/A
A134: =ROW()-1 -> 133 | B134: 李妍 | C134: =IFERROR(VLOOKUP(B134,[66]工程研发事业部人员名单!B:D,2,0),"") -> 51435 | D134: =IFERROR(VLOOKUP(B134,[66]工程研发事业部人员名单!B:D,3,0),"") -> 系统室 | E134: 重点工作任务 | F134: =G134+H134+I134+J134 -> 15 | I134: 15 | M134: 1.S-文件，12份-换号、换模版、正文内容引用更改、打印签字等-10h 2.S-文件，19份-校对-5h | N134: =VLOOKUP(E134,订单号!B:C,2,0) -> 0 | O134: =VLOOKUP(C134,领导干部!B:B,1,0) -> #N/A | Q134: 陈诗春 | R134: 180 | S134: {=VLOOKUP(Q134&R134,IF({1,0},$B$2:$B$330&$F$2:$F$330,$C$2:$C$330),2,)} -> 52153 | T134: {=VLOOKUP(Q134&R134,IF({1,0},$B$2:$B$330&$F$2:$F$330,$D$2:$D$330),2,)} -> 强度室 | U134: {=VLOOKUP(Q134&R134,IF({1,0},$B$2:$B$330&$F$2:$F$330,$E$2:$E$330),2,)} -> C929设计（2025年上飞院） | V134: {=VLOOKUP(Q134&R134,IF({1,0},$B$2:$B$330&$F$2:$F$330,$N$2:$N$330),2,)} -> YZ40000415
A135: =ROW()-1 -> 134 | B135: 刘超 | C135: =IFERROR(VLOOKUP(B135,[66]工程研发事业部人员名单!B:D,2,0),"") -> 51430 | D135: =IFERROR(VLOOKUP(B135,[66]工程研发事业部人员名单!B:D,3,0),"") -> 系统室 | E135: 重点工作任务 | F135: =G135+H135+I135+J135 -> 7 | I135: 7 | M135: 1.S-文件，3份-换号、换模版、正文内容引用更改、打印签字等-5h 2.S-文件，3份-校对-2h | N135: =VLOOKUP(E135,订单号!B:C,2,0) -> 0 | O135: =VLOOKUP(C135,领导干部!B:B,1,0) -> #N/A | Q135: 乔志斌 | R135: 170 | S135: {=VLOOKUP(Q135&R135,IF({1,0},$B$2:$B$330&$F$2:$F$330,$C$2:$C$330),2,)} -> 53422 | T135: {=VLOOKUP(Q135&R135,IF({1,0},$B$2:$B$330&$F$2:$F$330,$D$2:$D$330),2,)} -> 强度室 | U135: {=VLOOKUP(Q135&R135,IF({1,0},$B$2:$B$330&$F$2:$F$330,$E$2:$E$330),2,)} -> C919基本型设计（2025年上飞院） | V135: {=VLOOKUP(Q135&R135,IF({1,0},$B$2:$B$330&$F$2:$F$330,$N$2:$N$330),2,)} -> YZ40000419
A136: =ROW()-1 -> 135 | B136: 夏雷 | C136: =IFERROR(VLOOKUP(B136,[66]工程研发事业部人员名单!B:D,2,0),"") -> 52587 | D136: =IFERROR(VLOOKUP(B136,[66]工程研发事业部人员名单!B:D,3,0),"") -> 系统室 | E136: 重点工作任务 | F136: =G136+H136+I136+J136 -> 20 | I136: 20 | M136: 1.S-文件，22份-换号、换模版、正文内容引用更改、补充附录等-20h | N136: =VLOOKUP(E136,订单号!B:C,2,0) -> 0 | O136: =VLOOKUP(C136,领导干部!B:B,1,0) -> #N/A | Q136: 祝堃 | R136: 200 | S136: {=VLOOKUP(Q136&R136,IF({1,0},$B$2:$B$330&$F$2:$F$330,$C$2:$C$330),2,)} -> 52256 | T136: {=VLOOKUP(Q136&R136,IF({1,0},$B$2:$B$330&$F$2:$F$330,$D$2:$D$330),2,)} -> 强度室 | U136: {=VLOOKUP(Q136&R136,IF({1,0},$B$2:$B$330&$F$2:$F$330,$E$2:$E$330),2,)} -> C919基本型设计（2025年上飞院） | V136: {=VLOOKUP(Q136&R136,IF({1,0},$B$2:$B$330&$F$2:$F$330,$N$2:$N$330),2,)} -> YZ40000419
A137: =ROW()-1 -> 136 | B137: 骆美玲 | C137: =IFERROR(VLOOKUP(B137,[66]工程研发事业部人员名单!B:D,2,0),"") -> 50713 | D137: =IFERROR(VLOOKUP(B137,[66]工程研发事业部人员名单!B:D,3,0),"") -> 系统室 | E137: 重点工作任务 | F137: =G137+H137+I137+J137 -> 12 | I137: 12 | M137: 1.S-文件，3份-换号、换模版、正文内容引用更改、打印签字等-3h 2.S-文件，1份换号、换模版、正文内容引用更改，正文内容补充及修改等-6h 3.S-文件，4份-校对-3h | N137: =VLOOKUP(E137,订单号!B:C,2,0) -> 0 | O137: =VLOOKUP(C137,领导干部!B:B,1,0) -> #N/A | Q137: 杨帆 | R137: 200 | S137: {=VLOOKUP(Q137&R137,IF({1,0},$B$2:$B$330&$F$2:$F$330,$C$2:$C$330),2,)} -> 25078 | T137: {=VLOOKUP(Q137&R137,IF({1,0},$B$2:$B$330&$F$2:$F$330,$D$2:$D$330),2,)} -> 结构一室 | U137: {=VLOOKUP(Q137&R137,IF({1,0},$B$2:$B$330&$F$2:$F$330,$E$2:$E$330),2,)} -> C929设计（2025年复材中心） | V137: {=VLOOKUP(Q137&R137,IF({1,0},$B$2:$B$330&$F$2:$F$330,$N$2:$N$330),2,)} -> YZ40000418
A138: =ROW()-1 -> 137 | B138: 万方 | C138: =IFERROR(VLOOKUP(B138,[66]工程研发事业部人员名单!B:D,2,0),"") -> 51387 | D138: =IFERROR(VLOOKUP(B138,[66]工程研发事业部人员名单!B:D,3,0),"") -> 系统室 | E138: 重点工作任务 | F138: =G138+H138+I138+J138 -> 20 | I138: 20 | M138: 1.S-文件10份-换号、换模版、正文内容引用更改、打印签字等-10h 2.S-文件2份-换号、换模版、正文内容引用更改，章节号更新、正文内容补充及修改等-4h 3.S-文件17份-校对-6h | N138: =VLOOKUP(E138,订单号!B:C,2,0) -> 0 | O138: =VLOOKUP(C138,领导干部!B:B,1,0) -> #N/A | Q138: 崔建军 | R138: 190 | S138: {=VLOOKUP(Q138&R138,IF({1,0},$B$2:$B$330&$F$2:$F$330,$C$2:$C$330),2,)} -> 51647 | T138: {=VLOOKUP(Q138&R138,IF({1,0},$B$2:$B$330&$F$2:$F$330,$D$2:$D$330),2,)} -> 结构一室 | U138: {=VLOOKUP(Q138&R138,IF({1,0},$B$2:$B$330&$F$2:$F$330,$E$2:$E$330),2,)} -> C929设计（2025年上飞院） | V138: {=VLOOKUP(Q138&R138,IF({1,0},$B$2:$B$330&$F$2:$F$330,$N$2:$N$330),2,)} -> YZ40000415
A139: =ROW()-1 -> 138 | B139: 任斌 | C139: =IFERROR(VLOOKUP(B139,[66]工程研发事业部人员名单!B:D,2,0),"") -> 51517 | D139: =IFERROR(VLOOKUP(B139,[66]工程研发事业部人员名单!B:D,3,0),"") -> 系统室 | E139: 重点工作任务 | F139: =G139+H139+I139+J139 -> 10 | I139: 10 | M139: 1.编制文件《S-2041ZN-2001Rev.A_液压系统部件设计要求》-3h； 2.校对《引气系统安装设计要求》-1h 3.校对《民用飞机系统安装设计流程指南》-2h 4.校对《CATIA管路模块使用指南》-4h | N139: =VLOOKUP(E139,订单号!B:C,2,0) -> 0 | O139: =VLOOKUP(C139,领导干部!B:B,1,0) -> #N/A | Q139: 王君元 | R139: 160 | S139: {=VLOOKUP(Q139&R139,IF({1,0},$B$2:$B$330&$F$2:$F$330,$C$2:$C$330),2,)} -> 50735 | T139: {=VLOOKUP(Q139&R139,IF({1,0},$B$2:$B$330&$F$2:$F$330,$D$2:$D$330),2,)} -> 结构一室 | U139: {=VLOOKUP(Q139&R139,IF({1,0},$B$2:$B$330&$F$2:$F$330,$E$2:$E$330),2,)} -> C929设计（2025年上飞院） | V139: {=VLOOKUP(Q139&R139,IF({1,0},$B$2:$B$330&$F$2:$F$330,$N$2:$N$330),2,)} -> YZ40000415
A140: =ROW()-1 -> 139 | B140: 刘凯男 | C140: =IFERROR(VLOOKUP(B140,[66]工程研发事业部人员名单!B:D,2,0),"") -> 52156 | D140: =IFERROR(VLOOKUP(B140,[66]工程研发事业部人员名单!B:D,3,0),"") -> 系统室 | E140: 重点工作任务 | F140: =G140+H140+I140+J140 -> 10 | I140: 10 | M140: 1.S-文件，11份-换号、换模版、正文内容引用更改、打印签字等-3h 2.S-文件，1份换号、换模版、正文内容引用更改，正文内容补充及修改等-2h 3.S-文件，16份-校对-5h | N140: =VLOOKUP(E140,订单号!B:C,2,0) -> 0 | O140: =VLOOKUP(C140,领导干部!B:B,1,0) -> #N/A | Q140: (空白) | R140: 0 | S140: {=VLOOKUP(Q140&R140,IF({1,0},$B$2:$B$330&$F$2:$F$330,$C$2:$C$330),2,)} -> #N/A | T140: {=VLOOKUP(Q140&R140,IF({1,0},$B$2:$B$330&$F$2:$F$330,$D$2:$D$330),2,)} -> #N/A | U140: {=VLOOKUP(Q140&R140,IF({1,0},$B$2:$B$330&$F$2:$F$330,$E$2:$E$330),2,)} -> #N/A | V140: {=VLOOKUP(Q140&R140,IF({1,0},$B$2:$B$330&$F$2:$F$330,$N$2:$N$330),2,)} -> #N/A
A141: =ROW()-1 -> 140 | B141: 宋凯 | C141: =IFERROR(VLOOKUP(B141,[66]工程研发事业部人员名单!B:D,2,0),"") -> 51951 | D141: =IFERROR(VLOOKUP(B141,[66]工程研发事业部人员名单!B:D,3,0),"") -> 系统室 | E141: 重点工作任务 | F141: =G141+H141+I141+J141 -> 16 | I141: 16 | M141: 1.S-文件，3份换号，换号、换模版、更改正文格式、打印签字等。（一份60多页，一份90多页）-13h 2.S-文件，3份校对工作-3h | N141: =VLOOKUP(E141,订单号!B:C,2,0) -> 0 | O141: =VLOOKUP(C141,领导干部!B:B,1,0) -> #N/A | Q141: 费天行 | R141: 100 | S141: {=VLOOKUP(Q141&R141,IF({1,0},$B$2:$B$330&$F$2:$F$330,$C$2:$C$330),2,)} -> 52570 | T141: {=VLOOKUP(Q141&R141,IF({1,0},$B$2:$B$330&$F$2:$F$330,$D$2:$D$330),2,)} -> 工程项目室 /适航工程室 | U141: {=VLOOKUP(Q141&R141,IF({1,0},$B$2:$B$330&$F$2:$F$330,$E$2:$E$330),2,)} -> C919高原型设计（2025年上飞院） | V141: {=VLOOKUP(Q141&R141,IF({1,0},$B$2:$B$330&$F$2:$F$330,$N$2:$N$330),2,)} -> YZ40000417
A142: =ROW()-1 -> 141 | B142: 刘媛媛 | C142: =IFERROR(VLOOKUP(B142,[66]工程研发事业部人员名单!B:D,2,0),"") -> 51385 | D142: =IFERROR(VLOOKUP(B142,[66]工程研发事业部人员名单!B:D,3,0),"") -> 系统室 | E142: 重点工作任务 | F142: =G142+H142+I142+J142 -> 20 | I142: 20 | M142: 1.S-文件，5份-换号、换模版、正文内容引用更改、打印签字等-8h 2.S-文件，15份-校对-8h 3.科室全部文件打印并走审签流程，及相关问题解决-4h | N142: =VLOOKUP(E142,订单号!B:C,2,0) -> 0 | O142: =VLOOKUP(C142,领导干部!B:B,1,0) -> #N/A | Q142: 王佳琪 | R142: 170 | S142: {=VLOOKUP(Q142&R142,IF({1,0},$B$2:$B$330&$F$2:$F$330,$C$2:$C$330),2,)} -> 52341 | T142: {=VLOOKUP(Q142&R142,IF({1,0},$B$2:$B$330&$F$2:$F$330,$D$2:$D$330),2,)} -> 结构二室 | U142: {=VLOOKUP(Q142&R142,IF({1,0},$B$2:$B$330&$F$2:$F$330,$E$2:$E$330),2,)} -> C929设计（2025年上飞院） | V142: {=VLOOKUP(Q142&R142,IF({1,0},$B$2:$B$330&$F$2:$F$330,$N$2:$N$330),2,)} -> YZ40000415
A143: =ROW()-1 -> 142 | B143: 魏春生 | C143: =IFERROR(VLOOKUP(B143,[66]工程研发事业部人员名单!B:D,2,0),"") -> 51389 | D143: =IFERROR(VLOOKUP(B143,[66]工程研发事业部人员名单!B:D,3,0),"") -> 系统室 | E143: 重点工作任务 | F143: =G143+H143+I143+J143 -> 5 | I143: 5 | M143: 1.S-文件，7份-换号、换模版、正文内容引用更改、打印签字等-3h 2.S-文件，5份-校对-2h | N143: =VLOOKUP(E143,订单号!B:C,2,0) -> 0 | O143: =VLOOKUP(C143,领导干部!B:B,1,0) -> #N/A | Q143: 李泽霖 | R143: 170 | S143: {=VLOOKUP(Q143&R143,IF({1,0},$B$2:$B$330&$F$2:$F$330,$C$2:$C$330),2,)} -> 52569 | T143: {=VLOOKUP(Q143&R143,IF({1,0},$B$2:$B$330&$F$2:$F$330,$D$2:$D$330),2,)} -> 强度室 | U143: {=VLOOKUP(Q143&R143,IF({1,0},$B$2:$B$330&$F$2:$F$330,$E$2:$E$330),2,)} -> C929设计（2025年上飞院） | V143: {=VLOOKUP(Q143&R143,IF({1,0},$B$2:$B$330&$F$2:$F$330,$N$2:$N$330),2,)} -> YZ40000415
A144: =ROW()-1 -> 143 | B144: 赵子维 | C144: =IFERROR(VLOOKUP(B144,[66]工程研发事业部人员名单!B:D,2,0),"") -> 52585 | D144: =IFERROR(VLOOKUP(B144,[66]工程研发事业部人员名单!B:D,3,0),"") -> 系统室 | E144: 重点工作任务 | F144: =G144+H144+I144+J144 -> 6 | I144: 6 | M144: 1.S-文件，6份-换号、换模版、正文内容引用更改、补充附录等-20h | N144: =VLOOKUP(E144,订单号!B:C,2,0) -> 0 | O144: =VLOOKUP(C144,领导干部!B:B,1,0) -> #N/A | Q144: 徐楚桓 | R144: 180 | S144: {=VLOOKUP(Q144&R144,IF({1,0},$B$2:$B$330&$F$2:$F$330,$C$2:$C$330),2,)} -> 52579 | T144: {=VLOOKUP(Q144&R144,IF({1,0},$B$2:$B$330&$F$2:$F$330,$D$2:$D$330),2,)} -> 结构一室 | U144: {=VLOOKUP(Q144&R144,IF({1,0},$B$2:$B$330&$F$2:$F$330,$E$2:$E$330),2,)} -> C929设计（2025年复材中心） | V144: {=VLOOKUP(Q144&R144,IF({1,0},$B$2:$B$330&$F$2:$F$330,$N$2:$N$330),2,)} -> YZ40000418
A145: =ROW()-1 -> 144 | B145: 许美娟 | C145: =IFERROR(VLOOKUP(B145,[66]工程研发事业部人员名单!B:D,2,0),"") -> 51194 | D145: =IFERROR(VLOOKUP(B145,[66]工程研发事业部人员名单!B:D,3,0),"") -> 强度室 | E145: WH1项目结构强度综合 | F145: =G145+H145+I145+J145 -> 213 | I145: 213 | K145: 强度 | L145: 机身 | M145: 1）瘦身模型中机身后段gfem建模，合并中机身及全机模型，建立各段连接 2）组织提取瘦身模型全机质量点 3）瘦身前模型，机翼蒙皮、梁分组及尺寸提取，梁腹板稳定性分析和优化 4）瘦身模型加长桁加筋条，加载输入文件处理，模型调试 5）全机模型配平方法研究和对比，载荷分载研究和对比 | N145: =VLOOKUP(E145,订单号!B:C,2,0) -> YZ-RD202428 | O145: =VLOOKUP(C145,领导干部!B:B,1,0) -> #N/A | Q145: 刘岩东 | R145: 150 | S145: {=VLOOKUP(Q145&R145,IF({1,0},$B$2:$B$330&$F$2:$F$330,$C$2:$C$330),2,)} -> 50245 | T145: {=VLOOKUP(Q145&R145,IF({1,0},$B$2:$B$330&$F$2:$F$330,$D$2:$D$330),2,)} -> 联络工程室 | U145: {=VLOOKUP(Q145&R145,IF({1,0},$B$2:$B$330&$F$2:$F$330,$E$2:$E$330),2,)} -> 工程支持 | V145: {=VLOOKUP(Q145&R145,IF({1,0},$B$2:$B$330&$F$2:$F$330,$N$2:$N$330),2,)} -> 10502
...

Sheet X月项目工时 (固定公式)
A1: 序号 | B1: 姓名 | C1: 胸卡号 | D1: 专业室 | E1: 项目简称 | F1: 个人原始项目工时之和/h | G1: 第一年跨专业原始项目工时/h | H1: 第二年跨专业原始项目工时/h | I1: 沈阳工时/h | J1: 市外出差工时/h | K1: 专业 | L1: 工作包 | M1: 主要工作任务 （请简要说明每项设计任务、工时及所属任务通知单编号） 例：序号.工作包-任务通知单编号-设计任务-工时 | N1: 订单号 | O1: 是否国际 | Q1: 姓名 | R1: 最大值项:个人原始项目工时之和/h | S1: 订单号 | T1: 项目简称 | U1: 胸卡号 | V1: 专业室
A2: =ROW()-1 -> 1 | B2: 赵艳秦 | C2: =IFERROR(VLOOKUP(B2,[1]工程研发事业部人员名单!B:D,2,0),"") -> 50022 | D2: =IFERROR(VLOOKUP(B2,[1]工程研发事业部人员名单!B:D,3,0),"") -> 结构二室 | E2: CR929设计（2022年复材中心） | F2: =G2+H2+I2+J2 -> 180 | I2: 180 | K2: 结构 | L2: 前机身 | N2: =VLOOKUP(E2,订单号!B:C,2,0) -> #N/A | O2: =VLOOKUP(C2,领导干部!B:B,1,0) -> #N/A | Q2: 柴宝 | R2: 200 | S2: {=VLOOKUP(Q2&R2,IF({1,0},$B$2:$B$464&$F$2:$F$464,$N$2:$N$464),2,)} -> #N/A | T2: {=VLOOKUP(Q2&R2,IF({1,0},$B$2:$B$464&$F$2:$F$464,$E$2:$E$464),2,)} -> CR929设计（2022年复材中心） | U2: {=VLOOKUP(Q2&R2,IF({1,0},$B$2:$B$464&$F$2:$F$464,$C$2:$C$464),2,)} -> 51944 | V2: {=VLOOKUP(Q2&R2,IF({1,0},$B$2:$B$464&$F$2:$F$464,$D$2:$D$464),2,)} -> 强度室
A3: =ROW()-1 -> 2 | B3: 陈杰 | C3: =IFERROR(VLOOKUP(B3,[1]工程研发事业部人员名单!B:D,2,0),"") -> 25600 | D3: =IFERROR(VLOOKUP(B3,[1]工程研发事业部人员名单!B:D,3,0),"") -> 结构二室 | E3: CR929设计（2022年复材中心） | F3: =G3+H3+I3+J3 -> 160 | I3: 160 | K3: 结构 | L3: 前机身 | N3: =VLOOKUP(E3,订单号!B:C,2,0) -> #N/A | O3: =VLOOKUP(C3,领导干部!B:B,1,0) -> #N/A | Q3: 陈杰 | R3: 160 | S3: {=VLOOKUP(Q3&R3,IF({1,0},$B$2:$B$464&$F$2:$F$464,$N$2:$N$464),2,)} -> #N/A | T3: {=VLOOKUP(Q3&R3,IF({1,0},$B$2:$B$464&$F$2:$F$464,$E$2:$E$464),2,)} -> CR929设计（2022年复材中心） | U3: {=VLOOKUP(Q3&R3,IF({1,0},$B$2:$B$464&$F$2:$F$464,$C$2:$C$464),2,)} -> 25600 | V3: {=VLOOKUP(Q3&R3,IF({1,0},$B$2:$B$464&$F$2:$F$464,$D$2:$D$464),2,)} -> 结构二室
A4: =ROW()-1 -> 3 | B4: 郑石 | C4: =IFERROR(VLOOKUP(B4,[1]工程研发事业部人员名单!B:D,2,0),"") -> 26766 | D4: =IFERROR(VLOOKUP(B4,[1]工程研发事业部人员名单!B:D,3,0),"") -> 强度室 | E4: CR929设计（2022年复材中心） | F4: =G4+H4+I4+J4 -> 300 | I4: 300 | K4: 强度 | L4: 前机身 | N4: =VLOOKUP(E4,订单号!B:C,2,0) -> #N/A | O4: =VLOOKUP(C4,领导干部!B:B,1,0) -> #N/A | Q4: 陈坤 | R4: 227.25 | S4: {=VLOOKUP(Q4&R4,IF({1,0},$B$2:$B$464&$F$2:$F$464,$N$2:$N$464),2,)} -> 10502 | T4: {=VLOOKUP(Q4&R4,IF({1,0},$B$2:$B$464&$F$2:$F$464,$E$2:$E$464),2,)} -> 工程支持 | U4: {=VLOOKUP(Q4&R4,IF({1,0},$B$2:$B$464&$F$2:$F$464,$C$2:$C$464),2,)} -> 51576 | V4: {=VLOOKUP(Q4&R4,IF({1,0},$B$2:$B$464&$F$2:$F$464,$D$2:$D$464),2,)} -> 联络工程室
A5: =ROW()-1 -> 4 | B5: 王琛 | C5: =IFERROR(VLOOKUP(B5,[1]工程研发事业部人员名单!B:D,2,0),"") -> 22291 | D5: =IFERROR(VLOOKUP(B5,[1]工程研发事业部人员名单!B:D,3,0),"") -> 综合技术室 | E5: CR929设计（2022年复材中心） | F5: =G5+H5+I5+J5 -> 30 | H5: 30 | K5: 强度 | L5: 前机身 | N5: =VLOOKUP(E5,订单号!B:C,2,0) -> #N/A | O5: =VLOOKUP(C5,领导干部!B:B,1,0) -> #N/A | Q5: 陈磊 | R5: 252 | S5: {=VLOOKUP(Q5&R5,IF({1,0},$B$2:$B$464&$F$2:$F$464,$N$2:$N$464),2,)} -> #N/A | T5: {=VLOOKUP(Q5&R5,IF({1,0},$B$2:$B$464&$F$2:$F$464,$E$2:$E$464),2,)} -> 1号设计（2022年KTB） | U5: {=VLOOKUP(Q5&R5,IF({1,0},$B$2:$B$464&$F$2:$F$464,$C$2:$C$464),2,)} -> 52180 | V5: {=VLOOKUP(Q5&R5,IF({1,0},$B$2:$B$464&$F$2:$F$464,$D$2:$D$464),2,)} -> 结构一室
A6: =ROW()-1 -> 5 | B6: 张刚 | C6: =IFERROR(VLOOKUP(B6,[1]工程研发事业部人员名单!B:D,2,0),"") -> 50278 | D6: =IFERROR(VLOOKUP(B6,[1]工程研发事业部人员名单!B:D,3,0),"") -> 结构二室 | E6: CR929设计（2022年复材中心） | F6: =G6+H6+I6+J6 -> 208 | J6: 208 | K6: 结构 | L6: 中机身 | N6: =VLOOKUP(E6,订单号!B:C,2,0) -> #N/A | O6: =VLOOKUP(C6,领导干部!B:B,1,0) -> #N/A | Q6: 陈瑞东 | R6: 220 | S6: {=VLOOKUP(Q6&R6,IF({1,0},$B$2:$B$464&$F$2:$F$464,$N$2:$N$464),2,)} -> #N/A | T6: {=VLOOKUP(Q6&R6,IF({1,0},$B$2:$B$464&$F$2:$F$464,$E$2:$E$464),2,)} -> CR929设计（2022年上飞院） | U6: {=VLOOKUP(Q6&R6,IF({1,0},$B$2:$B$464&$F$2:$F$464,$C$2:$C$464),2,)} -> 51181 | V6: {=VLOOKUP(Q6&R6,IF({1,0},$B$2:$B$464&$F$2:$F$464,$D$2:$D$464),2,)} -> 强度室
A7: =ROW()-1 -> 6 | B7: 孟玲俊 | C7: =IFERROR(VLOOKUP(B7,[1]工程研发事业部人员名单!B:D,2,0),"") -> 22298 | D7: =IFERROR(VLOOKUP(B7,[1]工程研发事业部人员名单!B:D,3,0),"") -> 结构二室 | E7: CR929设计（2022年复材中心） | F7: =G7+H7+I7+J7 -> 164 | I7: 164 | K7: 结构 | L7: 中机身 | N7: =VLOOKUP(E7,订单号!B:C,2,0) -> #N/A | O7: =VLOOKUP(C7,领导干部!B:B,1,0) -> #N/A | Q7: 陈志禹 | R7: 145.5 | S7: {=VLOOKUP(Q7&R7,IF({1,0},$B$2:$B$464&$F$2:$F$464,$N$2:$N$464),2,)} -> 10502 | T7: {=VLOOKUP(Q7&R7,IF({1,0},$B$2:$B$464&$F$2:$F$464,$E$2:$E$464),2,)} -> 工程支持 | U7: {=VLOOKUP(Q7&R7,IF({1,0},$B$2:$B$464&$F$2:$F$464,$C$2:$C$464),2,)} -> 17787 | V7: {=VLOOKUP(Q7&R7,IF({1,0},$B$2:$B$464&$F$2:$F$464,$D$2:$D$464),2,)} -> 综合技术室
A8: =ROW()-1 -> 7 | B8: 朱海 | C8: =IFERROR(VLOOKUP(B8,[1]工程研发事业部人员名单!B:D,2,0),"") -> 52232 | D8: =IFERROR(VLOOKUP(B8,[1]工程研发事业部人员名单!B:D,3,0),"") -> 结构二室 | E8: CR929设计（2022年复材中心） | F8: =G8+H8+I8+J8 -> 152 | I8: 152 | K8: 结构 | L8: 中机身 | N8: =VLOOKUP(E8,订单号!B:C,2,0) -> #N/A | O8: =VLOOKUP(C8,领导干部!B:B,1,0) -> #N/A | Q8: 晨曦 | R8: 130 | S8: {=VLOOKUP(Q8&R8,IF({1,0},$B$2:$B$464&$F$2:$F$464,$N$2:$N$464),2,)} -> YZ40000680 | T8: {=VLOOKUP(Q8&R8,IF({1,0},$B$2:$B$464&$F$2:$F$464,$E$2:$E$464),2,)} -> C919设计（2022年上飞院） | U8: {=VLOOKUP(Q8&R8,IF({1,0},$B$2:$B$464&$F$2:$F$464,$C$2:$C$464),2,)} -> 50030 | V8: {=VLOOKUP(Q8&R8,IF({1,0},$B$2:$B$464&$F$2:$F$464,$D$2:$D$464),2,)} -> 总体室
A9: =ROW()-1 -> 8 | B9: 马爽 | C9: =IFERROR(VLOOKUP(B9,[1]工程研发事业部人员名单!B:D,2,0),"") -> 51642 | D9: =IFERROR(VLOOKUP(B9,[1]工程研发事业部人员名单!B:D,3,0),"") -> 结构二室 | E9: CR929设计（2022年复材中心） | F9: =G9+H9+I9+J9 -> 192 | I9: 192 | K9: 结构 | L9: 中机身 | N9: =VLOOKUP(E9,订单号!B:C,2,0) -> #N/A | O9: =VLOOKUP(C9,领导干部!B:B,1,0) -> #N/A | Q9: 褚永鑫 | R9: 293.6 | S9: {=VLOOKUP(Q9&R9,IF({1,0},$B$2:$B$464&$F$2:$F$464,$N$2:$N$464),2,)} -> 10502 | T9: {=VLOOKUP(Q9&R9,IF({1,0},$B$2:$B$464&$F$2:$F$464,$E$2:$E$464),2,)} -> 工程支持 | U9: {=VLOOKUP(Q9&R9,IF({1,0},$B$2:$B$464&$F$2:$F$464,$C$2:$C$464),2,)} -> 22253 | V9: {=VLOOKUP(Q9&R9,IF({1,0},$B$2:$B$464&$F$2:$F$464,$D$2:$D$464),2,)} -> 联络工程室
A10: =ROW()-1 -> 9 | B10: 徐丹 | C10: =IFERROR(VLOOKUP(B10,[1]工程研发事业部人员名单!B:D,2,0),"") -> 51407 | D10: =IFERROR(VLOOKUP(B10,[1]工程研发事业部人员名单!B:D,3,0),"") -> 结构二室 | E10: CR929设计（2022年复材中心） | F10: =G10+H10+I10+J10 -> 166 | I10: 166 | K10: 结构 | L10: 中机身 | N10: =VLOOKUP(E10,订单号!B:C,2,0) -> #N/A | O10: =VLOOKUP(C10,领导干部!B:B,1,0) -> #N/A | Q10: 丛家勇 | R10: 340 | S10: {=VLOOKUP(Q10&R10,IF({1,0},$B$2:$B$464&$F$2:$F$464,$N$2:$N$464),2,)} -> #N/A | T10: {=VLOOKUP(Q10&R10,IF({1,0},$B$2:$B$464&$F$2:$F$464,$E$2:$E$464),2,)} -> CR929设计（2022年上飞院） | U10: {=VLOOKUP(Q10&R10,IF({1,0},$B$2:$B$464&$F$2:$F$464,$C$2:$C$464),2,)} -> 50281 | V10: {=VLOOKUP(Q10&R10,IF({1,0},$B$2:$B$464&$F$2:$F$464,$D$2:$D$464),2,)} -> 结构一室
A11: =ROW()-1 -> 10 | B11: 柴宝 | C11: =IFERROR(VLOOKUP(B11,[1]工程研发事业部人员名单!B:D,2,0),"") -> 51944 | D11: =IFERROR(VLOOKUP(B11,[1]工程研发事业部人员名单!B:D,3,0),"") -> 强度室 | E11: CR929设计（2022年复材中心） | F11: =G11+H11+I11+J11 -> 200 | I11: 200 | K11: 强度 | L11: 中机身 | N11: =VLOOKUP(E11,订单号!B:C,2,0) -> #N/A | O11: =VLOOKUP(C11,领导干部!B:B,1,0) -> #N/A | Q11: 董晓莉 | R11: 220 | S11: {=VLOOKUP(Q11&R11,IF({1,0},$B$2:$B$464&$F$2:$F$464,$N$2:$N$464),2,)} -> #N/A | T11: {=VLOOKUP(Q11&R11,IF({1,0},$B$2:$B$464&$F$2:$F$464,$E$2:$E$464),2,)} -> CR929设计（2022年复材中心） | U11: {=VLOOKUP(Q11&R11,IF({1,0},$B$2:$B$464&$F$2:$F$464,$C$2:$C$464),2,)} -> 51211 | V11: {=VLOOKUP(Q11&R11,IF({1,0},$B$2:$B$464&$F$2:$F$464,$D$2:$D$464),2,)} -> 结构一室
A12: =ROW()-1 -> 11 | B12: 赵永利 | C12: =IFERROR(VLOOKUP(B12,[1]工程研发事业部人员名单!B:D,2,0),"") -> 28161 | D12: =IFERROR(VLOOKUP(B12,[1]工程研发事业部人员名单!B:D,3,0),"") -> 强度室 | E12: CR929设计（2022年复材中心） | F12: =G12+H12+I12+J12 -> 140 | I12: 140 | K12: 强度 | L12: 中机身 | N12: =VLOOKUP(E12,订单号!B:C,2,0) -> #N/A | O12: =VLOOKUP(C12,领导干部!B:B,1,0) -> #N/A | Q12: 杜洪雨 | R12: 220 | S12: {=VLOOKUP(Q12&R12,IF({1,0},$B$2:$B$464&$F$2:$F$464,$N$2:$N$464),2,)} -> YZ40000680 | T12: {=VLOOKUP(Q12&R12,IF({1,0},$B$2:$B$464&$F$2:$F$464,$E$2:$E$464),2,)} -> C919设计（2022年上飞院） | U12: {=VLOOKUP(Q12&R12,IF({1,0},$B$2:$B$464&$F$2:$F$464,$C$2:$C$464),2,)} -> 51170 | V12: {=VLOOKUP(Q12&R12,IF({1,0},$B$2:$B$464&$F$2:$F$464,$D$2:$D$464),2,)} -> 结构二室
A13: =ROW()-1 -> 12 | B13: 付泉铭 | C13: =IFERROR(VLOOKUP(B13,[1]工程研发事业部人员名单!B:D,2,0),"") -> 51555 | D13: =IFERROR(VLOOKUP(B13,[1]工程研发事业部人员名单!B:D,3,0),"") -> 联络工程室 | E13: CR929设计（2022年复材中心） | F13: =G13+H13+I13+J13 -> 65.5 | G13: 65.5 | K13: 强度 | L13: 中机身 | N13: =VLOOKUP(E13,订单号!B:C,2,0) -> #N/A | O13: =VLOOKUP(C13,领导干部!B:B,1,0) -> #N/A | Q13: 付强 | R13: 384.69 | S13: {=VLOOKUP(Q13&R13,IF({1,0},$B$2:$B$464&$F$2:$F$464,$N$2:$N$464),2,)} -> 10502 | T13: {=VLOOKUP(Q13&R13,IF({1,0},$B$2:$B$464&$F$2:$F$464,$E$2:$E$464),2,)} -> 工程支持 | U13: {=VLOOKUP(Q13&R13,IF({1,0},$B$2:$B$464&$F$2:$F$464,$C$2:$C$464),2,)} -> 25549 | V13: {=VLOOKUP(Q13&R13,IF({1,0},$B$2:$B$464&$F$2:$F$464,$D$2:$D$464),2,)} -> 联络工程室
A14: =ROW()-1 -> 13 | B14: 魏春生 | C14: =IFERROR(VLOOKUP(B14,[1]工程研发事业部人员名单!B:D,2,0),"") -> 51389 | D14: =IFERROR(VLOOKUP(B14,[1]工程研发事业部人员名单!B:D,3,0),"") -> 系统室 | E14: CR929设计（2022年复材中心） | F14: =G14+H14+I14+J14 -> 56 | G14: 56 | K14: 强度 | L14: 中机身 | N14: =VLOOKUP(E14,订单号!B:C,2,0) -> #N/A | O14: =VLOOKUP(C14,领导干部!B:B,1,0) -> #N/A | Q14: 付泉铭 | R14: 155 | S14: {=VLOOKUP(Q14&R14,IF({1,0},$B$2:$B$464&$F$2:$F$464,$N$2:$N$464),2,)} -> 0 | T14: {=VLOOKUP(Q14&R14,IF({1,0},$B$2:$B$464&$F$2:$F$464,$E$2:$E$464),2,)} -> 培训工作 | U14: {=VLOOKUP(Q14&R14,IF({1,0},$B$2:$B$464&$F$2:$F$464,$C$2:$C$464),2,)} -> 51555 | V14: {=VLOOKUP(Q14&R14,IF({1,0},$B$2:$B$464&$F$2:$F$464,$D$2:$D$464),2,)} -> 联络工程室
A15: =ROW()-1 -> 14 | B15: 李爱环 | C15: =IFERROR(VLOOKUP(B15,[1]工程研发事业部人员名单!B:D,2,0),"") -> 50726 | D15: =IFERROR(VLOOKUP(B15,[1]工程研发事业部人员名单!B:D,3,0),"") -> 强度室 | E15: CR929设计（2022年复材中心） | F15: =G15+H15+I15+J15 -> 180 | I15: 180 | K15: 强度 | L15: 后压力框 | N15: =VLOOKUP(E15,订单号!B:C,2,0) -> #N/A | O15: =VLOOKUP(C15,领导干部!B:B,1,0) -> #N/A | Q15: 付容容 | R15: 126 | S15: {=VLOOKUP(Q15&R15,IF({1,0},$B$2:$B$464&$F$2:$F$464,$N$2:$N$464),2,)} -> YZ40000680 | T15: {=VLOOKUP(Q15&R15,IF({1,0},$B$2:$B$464&$F$2:$F$464,$E$2:$E$464),2,)} -> C919设计（2022年上飞院） | U15: {=VLOOKUP(Q15&R15,IF({1,0},$B$2:$B$464&$F$2:$F$464,$C$2:$C$464),2,)} -> 51183 | V15: {=VLOOKUP(Q15&R15,IF({1,0},$B$2:$B$464&$F$2:$F$464,$D$2:$D$464),2,)} -> 结构一室
A16: =ROW()-1 -> 15 | B16: 牛福春 | C16: =IFERROR(VLOOKUP(B16,[1]工程研发事业部人员名单!B:D,2,0),"") -> 50710 | D16: =IFERROR(VLOOKUP(B16,[1]工程研发事业部人员名单!B:D,3,0),"") -> 结构二室 | E16: CR929设计（2022年复材中心） | F16: =G16+H16+I16+J16 -> 168 | I16: 168 | K16: 结构 | L16: 后机身 | N16: =VLOOKUP(E16,订单号!B:C,2,0) -> #N/A | O16: =VLOOKUP(C16,领导干部!B:B,1,0) -> #N/A | Q16: 高秉芳 | R16: 378.85 | S16: {=VLOOKUP(Q16&R16,IF({1,0},$B$2:$B$464&$F$2:$F$464,$N$2:$N$464),2,)} -> 10502 | T16: {=VLOOKUP(Q16&R16,IF({1,0},$B$2:$B$464&$F$2:$F$464,$E$2:$E$464),2,)} -> 工程支持 | U16: {=VLOOKUP(Q16&R16,IF({1,0},$B$2:$B$464&$F$2:$F$464,$C$2:$C$464),2,)} -> 26688 | V16: {=VLOOKUP(Q16&R16,IF({1,0},$B$2:$B$464&$F$2:$F$464,$D$2:$D$464),2,)} -> 联络工程室
A17: =ROW()-1 -> 16 | B17: 康霞 | C17: =IFERROR(VLOOKUP(B17,[1]工程研发事业部人员名单!B:D,2,0),"") -> 52132 | D17: =IFERROR(VLOOKUP(B17,[1]工程研发事业部人员名单!B:D,3,0),"") -> 结构二室 | E17: CR929设计（2022年复材中心） | F17: =G17+H17+I17+J17 -> 30 | I17: 30 | K17: 结构 | L17: 后机身 | N17: =VLOOKUP(E17,订单号!B:C,2,0) -> #N/A | O17: =VLOOKUP(C17,领导干部!B:B,1,0) -> #N/A | Q17: 高奇 | R17: 226.46 | S17: {=VLOOKUP(Q17&R17,IF({1,0},$B$2:$B$464&$F$2:$F$464,$N$2:$N$464),2,)} -> 10502 | T17: {=VLOOKUP(Q17&R17,IF({1,0},$B$2:$B$464&$F$2:$F$464,$E$2:$E$464),2,)} -> 工程支持 | U17: {=VLOOKUP(Q17&R17,IF({1,0},$B$2:$B$464&$F$2:$F$464,$C$2:$C$464),2,)} -> 17732 | V17: {=VLOOKUP(Q17&R17,IF({1,0},$B$2:$B$464&$F$2:$F$464,$D$2:$D$464),2,)} -> 联络工程室
A18: =ROW()-1 -> 17 | B18: 周莫普 | C18: =IFERROR(VLOOKUP(B18,[1]工程研发事业部人员名单!B:D,2,0),"") -> 51397 | D18: =IFERROR(VLOOKUP(B18,[1]工程研发事业部人员名单!B:D,3,0),"") -> 结构二室 | E18: CR929设计（2022年复材中心） | F18: =G18+H18+I18+J18 -> 168 | I18: 168 | K18: 结构 | L18: 后机身 | N18: =VLOOKUP(E18,订单号!B:C,2,0) -> #N/A | O18: =VLOOKUP(C18,领导干部!B:B,1,0) -> #N/A | Q18: 葛春生 | R18: 170 | S18: {=VLOOKUP(Q18&R18,IF({1,0},$B$2:$B$464&$F$2:$F$464,$N$2:$N$464),2,)} -> #N/A | T18: {=VLOOKUP(Q18&R18,IF({1,0},$B$2:$B$464&$F$2:$F$464,$E$2:$E$464),2,)} -> CR929设计（2022年复材中心） | U18: {=VLOOKUP(Q18&R18,IF({1,0},$B$2:$B$464&$F$2:$F$464,$C$2:$C$464),2,)} -> 51410 | V18: {=VLOOKUP(Q18&R18,IF({1,0},$B$2:$B$464&$F$2:$F$464,$D$2:$D$464),2,)} -> 结构一室
A19: =ROW()-1 -> 18 | B19: 贾永亮 | C19: =IFERROR(VLOOKUP(B19,[1]工程研发事业部人员名单!B:D,2,0),"") -> 52131 | D19: =IFERROR(VLOOKUP(B19,[1]工程研发事业部人员名单!B:D,3,0),"") -> 结构二室 | E19: CR929设计（2022年复材中心） | F19: =G19+H19+I19+J19 -> 168 | I19: 168 | K19: 结构 | L19: 后机身 | N19: =VLOOKUP(E19,订单号!B:C,2,0) -> #N/A | O19: =VLOOKUP(C19,领导干部!B:B,1,0) -> #N/A | Q19: 耿璐璐 | R19: 138.17 | S19: {=VLOOKUP(Q19&R19,IF({1,0},$B$2:$B$464&$F$2:$F$464,$N$2:$N$464),2,)} -> 10502 | T19: {=VLOOKUP(Q19&R19,IF({1,0},$B$2:$B$464&$F$2:$F$464,$E$2:$E$464),2,)} -> 工程支持 | U19: {=VLOOKUP(Q19&R19,IF({1,0},$B$2:$B$464&$F$2:$F$464,$C$2:$C$464),2,)} -> 51405 | V19: {=VLOOKUP(Q19&R19,IF({1,0},$B$2:$B$464&$F$2:$F$464,$D$2:$D$464),2,)} -> 综合技术室
A20: =ROW()-1 -> 19 | B20: 许美娟 | C20: =IFERROR(VLOOKUP(B20,[1]工程研发事业部人员名单!B:D,2,0),"") -> 51194 | D20: =IFERROR(VLOOKUP(B20,[1]工程研发事业部人员名单!B:D,3,0),"") -> 强度室 | E20: CR929设计（2022年复材中心） | F20: =G20+H20+I20+J20 -> 110 | I20: 110 | K20: 强度 | L20: 后机身 | N20: =VLOOKUP(E20,订单号!B:C,2,0) -> #N/A | O20: =VLOOKUP(C20,领导干部!B:B,1,0) -> #N/A | Q20: 郭静 | R20: 336.65 | S20: {=VLOOKUP(Q20&R20,IF({1,0},$B$2:$B$464&$F$2:$F$464,$N$2:$N$464),2,)} -> 10502 | T20: {=VLOOKUP(Q20&R20,IF({1,0},$B$2:$B$464&$F$2:$F$464,$E$2:$E$464),2,)} -> 工程支持 | U20: {=VLOOKUP(Q20&R20,IF({1,0},$B$2:$B$464&$F$2:$F$464,$C$2:$C$464),2,)} -> 50027 | V20: {=VLOOKUP(Q20&R20,IF({1,0},$B$2:$B$464&$F$2:$F$464,$D$2:$D$464),2,)} -> 联络工程室
A21: =ROW()-1 -> 20 | B21: 刘可佳 | C21: =IFERROR(VLOOKUP(B21,[1]工程研发事业部人员名单!B:D,2,0),"") -> 51793 | D21: =IFERROR(VLOOKUP(B21,[1]工程研发事业部人员名单!B:D,3,0),"") -> 强度室 | E21: CR929设计（2022年复材中心） | F21: =G21+H21+I21+J21 -> 50 | I21: 50 | K21: 强度 | L21: 后机身 | N21: =VLOOKUP(E21,订单号!B:C,2,0) -> #N/A | O21: =VLOOKUP(C21,领导干部!B:B,1,0) -> #N/A | Q21: 郭晓庆 | R21: 283.5 | S21: {=VLOOKUP(Q21&R21,IF({1,0},$B$2:$B$464&$F$2:$F$464,$N$2:$N$464),2,)} -> YZ40000680 | T21: {=VLOOKUP(Q21&R21,IF({1,0},$B$2:$B$464&$F$2:$F$464,$E$2:$E$464),2,)} -> C919设计（2022年上飞院） | U21: {=VLOOKUP(Q21&R21,IF({1,0},$B$2:$B$464&$F$2:$F$464,$C$2:$C$464),2,)} -> 50275 | V21: {=VLOOKUP(Q21&R21,IF({1,0},$B$2:$B$464&$F$2:$F$464,$D$2:$D$464),2,)} -> 结构一室
A22: =ROW()-1 -> 21 | B22: 王岩 | C22: =IFERROR(VLOOKUP(B22,[1]工程研发事业部人员名单!B:D,2,0),"") -> 51175 | D22: =IFERROR(VLOOKUP(B22,[1]工程研发事业部人员名单!B:D,3,0),"") -> 强度室 | E22: CR929设计（2022年复材中心） | F22: =G22+H22+I22+J22 -> 122.5 | I22: 122.5 | K22: 强度 | L22: 后机身 | N22: =VLOOKUP(E22,订单号!B:C,2,0) -> #N/A | O22: =VLOOKUP(C22,领导干部!B:B,1,0) -> #N/A | Q22: 韩南逍 | R22: 157.5 | S22: {=VLOOKUP(Q22&R22,IF({1,0},$B$2:$B$464&$F$2:$F$464,$N$2:$N$464),2,)} -> 10502 | T22: {=VLOOKUP(Q22&R22,IF({1,0},$B$2:$B$464&$F$2:$F$464,$E$2:$E$464),2,)} -> 工程支持 | U22: {=VLOOKUP(Q22&R22,IF({1,0},$B$2:$B$464&$F$2:$F$464,$C$2:$C$464),2,)} -> 50029 | V22: {=VLOOKUP(Q22&R22,IF({1,0},$B$2:$B$464&$F$2:$F$464,$D$2:$D$464),2,)} -> 综合技术室
A23: =ROW()-1 -> 22 | B23: 马雪菲 | C23: =IFERROR(VLOOKUP(B23,[1]工程研发事业部人员名单!B:D,2,0),"") -> 52560 | D23: =IFERROR(VLOOKUP(B23,[1]工程研发事业部人员名单!B:D,3,0),"") -> 强度室 | E23: CR929设计（2022年复材中心） | F23: =G23+H23+I23+J23 -> 80 | I23: 80 | K23: 强度 | L23: 后机身 | N23: =VLOOKUP(E23,订单号!B:C,2,0) -> #N/A | O23: =VLOOKUP(C23,领导干部!B:B,1,0) -> #N/A | Q23: 何续斌 | R23: 255 | S23: {=VLOOKUP(Q23&R23,IF({1,0},$B$2:$B$464&$F$2:$F$464,$N$2:$N$464),2,)} -> YZ40000680 | T23: {=VLOOKUP(Q23&R23,IF({1,0},$B$2:$B$464&$F$2:$F$464,$E$2:$E$464),2,)} -> C919设计（2022年上飞院） | U23: {=VLOOKUP(Q23&R23,IF({1,0},$B$2:$B$464&$F$2:$F$464,$C$2:$C$464),2,)} -> 50871 | V23: {=VLOOKUP(Q23&R23,IF({1,0},$B$2:$B$464&$F$2:$F$464,$D$2:$D$464),2,)} -> 强度室
A24: =ROW()-1 -> 23 | B24: 刘成 | C24: =IFERROR(VLOOKUP(B24,[1]工程研发事业部人员名单!B:D,2,0),"") -> 51860 | D24: =IFERROR(VLOOKUP(B24,[1]工程研发事业部人员名单!B:D,3,0),"") -> 总体室 | E24: CR929设计（2022年复材中心） | F24: =G24+H24+I24+J24 -> 65 | H24: 65 | K24: 强度 | L24: 后机身 | N24: =VLOOKUP(E24,订单号!B:C,2,0) -> #N/A | O24: =VLOOKUP(C24,领导干部!B:B,1,0) -> #N/A | Q24: 黄文超 | R24: 120 | S24: {=VLOOKUP(Q24&R24,IF({1,0},$B$2:$B$464&$F$2:$F$464,$N$2:$N$464),2,)} -> #N/A | T24: {=VLOOKUP(Q24&R24,IF({1,0},$B$2:$B$464&$F$2:$F$464,$E$2:$E$464),2,)} -> CR929设计（2022年复材中心） | U24: {=VLOOKUP(Q24&R24,IF({1,0},$B$2:$B$464&$F$2:$F$464,$C$2:$C$464),2,)} -> 51200 | V24: {=VLOOKUP(Q24&R24,IF({1,0},$B$2:$B$464&$F$2:$F$464,$D$2:$D$464),2,)} -> 强度室
A25: =ROW()-1 -> 24 | B25: 康霞 | C25: =IFERROR(VLOOKUP(B25,[1]工程研发事业部人员名单!B:D,2,0),"") -> 52132 | D25: =IFERROR(VLOOKUP(B25,[1]工程研发事业部人员名单!B:D,3,0),"") -> 结构二室 | E25: CR929设计（2022年复材中心） | F25: =G25+H25+I25+J25 -> 78 | H25: 78 | K25: 强度 | L25: 后机身 | N25: =VLOOKUP(E25,订单号!B:C,2,0) -> #N/A | O25: =VLOOKUP(C25,领导干部!B:B,1,0) -> #N/A | Q25: 霍东旭 | R25: 393.65 | S25: {=VLOOKUP(Q25&R25,IF({1,0},$B$2:$B$464&$F$2:$F$464,$N$2:$N$464),2,)} -> 10502 | T25: {=VLOOKUP(Q25&R25,IF({1,0},$B$2:$B$464&$F$2:$F$464,$E$2:$E$464),2,)} -> 工程支持 | U25: {=VLOOKUP(Q25&R25,IF({1,0},$B$2:$B$464&$F$2:$F$464,$C$2:$C$464),2,)} -> 51941 | V25: {=VLOOKUP(Q25&R25,IF({1,0},$B$2:$B$464&$F$2:$F$464,$D$2:$D$464),2,)} -> 联络工程室
A26: =ROW()-1 -> 25 | B26: 王琛 | C26: =IFERROR(VLOOKUP(B26,[1]工程研发事业部人员名单!B:D,2,0),"") -> 22291 | D26: =IFERROR(VLOOKUP(B26,[1]工程研发事业部人员名单!B:D,3,0),"") -> 综合技术室 | E26: CR929设计（2022年复材中心） | F26: =G26+H26+I26+J26 -> 26 | H26: 26 | K26: 强度 | L26: 后机身 | N26: =VLOOKUP(E26,订单号!B:C,2,0) -> #N/A | O26: =VLOOKUP(C26,领导干部!B:B,1,0) -> #N/A | Q26: 纪可 | R26: 130 | S26: {=VLOOKUP(Q26&R26,IF({1,0},$B$2:$B$464&$F$2:$F$464,$N$2:$N$464),2,)} -> YZ40000680 | T26: {=VLOOKUP(Q26&R26,IF({1,0},$B$2:$B$464&$F$2:$F$464,$E$2:$E$464),2,)} -> C919设计（2022年上飞院） | U26: {=VLOOKUP(Q26&R26,IF({1,0},$B$2:$B$464&$F$2:$F$464,$C$2:$C$464),2,)} -> 26689 | V26: {=VLOOKUP(Q26&R26,IF({1,0},$B$2:$B$464&$F$2:$F$464,$D$2:$D$464),2,)} -> 强度室
A27: =ROW()-1 -> 26 | B27: 孔婷婷 | C27: =IFERROR(VLOOKUP(B27,[1]工程研发事业部人员名单!B:D,2,0),"") -> 23525 | D27: =IFERROR(VLOOKUP(B27,[1]工程研发事业部人员名单!B:D,3,0),"") -> 强度室 | E27: CR929设计（2022年复材中心） | F27: =G27+H27+I27+J27 -> 140 | I27: 140 | K27: 强度 | L27: 机翼 | N27: =VLOOKUP(E27,订单号!B:C,2,0) -> #N/A | O27: =VLOOKUP(C27,领导干部!B:B,1,0) -> #N/A | Q27: 贾永亮 | R27: 168 | S27: {=VLOOKUP(Q27&R27,IF({1,0},$B$2:$B$464&$F$2:$F$464,$N$2:$N$464),2,)} -> #N/A | T27: {=VLOOKUP(Q27&R27,IF({1,0},$B$2:$B$464&$F$2:$F$464,$E$2:$E$464),2,)} -> CR929设计（2022年复材中心） | U27: {=VLOOKUP(Q27&R27,IF({1,0},$B$2:$B$464&$F$2:$F$464,$C$2:$C$464),2,)} -> 52131 | V27: {=VLOOKUP(Q27&R27,IF({1,0},$B$2:$B$464&$F$2:$F$464,$D$2:$D$464),2,)} -> 结构二室
A28: =ROW()-1 -> 27 | B28: 黄文超 | C28: =IFERROR(VLOOKUP(B28,[1]工程研发事业部人员名单!B:D,2,0),"") -> 51200 | D28: =IFERROR(VLOOKUP(B28,[1]工程研发事业部人员名单!B:D,3,0),"") -> 强度室 | E28: CR929设计（2022年复材中心） | F28: =G28+H28+I28+J28 -> 120 | I28: 120 | K28: 强度 | L28: 机翼 | N28: =VLOOKUP(E28,订单号!B:C,2,0) -> #N/A | O28: =VLOOKUP(C28,领导干部!B:B,1,0) -> #N/A | Q28: 焦凯 | R28: 150 | S28: {=VLOOKUP(Q28&R28,IF({1,0},$B$2:$B$464&$F$2:$F$464,$N$2:$N$464),2,)} -> YZ40000680 | T28: {=VLOOKUP(Q28&R28,IF({1,0},$B$2:$B$464&$F$2:$F$464,$E$2:$E$464),2,)} -> C919设计（2022年上飞院） | U28: {=VLOOKUP(Q28&R28,IF({1,0},$B$2:$B$464&$F$2:$F$464,$C$2:$C$464),2,)} -> 52342 | V28: {=VLOOKUP(Q28&R28,IF({1,0},$B$2:$B$464&$F$2:$F$464,$D$2:$D$464),2,)} -> 强度室
A29: =ROW()-1 -> 28 | B29: 朱照泽 | C29: =IFERROR(VLOOKUP(B29,[1]工程研发事业部人员名单!B:D,2,0),"") -> 51763 | D29: =IFERROR(VLOOKUP(B29,[1]工程研发事业部人员名单!B:D,3,0),"") -> 强度室 | E29: CR929设计（2022年复材中心） | F29: =G29+H29+I29+J29 -> 120 | I29: 120 | K29: 强度 | L29: 机翼 | N29: =VLOOKUP(E29,订单号!B:C,2,0) -> #N/A | O29: =VLOOKUP(C29,领导干部!B:B,1,0) -> #N/A | Q29: 靳海丰 | R29: 200 | S29: {=VLOOKUP(Q29&R29,IF({1,0},$B$2:$B$464&$F$2:$F$464,$N$2:$N$464),2,)} -> #N/A | T29: {=VLOOKUP(Q29&R29,IF({1,0},$B$2:$B$464&$F$2:$F$464,$E$2:$E$464),2,)} -> C919设计（2021年上飞院） | U29: {=VLOOKUP(Q29&R29,IF({1,0},$B$2:$B$464&$F$2:$F$464,$C$2:$C$464),2,)} -> 51158 | V29: {=VLOOKUP(Q29&R29,IF({1,0},$B$2:$B$464&$F$2:$F$464,$D$2:$D$464),2,)} -> 强度室
A30: =ROW()-1 -> 29 | B30: 闫洪乐 | C30: =IFERROR(VLOOKUP(B30,[1]工程研发事业部人员名单!B:D,2,0),"") -> 52347 | D30: =IFERROR(VLOOKUP(B30,[1]工程研发事业部人员名单!B:D,3,0),"") -> 强度室 | E30: CR929设计（2022年复材中心） | F30: =G30+H30+I30+J30 -> 120 | I30: 120 | K30: 强度 | L30: 机翼 | N30: =VLOOKUP(E30,订单号!B:C,2,0) -> #N/A | O30: =VLOOKUP(C30,领导干部!B:B,1,0) -> #N/A | Q30: 康霞 | R30: 90 | S30: {=VLOOKUP(Q30&R30,IF({1,0},$B$2:$B$464&$F$2:$F$464,$N$2:$N$464),2,)} -> YZ40000680 | T30: {=VLOOKUP(Q30&R30,IF({1,0},$B$2:$B$464&$F$2:$F$464,$E$2:$E$464),2,)} -> C919设计（2022年上飞院） | U30: {=VLOOKUP(Q30&R30,IF({1,0},$B$2:$B$464&$F$2:$F$464,$C$2:$C$464),2,)} -> 52132 | V30: {=VLOOKUP(Q30&R30,IF({1,0},$B$2:$B$464&$F$2:$F$464,$D$2:$D$464),2,)} -> 结构二室
A31: =ROW()-1 -> 30 | B31: 王呈呈 | C31: =IFERROR(VLOOKUP(B31,[1]工程研发事业部人员名单!B:D,2,0),"") -> 51196 | D31: =IFERROR(VLOOKUP(B31,[1]工程研发事业部人员名单!B:D,3,0),"") -> 强度室 | E31: CR929设计（2022年复材中心） | F31: =G31+H31+I31+J31 -> 120 | I31: 120 | K31: 强度 | L31: 机翼 | N31: =VLOOKUP(E31,订单号!B:C,2,0) -> #N/A | O31: =VLOOKUP(C31,领导干部!B:B,1,0) -> #N/A | Q31: 康志明 | R31: 240 | S31: {=VLOOKUP(Q31&R31,IF({1,0},$B$2:$B$464&$F$2:$F$464,$N$2:$N$464),2,)} -> #N/A | T31: {=VLOOKUP(Q31&R31,IF({1,0},$B$2:$B$464&$F$2:$F$464,$E$2:$E$464),2,)} -> 1号设计（2022年KTB） | U31: {=VLOOKUP(Q31&R31,IF({1,0},$B$2:$B$464&$F$2:$F$464,$C$2:$C$464),2,)} -> 25765 | V31: {=VLOOKUP(Q31&R31,IF({1,0},$B$2:$B$464&$F$2:$F$464,$D$2:$D$464),2,)} -> 结构一室
A32: =ROW()-1 -> 31 | B32: 李妍 | C32: =IFERROR(VLOOKUP(B32,[1]工程研发事业部人员名单!B:D,2,0),"") -> 51435 | D32: =IFERROR(VLOOKUP(B32,[1]工程研发事业部人员名单!B:D,3,0),"") -> 系统室 | E32: CR929设计（2022年复材中心） | F32: =G32+H32+I32+J32 -> 120 | G32: 120 | K32: 强度 | L32: 机翼 | N32: =VLOOKUP(E32,订单号!B:C,2,0) -> #N/A | O32: =VLOOKUP(C32,领导干部!B:B,1,0) -> #N/A | Q32: 孔婷婷 | R32: 140 | S32: {=VLOOKUP(Q32&R32,IF({1,0},$B$2:$B$464&$F$2:$F$464,$N$2:$N$464),2,)} -> #N/A | T32: {=VLOOKUP(Q32&R32,IF({1,0},$B$2:$B$464&$F$2:$F$464,$E$2:$E$464),2,)} -> CR929设计（2022年复材中心） | U32: {=VLOOKUP(Q32&R32,IF({1,0},$B$2:$B$464&$F$2:$F$464,$C$2:$C$464),2,)} -> 23525 | V32: {=VLOOKUP(Q32&R32,IF({1,0},$B$2:$B$464&$F$2:$F$464,$D$2:$D$464),2,)} -> 强度室
A33: =ROW()-1 -> 32 | B33: 宋凯 | C33: =IFERROR(VLOOKUP(B33,[1]工程研发事业部人员名单!B:D,2,0),"") -> 51951 | D33: =IFERROR(VLOOKUP(B33,[1]工程研发事业部人员名单!B:D,3,0),"") -> 系统室 | E33: CR929设计（2022年复材中心） | F33: =G33+H33+I33+J33 -> 60 | G33: 60 | K33: 强度 | L33: 机翼 | N33: =VLOOKUP(E33,订单号!B:C,2,0) -> #N/A | O33: =VLOOKUP(C33,领导干部!B:B,1,0) -> #N/A | Q33: 李爱环 | R33: 180 | S33: {=VLOOKUP(Q33&R33,IF({1,0},$B$2:$B$464&$F$2:$F$464,$N$2:$N$464),2,)} -> #N/A | T33: {=VLOOKUP(Q33&R33,IF({1,0},$B$2:$B$464&$F$2:$F$464,$E$2:$E$464),2,)} -> CR929设计（2022年复材中心） | U33: {=VLOOKUP(Q33&R33,IF({1,0},$B$2:$B$464&$F$2:$F$464,$C$2:$C$464),2,)} -> 50726 | V33: {=VLOOKUP(Q33&R33,IF({1,0},$B$2:$B$464&$F$2:$F$464,$D$2:$D$464),2,)} -> 强度室
A34: =ROW()-1 -> 33 | B34: 万方 | C34: =IFERROR(VLOOKUP(B34,[1]工程研发事业部人员名单!B:D,2,0),"") -> 51387 | D34: =IFERROR(VLOOKUP(B34,[1]工程研发事业部人员名单!B:D,3,0),"") -> 系统室 | E34: CR929设计（2022年复材中心） | F34: =G34+H34+I34+J34 -> 100 | G34: 100 | K34: 强度 | L34: 机翼 | N34: =VLOOKUP(E34,订单号!B:C,2,0) -> #N/A | O34: =VLOOKUP(C34,领导干部!B:B,1,0) -> #N/A | Q34: 李金鹰 | R34: 75 | S34: {=VLOOKUP(Q34&R34,IF({1,0},$B$2:$B$464&$F$2:$F$464,$N$2:$N$464),2,)} -> 0 | T34: {=VLOOKUP(Q34&R34,IF({1,0},$B$2:$B$464&$F$2:$F$464,$E$2:$E$464),2,)} -> 培训工作 | U34: {=VLOOKUP(Q34&R34,IF({1,0},$B$2:$B$464&$F$2:$F$464,$C$2:$C$464),2,)} -> 51227 | V34: {=VLOOKUP(Q34&R34,IF({1,0},$B$2:$B$464&$F$2:$F$464,$D$2:$D$464),2,)} -> 结构一室
A35: =ROW()-1 -> 34 | B35: 骆美玲 | C35: =IFERROR(VLOOKUP(B35,[1]工程研发事业部人员名单!B:D,2,0),"") -> 50713 | D35: =IFERROR(VLOOKUP(B35,[1]工程研发事业部人员名单!B:D,3,0),"") -> 系统室 | E35: CR929设计（2022年复材中心） | F35: =G35+H35+I35+J35 -> 5 | G35: 5 | K35: 强度 | L35: 机翼 | N35: =VLOOKUP(E35,订单号!B:C,2,0) -> #N/A | O35: =VLOOKUP(C35,领导干部!B:B,1,0) -> #N/A | Q35: 李其鹏 | R35: 150.5 | S35: {=VLOOKUP(Q35&R35,IF({1,0},$B$2:$B$464&$F$2:$F$464,$N$2:$N$464),2,)} -> 10502 | T35: {=VLOOKUP(Q35&R35,IF({1,0},$B$2:$B$464&$F$2:$F$464,$E$2:$E$464),2,)} -> 工程支持 | U35: {=VLOOKUP(Q35&R35,IF({1,0},$B$2:$B$464&$F$2:$F$464,$C$2:$C$464),2,)} -> 51429 | V35: {=VLOOKUP(Q35&R35,IF({1,0},$B$2:$B$464&$F$2:$F$464,$D$2:$D$464),2,)} -> 综合技术室
A36: =ROW()-1 -> 35 | B36: 魏春生 | C36: =IFERROR(VLOOKUP(B36,[1]工程研发事业部人员名单!B:D,2,0),"") -> 51389 | D36: =IFERROR(VLOOKUP(B36,[1]工程研发事业部人员名单!B:D,3,0),"") -> 系统室 | E36: CR929设计（2022年复材中心） | F36: =G36+H36+I36+J36 -> 5 | G36: 5 | K36: 强度 | L36: 机翼 | N36: =VLOOKUP(E36,订单号!B:C,2,0) -> #N/A | O36: =VLOOKUP(C36,领导干部!B:B,1,0) -> #N/A | Q36: 李森 | R36: 260 | S36: {=VLOOKUP(Q36&R36,IF({1,0},$B$2:$B$464&$F$2:$F$464,$N$2:$N$464),2,)} -> #N/A | T36: {=VLOOKUP(Q36&R36,IF({1,0},$B$2:$B$464&$F$2:$F$464,$E$2:$E$464),2,)} -> 1号设计（2022年KTB） | U36: {=VLOOKUP(Q36&R36,IF({1,0},$B$2:$B$464&$F$2:$F$464,$C$2:$C$464),2,)} -> 17238 | V36: {=VLOOKUP(Q36&R36,IF({1,0},$B$2:$B$464&$F$2:$F$464,$D$2:$D$464),2,)} -> 结构二室
A37: =ROW()-1 -> 36 | B37: 刘凯男 | C37: =IFERROR(VLOOKUP(B37,[1]工程研发事业部人员名单!B:D,2,0),"") -> 52156 | D37: =IFERROR(VLOOKUP(B37,[1]工程研发事业部人员名单!B:D,3,0),"") -> 系统室 | E37: CR929设计（2022年复材中心） | F37: =G37+H37+I37+J37 -> 150 | G37: 150 | K37: 强度 | L37: 机翼 | N37: =VLOOKUP(E37,订单号!B:C,2,0) -> #N/A | O37: =VLOOKUP(C37,领导干部!B:B,1,0) -> #N/A | Q37: 李守玺 | R37: 300 | S37: {=VLOOKUP(Q37&R37,IF({1,0},$B$2:$B$464&$F$2:$F$464,$N$2:$N$464),2,)} -> #N/A | T37: {=VLOOKUP(Q37&R37,IF({1,0},$B$2:$B$464&$F$2:$F$464,$E$2:$E$464),2,)} -> 1号设计（2022年KTB） | U37: {=VLOOKUP(Q37&R37,IF({1,0},$B$2:$B$464&$F$2:$F$464,$C$2:$C$464),2,)} -> 25763 | V37: {=VLOOKUP(Q37&R37,IF({1,0},$B$2:$B$464&$F$2:$F$464,$D$2:$D$464),2,)} -> 结构一室
A38: =ROW()-1 -> 37 | B38: 杨春 | C38: =IFERROR(VLOOKUP(B38,[1]工程研发事业部人员名单!B:D,2,0),"") -> 51624 | D38: =IFERROR(VLOOKUP(B38,[1]工程研发事业部人员名单!B:D,3,0),"") -> 结构一室 | E38: CR929设计（2022年复材中心） | F38: =G38+H38+I38+J38 -> 80 | I38: 80 | K38: 结构 | L38: 平尾 | N38: =VLOOKUP(E38,订单号!B:C,2,0) -> #N/A | O38: =VLOOKUP(C38,领导干部!B:B,1,0) -> #N/A | Q38: 李湘芝 | R38: 287.92 | S38: {=VLOOKUP(Q38&R38,IF({1,0},$B$2:$B$464&$F$2:$F$464,$N$2:$N$464),2,)} -> 10502 | T38: {=VLOOKUP(Q38&R38,IF({1,0},$B$2:$B$464&$F$2:$F$464,$E$2:$E$464),2,)} -> 工程支持 | U38: {=VLOOKUP(Q38&R38,IF({1,0},$B$2:$B$464&$F$2:$F$464,$C$2:$C$464),2,)} -> 50019 | V38: {=VLOOKUP(Q38&R38,IF({1,0},$B$2:$B$464&$F$2:$F$464,$D$2:$D$464),2,)} -> 联络工程室
A39: =ROW()-1 -> 38 | B39: 葛春生 | C39: =IFERROR(VLOOKUP(B39,[1]工程研发事业部人员名单!B:D,2,0),"") -> 51410 | D39: =IFERROR(VLOOKUP(B39,[1]工程研发事业部人员名单!B:D,3,0),"") -> 结构一室 | E39: CR929设计（2022年复材中心） | F39: =G39+H39+I39+J39 -> 170 | I39: 170 | K39: 结构 | L39: 平尾 | N39: =VLOOKUP(E39,订单号!B:C,2,0) -> #N/A | O39: =VLOOKUP(C39,领导干部!B:B,1,0) -> #N/A | Q39: 李妍 | R39: 120 | S39: {=VLOOKUP(Q39&R39,IF({1,0},$B$2:$B$464&$F$2:$F$464,$N$2:$N$464),2,)} -> #N/A | T39: {=VLOOKUP(Q39&R39,IF({1,0},$B$2:$B$464&$F$2:$F$464,$E$2:$E$464),2,)} -> CR929设计（2022年复材中心） | U39: {=VLOOKUP(Q39&R39,IF({1,0},$B$2:$B$464&$F$2:$F$464,$C$2:$C$464),2,)} -> 51435 | V39: {=VLOOKUP(Q39&R39,IF({1,0},$B$2:$B$464&$F$2:$F$464,$D$2:$D$464),2,)} -> 系统室
A40: =ROW()-1 -> 39 | B40: 杨春 | C40: =IFERROR(VLOOKUP(B40,[1]工程研发事业部人员名单!B:D,2,0),"") -> 51624 | D40: =IFERROR(VLOOKUP(B40,[1]工程研发事业部人员名单!B:D,3,0),"") -> 结构一室 | E40: CR929设计（2022年复材中心） | F40: =G40+H40+I40+J40 -> 25 | I40: 25 | K40: 结构 | L40: 平尾 | N40: =VLOOKUP(E40,订单号!B:C,2,0) -> #N/A | O40: =VLOOKUP(C40,领导干部!B:B,1,0) -> #N/A | Q40: 李忠霖 | R40: 280 | S40: {=VLOOKUP(Q40&R40,IF({1,0},$B$2:$B$464&$F$2:$F$464,$N$2:$N$464),2,)} -> YZ40000680 | T40: {=VLOOKUP(Q40&R40,IF({1,0},$B$2:$B$464&$F$2:$F$464,$E$2:$E$464),2,)} -> C919设计（2022年上飞院） | U40: {=VLOOKUP(Q40&R40,IF({1,0},$B$2:$B$464&$F$2:$F$464,$C$2:$C$464),2,)} -> 23524 | V40: {=VLOOKUP(Q40&R40,IF({1,0},$B$2:$B$464&$F$2:$F$464,$D$2:$D$464),2,)} -> 强度室
A41: =ROW()-1 -> 40 | B41: 周天一 | C41: =IFERROR(VLOOKUP(B41,[1]工程研发事业部人员名单!B:D,2,0),"") -> 52345 | D41: =IFERROR(VLOOKUP(B41,[1]工程研发事业部人员名单!B:D,3,0),"") -> 结构一室 | E41: CR929设计（2022年复材中心） | F41: =G41+H41+I41+J41 -> 30 | I41: 30 | K41: 结构 | L41: 平尾 | N41: =VLOOKUP(E41,订单号!B:C,2,0) -> #N/A | O41: =VLOOKUP(C41,领导干部!B:B,1,0) -> #N/A | Q41: 梁枫 | R41: 393.37 | S41: {=VLOOKUP(Q41&R41,IF({1,0},$B$2:$B$464&$F$2:$F$464,$N$2:$N$464),2,)} -> 10502 | T41: {=VLOOKUP(Q41&R41,IF({1,0},$B$2:$B$464&$F$2:$F$464,$E$2:$E$464),2,)} -> 工程支持 | U41: {=VLOOKUP(Q41&R41,IF({1,0},$B$2:$B$464&$F$2:$F$464,$C$2:$C$464),2,)} -> 50316 | V41: {=VLOOKUP(Q41&R41,IF({1,0},$B$2:$B$464&$F$2:$F$464,$D$2:$D$464),2,)} -> 联络工程室
A42: =ROW()-1 -> 41 | B42: 卢伟 | C42: =IFERROR(VLOOKUP(B42,[1]工程研发事业部人员名单!B:D,2,0),"") -> 51844 | D42: =IFERROR(VLOOKUP(B42,[1]工程研发事业部人员名单!B:D,3,0),"") -> 结构一室 | E42: CR929设计（2022年复材中心） | F42: =G42+H42+I42+J42 -> 120 | I42: 120 | K42: 结构 | L42: 平尾 | N42: =VLOOKUP(E42,订单号!B:C,2,0) -> #N/A | O42: =VLOOKUP(C42,领导干部!B:B,1,0) -> #N/A | Q42: 林楠 | R42: 291.5 | S42: {=VLOOKUP(Q42&R42,IF({1,0},$B$2:$B$464&$F$2:$F$464,$N$2:$N$464),2,)} -> 10502 | T42: {=VLOOKUP(Q42&R42,IF({1,0},$B$2:$B$464&$F$2:$F$464,$E$2:$E$464),2,)} -> 工程支持 | U42: {=VLOOKUP(Q42&R42,IF({1,0},$B$2:$B$464&$F$2:$F$464,$C$2:$C$464),2,)} -> 25603 | V42: {=VLOOKUP(Q42&R42,IF({1,0},$B$2:$B$464&$F$2:$F$464,$D$2:$D$464),2,)} -> 联络工程室
A43: =ROW()-1 -> 42 | B43: 刘凯男 | C43: =IFERROR(VLOOKUP(B43,[1]工程研发事业部人员名单!B:D,2,0),"") -> 52156 | D43: =IFERROR(VLOOKUP(B43,[1]工程研发事业部人员名单!B:D,3,0),"") -> 系统室 | E43: CR929设计（2022年复材中心） | F43: =G43+H43+I43+J43 -> 20 | G43: 20 | K43: 强度 | L43: 平尾 | N43: =VLOOKUP(E43,订单号!B:C,2,0) -> #N/A | O43: =VLOOKUP(C43,领导干部!B:B,1,0) -> #N/A | Q43: 林树德 | R43: 160 | S43: {=VLOOKUP(Q43&R43,IF({1,0},$B$2:$B$464&$F$2:$F$464,$N$2:$N$464),2,)} -> YZ40000680 | T43: {=VLOOKUP(Q43&R43,IF({1,0},$B$2:$B$464&$F$2:$F$464,$E$2:$E$464),2,)} -> C919设计（2022年上飞院） | U43: {=VLOOKUP(Q43&R43,IF({1,0},$B$2:$B$464&$F$2:$F$464,$C$2:$C$464),2,)} -> 51202 | V43: {=VLOOKUP(Q43&R43,IF({1,0},$B$2:$B$464&$F$2:$F$464,$D$2:$D$464),2,)} -> 综合技术室
A44: =ROW()-1 -> 43 | B44: 朱照泽 | C44: =IFERROR(VLOOKUP(B44,[1]工程研发事业部人员名单!B:D,2,0),"") -> 51763 | D44: =IFERROR(VLOOKUP(B44,[1]工程研发事业部人员名单!B:D,3,0),"") -> 强度室 | E44: CR929设计（2022年复材中心） | F44: =G44+H44+I44+J44 -> 100 | I44: 100 | K44: 强度 | L44: 垂尾 | N44: =VLOOKUP(E44,订单号!B:C,2,0) -> #N/A | O44: =VLOOKUP(C44,领导干部!B:B,1,0) -> #N/A | Q44: 刘超 | R44: 90 | S44: {=VLOOKUP(Q44&R44,IF({1,0},$B$2:$B$464&$F$2:$F$464,$N$2:$N$464),2,)} -> #N/A | T44: {=VLOOKUP(Q44&R44,IF({1,0},$B$2:$B$464&$F$2:$F$464,$E$2:$E$464),2,)} -> 1号设计（2022年KTB） | U44: {=VLOOKUP(Q44&R44,IF({1,0},$B$2:$B$464&$F$2:$F$464,$C$2:$C$464),2,)} -> 51430 | V44: {=VLOOKUP(Q44&R44,IF({1,0},$B$2:$B$464&$F$2:$F$464,$D$2:$D$464),2,)} -> 系统室
A45: =ROW()-1 -> 44 | B45: 晨曦 | C45: =IFERROR(VLOOKUP(B45,[1]工程研发事业部人员名单!B:D,2,0),"") -> 50030 | D45: =IFERROR(VLOOKUP(B45,[1]工程研发事业部人员名单!B:D,3,0),"") -> 总体室 | E45: CR929设计（2022年复材中心） | F45: =G45+H45+I45+J45 -> 50 | I45: 50 | K45: 强度 | L45: 垂尾 | N45: =VLOOKUP(E45,订单号!B:C,2,0) -> #N/A | O45: =VLOOKUP(C45,领导干部!B:B,1,0) -> #N/A | Q45: 刘成 | R45: 65 | S45: {=VLOOKUP(Q45&R45,IF({1,0},$B$2:$B$464&$F$2:$F$464,$N$2:$N$464),2,)} -> #N/A | T45: {=VLOOKUP(Q45&R45,IF({1,0},$B$2:$B$464&$F$2:$F$464,$E$2:$E$464),2,)} -> CR929设计（2022年复材中心） | U45: {=VLOOKUP(Q45&R45,IF({1,0},$B$2:$B$464&$F$2:$F$464,$C$2:$C$464),2,)} -> 51860 | V45: {=VLOOKUP(Q45&R45,IF({1,0},$B$2:$B$464&$F$2:$F$464,$D$2:$D$464),2,)} -> 总体室
A46: =ROW()-1 -> 45 | B46: 黄文超 | C46: =IFERROR(VLOOKUP(B46,[1]工程研发事业部人员名单!B:D,2,0),"") -> 51200 | D46: =IFERROR(VLOOKUP(B46,[1]工程研发事业部人员名单!B:D,3,0),"") -> 强度室 | E46: CR929设计（2022年复材中心） | F46: =G46+H46+I46+J46 -> 50 | I46: 50 | K46: 强度 | L46: 垂尾 | N46: =VLOOKUP(E46,订单号!B:C,2,0) -> #N/A | O46: =VLOOKUP(C46,领导干部!B:B,1,0) -> #N/A | Q46: 刘聪 | R46: 222.9 | S46: {=VLOOKUP(Q46&R46,IF({1,0},$B$2:$B$464&$F$2:$F$464,$N$2:$N$464),2,)} -> #N/A | T46: {=VLOOKUP(Q46&R46,IF({1,0},$B$2:$B$464&$F$2:$F$464,$E$2:$E$464),2,)} -> 6号设计（2021年） | U46: {=VLOOKUP(Q46&R46,IF({1,0},$B$2:$B$464&$F$2:$F$464,$C$2:$C$464),2,)} -> 52018 | V46: {=VLOOKUP(Q46&R46,IF({1,0},$B$2:$B$464&$F$2:$F$464,$D$2:$D$464),2,)} -> 总体室
A47: =ROW()-1 -> 46 | B47: 王呈呈 | C47: =IFERROR(VLOOKUP(B47,[1]工程研发事业部人员名单!B:D,2,0),"") -> 51196 | D47: =IFERROR(VLOOKUP(B47,[1]工程研发事业部人员名单!B:D,3,0),"") -> 强度室 | E47: CR929设计（2022年复材中心） | F47: =G47+H47+I47+J47 -> 80 | I47: 80 | K47: 强度 | L47: 垂尾 | N47: =VLOOKUP(E47,订单号!B:C,2,0) -> #N/A | O47: =VLOOKUP(C47,领导干部!B:B,1,0) -> #N/A | Q47: 刘红双 | R47: 127 | S47: {=VLOOKUP(Q47&R47,IF({1,0},$B$2:$B$464&$F$2:$F$464,$N$2:$N$464),2,)} -> 10502 | T47: {=VLOOKUP(Q47&R47,IF({1,0},$B$2:$B$464&$F$2:$F$464,$E$2:$E$464),2,)} -> 工程支持 | U47: {=VLOOKUP(Q47&R47,IF({1,0},$B$2:$B$464&$F$2:$F$464,$C$2:$C$464),2,)} -> 51151 | V47: {=VLOOKUP(Q47&R47,IF({1,0},$B$2:$B$464&$F$2:$F$464,$D$2:$D$464),2,)} -> 综合技术室
A48: =ROW()-1 -> 47 | B48: 孟祥瑞 | C48: =IFERROR(VLOOKUP(B48,[1]工程研发事业部人员名单!B:D,2,0),"") -> 51615 | D48: =IFERROR(VLOOKUP(B48,[1]工程研发事业部人员名单!B:D,3,0),"") -> 结构一室 | E48: CR929设计（2022年复材中心） | F48: =G48+H48+I48+J48 -> 170 | I48: 170 | K48: 结构 | L48: 舵面 | N48: =VLOOKUP(E48,订单号!B:C,2,0) -> #N/A | O48: =VLOOKUP(C48,领导干部!B:B,1,0) -> #N/A | Q48: 刘金晶 | R48: 220 | S48: {=VLOOKUP(Q48&R48,IF({1,0},$B$2:$B$464&$F$2:$F$464,$N$2:$N$464),2,)} -> #N/A | T48: {=VLOOKUP(Q48&R48,IF({1,0},$B$2:$B$464&$F$2:$F$464,$E$2:$E$464),2,)} -> 1号设计（2022年KTB） | U48: {=VLOOKUP(Q48&R48,IF({1,0},$B$2:$B$464&$F$2:$F$464,$C$2:$C$464),2,)} -> 51641 | V48: {=VLOOKUP(Q48&R48,IF({1,0},$B$2:$B$464&$F$2:$F$464,$D$2:$D$464),2,)} -> 结构二室
A49: =ROW()-1 -> 48 | B49: 张熙尧 | C49: =IFERROR(VLOOKUP(B49,[1]工程研发事业部人员名单!B:D,2,0),"") -> 52017 | D49: =IFERROR(VLOOKUP(B49,[1]工程研发事业部人员名单!B:D,3,0),"") -> 结构一室 | E49: CR929设计（2022年复材中心） | F49: =G49+H49+I49+J49 -> 170 | I49: 170 | K49: 结构 | L49: 舵面 | N49: =VLOOKUP(E49,订单号!B:C,2,0) -> #N/A | O49: =VLOOKUP(C49,领导干部!B:B,1,0) -> #N/A | Q49: 刘凯男 | R49: 150 | S49: {=VLOOKUP(Q49&R49,IF({1,0},$B$2:$B$464&$F$2:$F$464,$N$2:$N$464),2,)} -> #N/A | T49: {=VLOOKUP(Q49&R49,IF({1,0},$B$2:$B$464&$F$2:$F$464,$E$2:$E$464),2,)} -> CR929设计（2022年复材中心） | U49: {=VLOOKUP(Q49&R49,IF({1,0},$B$2:$B$464&$F$2:$F$464,$C$2:$C$464),2,)} -> 52156 | V49: {=VLOOKUP(Q49&R49,IF({1,0},$B$2:$B$464&$F$2:$F$464,$D$2:$D$464),2,)} -> 系统室
A50: =ROW()-1 -> 49 | B50: 董晓莉 | C50: =IFERROR(VLOOKUP(B50,[1]工程研发事业部人员名单!B:D,2,0),"") -> 51211 | D50: =IFERROR(VLOOKUP(B50,[1]工程研发事业部人员名单!B:D,3,0),"") -> 结构一室 | E50: CR929设计（2022年复材中心） | F50: =G50+H50+I50+J50 -> 220 | I50: 220 | K50: 结构 | L50: 舵面 | N50: =VLOOKUP(E50,订单号!B:C,2,0) -> #N/A | O50: =VLOOKUP(C50,领导干部!B:B,1,0) -> #N/A | Q50: 刘可佳 | R50: 180 | S50: {=VLOOKUP(Q50&R50,IF({1,0},$B$2:$B$464&$F$2:$F$464,$N$2:$N$464),2,)} -> #N/A | T50: {=VLOOKUP(Q50&R50,IF({1,0},$B$2:$B$464&$F$2:$F$464,$E$2:$E$464),2,)} -> C919设计（2021年上飞院） | U50: {=VLOOKUP(Q50&R50,IF({1,0},$B$2:$B$464&$F$2:$F$464,$C$2:$C$464),2,)} -> 51793 | V50: {=VLOOKUP(Q50&R50,IF({1,0},$B$2:$B$464&$F$2:$F$464,$D$2:$D$464),2,)} -> 强度室
A51: =ROW()-1 -> 50 | B51: 晨曦 | C51: =IFERROR(VLOOKUP(B51,[1]工程研发事业部人员名单!B:D,2,0),"") -> 50030 | D51: =IFERROR(VLOOKUP(B51,[1]工程研发事业部人员名单!B:D,3,0),"") -> 总体室 | E51: CR929设计（2022年复材中心） | F51: =G51+H51+I51+J51 -> 50 | I51: 50 | K51: 强度 | L51: 舵面 | N51: =VLOOKUP(E51,订单号!B:C,2,0) -> #N/A | O51: =VLOOKUP(C51,领导干部!B:B,1,0) -> #N/A | Q51: 刘全 | R51: 220 | S51: {=VLOOKUP(Q51&R51,IF({1,0},$B$2:$B$464&$F$2:$F$464,$N$2:$N$464),2,)} -> YZ40000680 | T51: {=VLOOKUP(Q51&R51,IF({1,0},$B$2:$B$464&$F$2:$F$464,$E$2:$E$464),2,)} -> C919设计（2022年上飞院） | U51: {=VLOOKUP(Q51&R51,IF({1,0},$B$2:$B$464&$F$2:$F$464,$C$2:$C$464),2,)} -> 50874 | V51: {=VLOOKUP(Q51&R51,IF({1,0},$B$2:$B$464&$F$2:$F$464,$D$2:$D$464),2,)} -> 总体室
A52: =ROW()-1 -> 51 | B52: 马岩 | C52: =IFERROR(VLOOKUP(B52,[1]工程研发事业部人员名单!B:D,2,0),"") -> 50730 | D52: =IFERROR(VLOOKUP(B52,[1]工程研发事业部人员名单!B:D,3,0),"") -> 结构一室 | E52: CR929设计（2022年复材中心） | F52: =G52+H52+I52+J52 -> 60 | I52: 60 | K52: 结构 | L52: 货舱门 | N52: =VLOOKUP(E52,订单号!B:C,2,0) -> #N/A | O52: =VLOOKUP(C52,领导干部!B:B,1,0) -> #N/A | Q52: 刘曦 | R52: 80 | S52: {=VLOOKUP(Q52&R52,IF({1,0},$B$2:$B$464&$F$2:$F$464,$N$2:$N$464),2,)} -> #N/A | T52: {=VLOOKUP(Q52&R52,IF({1,0},$B$2:$B$464&$F$2:$F$464,$E$2:$E$464),2,)} -> 1号设计（2022年KTB） | U52: {=VLOOKUP(Q52&R52,IF({1,0},$B$2:$B$464&$F$2:$F$464,$C$2:$C$464),2,)} -> 52130 | V52: {=VLOOKUP(Q52&R52,IF({1,0},$B$2:$B$464&$F$2:$F$464,$D$2:$D$464),2,)} -> 强度室
A53: =ROW()-1 -> 52 | B53: 付容容 | C53: =IFERROR(VLOOKUP(B53,[1]工程研发事业部人员名单!B:D,2,0),"") -> 51183 | D53: =IFERROR(VLOOKUP(B53,[1]工程研发事业部人员名单!B:D,3,0),"") -> 结构一室 | E53: CR929设计（2022年复材中心） | F53: =G53+H53+I53+J53 -> 75 | I53: 75 | K53: 结构 | L53: 货舱门 | N53: =VLOOKUP(E53,订单号!B:C,2,0) -> #N/A | O53: =VLOOKUP(C53,领导干部!B:B,1,0) -> #N/A | Q53: 刘岩东 | R53: 150 | S53: {=VLOOKUP(Q53&R53,IF({1,0},$B$2:$B$464&$F$2:$F$464,$N$2:$N$464),2,)} -> 10502 | T53: {=VLOOKUP(Q53&R53,IF({1,0},$B$2:$B$464&$F$2:$F$464,$E$2:$E$464),2,)} -> 工程支持 | U53: {=VLOOKUP(Q53&R53,IF({1,0},$B$2:$B$464&$F$2:$F$464,$C$2:$C$464),2,)} -> 50245 | V53: {=VLOOKUP(Q53&R53,IF({1,0},$B$2:$B$464&$F$2:$F$464,$D$2:$D$464),2,)} -> 综合技术室
A54: =ROW()-1 -> 53 | B54: 张秀丽 | C54: =IFERROR(VLOOKUP(B54,[1]工程研发事业部人员名单!B:D,2,0),"") -> 51165 | D54: =IFERROR(VLOOKUP(B54,[1]工程研发事业部人员名单!B:D,3,0),"") -> 结构一室 | E54: CR929设计（2022年复材中心） | F54: =G54+H54+I54+J54 -> 50 | I54: 50 | K54: 结构 | L54: 起落架舱门 | N54: =VLOOKUP(E54,订单号!B:C,2,0) -> #N/A | O54: =VLOOKUP(C54,领导干部!B:B,1,0) -> #N/A | Q54: 刘洋 | R54: 2 | S54: {=VLOOKUP(Q54&R54,IF({1,0},$B$2:$B$464&$F$2:$F$464,$N$2:$N$464),2,)} -> 10502 | T54: {=VLOOKUP(Q54&R54,IF({1,0},$B$2:$B$464&$F$2:$F$464,$E$2:$E$464),2,)} -> 工程支持 | U54: {=VLOOKUP(Q54&R54,IF({1,0},$B$2:$B$464&$F$2:$F$464,$C$2:$C$464),2,)} -> 50709 | V54: {=VLOOKUP(Q54&R54,IF({1,0},$B$2:$B$464&$F$2:$F$464,$D$2:$D$464),2,)} -> 系统室
A55: =ROW()-1 -> 54 | B55: 栾鹏 | C55: =IFERROR(VLOOKUP(B55,[1]工程研发事业部人员名单!B:D,2,0),"") -> 51781 | D55: =IFERROR(VLOOKUP(B55,[1]工程研发事业部人员名单!B:D,3,0),"") -> 结构一室 | E55: CR929设计（2022年复材中心） | F55: =G55+H55+I55+J55 -> 40 | I55: 40 | K55: 结构 | L55: 起落架舱门 | N55: =VLOOKUP(E55,订单号!B:C,2,0) -> #N/A | O55: =VLOOKUP(C55,领导干部!B:B,1,0) -> #N/A | Q55: 刘媛媛 | R55: 123 | S55: {=VLOOKUP(Q55&R55,IF({1,0},$B$2:$B$464&$F$2:$F$464,$N$2:$N$464),2,)} -> #N/A | T55: {=VLOOKUP(Q55&R55,IF({1,0},$B$2:$B$464&$F$2:$F$464,$E$2:$E$464),2,)} -> 6号设计（2021年） | U55: {=VLOOKUP(Q55&R55,IF({1,0},$B$2:$B$464&$F$2:$F$464,$C$2:$C$464),2,)} -> 51385 | V55: {=VLOOKUP(Q55&R55,IF({1,0},$B$2:$B$464&$F$2:$F$464,$D$2:$D$464),2,)} -> 系统室
... A61: =ROW()-1 -> 60 | B61: 张秀丽 | C61: =IFERROR(VLOOKUP(B61,[1]工程研发事业部人员名单!B:D,2,0),"") -> 51165 | D61: =IFERROR(VLOOKUP(B61,[1]工程研发事业部人员名单!B:D,3,0),"") -> 结构一室 | E61: CR929设计（2022年上飞院） | F61: =G61+H61+I61+J61 -> 150 | I61: 150 | K61: 结构 | L61: 散货舱门 | N61: =VLOOKUP(E61,订单号!B:C,2,0) -> #N/A | O61: =VLOOKUP(C61,领导干部!B:B,1,0) -> #N/A | Q61: 骆美玲 | R61: 115 | S61: {=VLOOKUP(Q61&R61,IF({1,0},$B$2:$B$464&$F$2:$F$464,$N$2:$N$464),2,)} -> #N/A | T61: {=VLOOKUP(Q61&R61,IF({1,0},$B$2:$B$464&$F$2:$F$464,$E$2:$E$464),2,)} -> 6号设计（2021年） | U61: {=VLOOKUP(Q61&R61,IF({1,0},$B$2:$B$464&$F$2:$F$464,$C$2:$C$464),2,)} -> 50713 | V61: {=VLOOKUP(Q61&R61,IF({1,0},$B$2:$B$464&$F$2:$F$464,$D$2:$D$464),2,)} -> 系统室
A62: =ROW()-1 -> 61 | B62: 付容容 | C62: =IFERROR(VLOOKUP(B62,[1]工程研发事业部人员名单!B:D,2,0),"") -> 51183 | D62: =IFERROR(VLOOKUP(B62,[1]工程研发事业部人员名单!B:D,3,0),"") -> 结构一室 | E62: CR929设计（2022年上飞院） | F62: =G62+H62+I62+J62 -> 0 | K62: 结构 | L62: 散货舱门 | N62: =VLOOKUP(E62,订单号!B:C,2,0) -> #N/A | O62: =VLOOKUP(C62,领导干部!B:B,1,0) -> #N/A | Q62: 吕冬兰 | R62: 170 | S62: {=VLOOKUP(Q62&R62,IF({1,0},$B$2:$B$464&$F$2:$F$464,$N$2:$N$464),2,)} -> YZ40000680 | T62: {=VLOOKUP(Q62&R62,IF({1,0},$B$2:$B$464&$F$2:$F$464,$E$2:$E$464),2,)} -> C919设计（2022年上飞院） | U62: {=VLOOKUP(Q62&R62,IF({1,0},$B$2:$B$464&$F$2:$F$464,$C$2:$C$464),2,)} -> 51160 | V62: {=VLOOKUP(Q62&R62,IF({1,0},$B$2:$B$464&$F$2:$F$464,$D$2:$D$464),2,)} -> 综合技术室
A63: =ROW()-1 -> 62 | B63: 纪可 | C63: =IFERROR(VLOOKUP(B63,[1]工程研发事业部人员名单!B:D,2,0),"") -> 26689 | D63: =IFERROR(VLOOKUP(B63,[1]工程研发事业部人员名单!B:D,3,0),"") -> 强度室 | E63: CR929设计（2022年上飞院） | F63: =G63+H63+I63+J63 -> 60 | I63: 60 | K63: 强度 | L63: 散货舱门 | N63: =VLOOKUP(E63,订单号!B:C,2,0) -> #N/A | O63: =VLOOKUP(C63,领导干部!B:B,1,0) -> #N/A | Q63: 吕国成 | R63: 284.4 | S63: {=VLOOKUP(Q63&R63,IF({1,0},$B$2:$B$464&$F$2:$F$464,$N$2:$N$464),2,)} -> #N/A | T63: {=VLOOKUP(Q63&R63,IF({1,0},$B$2:$B$464&$F$2:$F$464,$E$2:$E$464),2,)} -> 6号设计（2021年） | U63: {=VLOOKUP(Q63&R63,IF({1,0},$B$2:$B$464&$F$2:$F$464,$C$2:$C$464),2,)} -> 51188 | V63: {=VLOOKUP(Q63&R63,IF({1,0},$B$2:$B$464&$F$2:$F$464,$D$2:$D$464),2,)} -> 强度室
A64: =ROW()-1 -> 63 | B64: 陈瑞东 | C64: =IFERROR(VLOOKUP(B64,[1]工程研发事业部人员名单!B:D,2,0),"") -> 51181 | D64: =IFERROR(VLOOKUP(B64,[1]工程研发事业部人员名单!B:D,3,0),"") -> 强度室 | E64: CR929设计（2022年上飞院） | F64: =G64+H64+I64+J64 -> 220 | I64: 220 | K64: 强度 | L64: 登机门 | N64: =VLOOKUP(E64,订单号!B:C,2,0) -> #N/A | O64: =VLOOKUP(C64,领导干部!B:B,1,0) -> #N/A | Q64: 马佳 | R64: 300 | S64: {=VLOOKUP(Q64&R64,IF({1,0},$B$2:$B$464&$F$2:$F$464,$N$2:$N$464),2,)} -> #N/A | T64: {=VLOOKUP(Q64&R64,IF({1,0},$B$2:$B$464&$F$2:$F$464,$E$2:$E$464),2,)} -> 1号设计（2022年KTB） | U64: {=VLOOKUP(Q64&R64,IF({1,0},$B$2:$B$464&$F$2:$F$464,$C$2:$C$464),2,)} -> 52236 | V64: {=VLOOKUP(Q64&R64,IF({1,0},$B$2:$B$464&$F$2:$F$464,$D$2:$D$464),2,)} -> 结构一室
A65: =ROW()-1 -> 64 | B65: 秦超 | C65: =IFERROR(VLOOKUP(B65,[1]工程研发事业部人员名单!B:D,2,0),"") -> 51591 | D65: =IFERROR(VLOOKUP(B65,[1]工程研发事业部人员名单!B:D,3,0),"") -> 总体室 | E65: CR929设计（2022年上飞院） | F65: =G65+H65+I65+J65 -> 170 | I65: 170 | K65: 强度 | L65: 登机门 | N65: =VLOOKUP(E65,订单号!B:C,2,0) -> #N/A | O65: =VLOOKUP(C65,领导干部!B:B,1,0) -> #N/A | Q65: 马爽 | R65: 192 | S65: {=VLOOKUP(Q65&R65,IF({1,0},$B$2:$B$464&$F$2:$F$464,$N$2:$N$464),2,)} -> #N/A | T65: {=VLOOKUP(Q65&R65,IF({1,0},$B$2:$B$464&$F$2:$F$464,$E$2:$E$464),2,)} -> CR929设计（2022年复材中心） | U65: {=VLOOKUP(Q65&R65,IF({1,0},$B$2:$B$464&$F$2:$F$464,$C$2:$C$464),2,)} -> 51642 | V65: {=VLOOKUP(Q65&R65,IF({1,0},$B$2:$B$464&$F$2:$F$464,$D$2:$D$464),2,)} -> 结构二室
A66: =ROW()-1 -> 65 | B66: 夏新鑫 | C66: =IFERROR(VLOOKUP(B66,[1]工程研发事业部人员名单!B:D,2,0),"") -> 50876 | D66: =IFERROR(VLOOKUP(B66,[1]工程研发事业部人员名单!B:D,3,0),"") -> 工程项目室 | E66: CR929设计（2022年复材中心） | F66: =G66+H66+I66+J66 -> 206 | I66: 206 | K66: PMO | L66: 工程项目 | N66: =VLOOKUP(E66,订单号!B:C,2,0) -> #N/A | O66: =VLOOKUP(C66,领导干部!B:B,1,0) -> #N/A | Q66: 马雪菲 | R66: 80 | S66: {=VLOOKUP(Q66&R66,IF({1,0},$B$2:$B$464&$F$2:$F$464,$N$2:$N$464),2,)} -> #N/A | T66: {=VLOOKUP(Q66&R66,IF({1,0},$B$2:$B$464&$F$2:$F$464,$E$2:$E$464),2,)} -> CR929设计（2022年复材中心） | U66: {=VLOOKUP(Q66&R66,IF({1,0},$B$2:$B$464&$F$2:$F$464,$C$2:$C$464),2,)} -> 52560 | V66: {=VLOOKUP(Q66&R66,IF({1,0},$B$2:$B$464&$F$2:$F$464,$D$2:$D$464),2,)} -> 强度室
A67: =ROW()-1 -> 66 | B67: 晨曦 | C67: =IFERROR(VLOOKUP(B67,[1]工程研发事业部人员名单!B:D,2,0),"") -> 50030 | D67: =IFERROR(VLOOKUP(B67,[1]工程研发事业部人员名单!B:D,3,0),"") -> 总体室 | E67: 工程支持 | F67: =G67+H67+I67+J67 -> 7.5 | I67: 7.5 | M67: 内控工作 | N67: =VLOOKUP(E67,订单号!B:C,2,0) -> 10502 | O67: =VLOOKUP(C67,领导干部!B:B,1,0) -> #N/A | Q67: 马岩 | R67: 315 | S67: {=VLOOKUP(Q67&R67,IF({1,0},$B$2:$B$464&$F$2:$F$464,$N$2:$N$464),2,)} -> YZ40000680 | T67: {=VLOOKUP(Q67&R67,IF({1,0},$B$2:$B$464&$F$2:$F$464,$E$2:$E$464),2,)} -> C919设计（2022年上飞院） | U67: {=VLOOKUP(Q67&R67,IF({1,0},$B$2:$B$464&$F$2:$F$464,$C$2:$C$464),2,)} -> 50730 | V67: {=VLOOKUP(Q67&R67,IF({1,0},$B$2:$B$464&$F$2:$F$464,$D$2:$D$464),2,)} -> 结构一室
A68: =ROW()-1 -> 67 | B68: 任璐璐 | C68: =IFERROR(VLOOKUP(B68,[1]工程研发事业部人员名单!B:D,2,0),"") -> 50032 | D68: =IFERROR(VLOOKUP(B68,[1]工程研发事业部人员名单!B:D,3,0),"") -> 总体室 | E68: 工程支持 | F68: =G68+H68+I68+J68 -> 4.5 | I68: 4.5 | M68: 内控工作 | N68: =VLOOKUP(E68,订单号!B:C,2,0) -> 10502 | O68: =VLOOKUP(C68,领导干部!B:B,1,0) -> #N/A | Q68: 马艺丹 | R68: 224.55 | S68: {=VLOOKUP(Q68&R68,IF({1,0},$B$2:$B$464&$F$2:$F$464,$N$2:$N$464),2,)} -> 10502 | T68: {=VLOOKUP(Q68&R68,IF({1,0},$B$2:$B$464&$F$2:$F$464,$E$2:$E$464),2,)} -> 工程支持 | U68: {=VLOOKUP(Q68&R68,IF({1,0},$B$2:$B$464&$F$2:$F$464,$C$2:$C$464),2,)} -> 51665 | V68: {=VLOOKUP(Q68&R68,IF({1,0},$B$2:$B$464&$F$2:$F$464,$D$2:$D$464),2,)} -> 联络工程室
A69: =ROW()-1 -> 68 | B69: 赵婷 | C69: =IFERROR(VLOOKUP(B69,[1]工程研发事业部人员名单!B:D,2,0),"") -> 50702 | D69: =IFERROR(VLOOKUP(B69,[1]工程研发事业部人员名单!B:D,3,0),"") -> 总体室 | E69: 工程支持 | F69: =G69+H69+I69+J69 -> 4.5 | I69: 4.5 | M69: 内控工作 | N69: =VLOOKUP(E69,订单号!B:C,2,0) -> 10502 | O69: =VLOOKUP(C69,领导干部!B:B,1,0) -> #N/A | Q69: 马壮 | R69: 300 | S69: {=VLOOKUP(Q69&R69,IF({1,0},$B$2:$B$464&$F$2:$F$464,$N$2:$N$464),2,)} -> #N/A | T69: {=VLOOKUP(Q69&R69,IF({1,0},$B$2:$B$464&$F$2:$F$464,$E$2:$E$464),2,)} -> 1号设计（2022年KTB） | U69: {=VLOOKUP(Q69&R69,IF({1,0},$B$2:$B$464&$F$2:$F$464,$C$2:$C$464),2,)} -> 51640 | V69: {=VLOOKUP(Q69&R69,IF({1,0},$B$2:$B$464&$F$2:$F$464,$D$2:$D$464),2,)} -> 结构一室
A70: =ROW()-1 -> 69 | B70: 刘全 | C70: =IFERROR(VLOOKUP(B70,[1]工程研发事业部人员名单!B:D,2,0),"") -> 50874 | D70: =IFERROR(VLOOKUP(B70,[1]工程研发事业部人员名单!B:D,3,0),"") -> 总体室 | E70: 工程支持 | F70: =G70+H70+I70+J70 -> 4.5 | I70: 4.5 | M70: 内控工作 | N70: =VLOOKUP(E70,订单号!B:C,2,0) -> 10502 | O70: =VLOOKUP(C70,领导干部!B:B,1,0) -> #N/A | Q70: 孟力华 | R70: 120 | S70: {=VLOOKUP(Q70&R70,IF({1,0},$B$2:$B$464&$F$2:$F$464,$N$2:$N$464),2,)} -> #N/A | T70: {=VLOOKUP(Q70&R70,IF({1,0},$B$2:$B$464&$F$2:$F$464,$E$2:$E$464),2,)} -> C919设计（2021年上飞院） | U70: {=VLOOKUP(Q70&R70,IF({1,0},$B$2:$B$464&$F$2:$F$464,$C$2:$C$464),2,)} -> 51234 | V70: {=VLOOKUP(Q70&R70,IF({1,0},$B$2:$B$464&$F$2:$F$464,$D$2:$D$464),2,)} -> 结构二室
A71: =ROW()-1 -> 70 | B71: 秦超 | C71: =IFERROR(VLOOKUP(B71,[1]工程研发事业部人员名单!B:D,2,0),"") -> 51591 | D71: =IFERROR(VLOOKUP(B71,[1]工程研发事业部人员名单!B:D,3,0),"") -> 总体室 | E71: 工程支持 | F71: =G71+H71+I71+J71 -> 4.5 | I71: 4.5 | M71: 内控工作 | N71: =VLOOKUP(E71,订单号!B:C,2,0) -> 10502 | O71: =VLOOKUP(C71,领导干部!B:B,1,0) -> #N/A | Q71: 孟玲俊 | R71: 164 | S71: {=VLOOKUP(Q71&R71,IF({1,0},$B$2:$B$464&$F$2:$F$464,$N$2:$N$464),2,)} -> #N/A | T71: {=VLOOKUP(Q71&R71,IF({1,0},$B$2:$B$464&$F$2:$F$464,$E$2:$E$464),2,)} -> CR929设计（2022年复材中心） | U71: {=VLOOKUP(Q71&R71,IF({1,0},$B$2:$B$464&$F$2:$F$464,$C$2:$C$464),2,)} -> 22298 | V71: {=VLOOKUP(Q71&R71,IF({1,0},$B$2:$B$464&$F$2:$F$464,$D$2:$D$464),2,)} -> 结构二室
A72: =ROW()-1 -> 71 | B72: 赵长辉 | C72: =IFERROR(VLOOKUP(B72,[1]工程研发事业部人员名单!B:D,2,0),"") -> 17725 | D72: =IFERROR(VLOOKUP(B72,[1]工程研发事业部人员名单!B:D,3,0),"") -> 总体室 | E72: 工程支持 | F72: =G72+H72+I72+J72 -> 4.5 | I72: 4.5 | M72: 内控工作 | N72: =VLOOKUP(E72,订单号!B:C,2,0) -> 10502 | O72: =VLOOKUP(C72,领导干部!B:B,1,0) -> #N/A | Q72: 孟维宇 | R72: 260 | S72: {=VLOOKUP(Q72&R72,IF({1,0},$B$2:$B$464&$F$2:$F$464,$N$2:$N$464),2,)} -> YZ40000680 | T72: {=VLOOKUP(Q72&R72,IF({1,0},$B$2:$B$464&$F$2:$F$464,$E$2:$E$464),2,)} -> C919设计（2022年上飞院） | U72: {=VLOOKUP(Q72&R72,IF({1,0},$B$2:$B$464&$F$2:$F$464,$C$2:$C$464),2,)} -> 50722 | V72: {=VLOOKUP(Q72&R72,IF({1,0},$B$2:$B$464&$F$2:$F$464,$D$2:$D$464),2,)} -> 强度室
A73: =ROW()-1 -> 72 | B73: 刘成 | C73: =IFERROR(VLOOKUP(B73,[1]工程研发事业部人员名单!B:D,2,0),"") -> 51860 | D73: =IFERROR(VLOOKUP(B73,[1]工程研发事业部人员名单!B:D,3,0),"") -> 总体室 | E73: 工程支持 | F73: =G73+H73+I73+J73 -> 4 | I73: 4 | M73: 内控工作 | N73: =VLOOKUP(E73,订单号!B:C,2,0) -> 10502 | O73: =VLOOKUP(C73,领导干部!B:B,1,0) -> #N/A | Q73: 孟祥瑞 | R73: 170 | S73: {=VLOOKUP(Q73&R73,IF({1,0},$B$2:$B$464&$F$2:$F$464,$N$2:$N$464),2,)} -> #N/A | T73: {=VLOOKUP(Q73&R73,IF({1,0},$B$2:$B$464&$F$2:$F$464,$E$2:$E$464),2,)} -> CR929设计（2022年复材中心） | U73: {=VLOOKUP(Q73&R73,IF({1,0},$B$2:$B$464&$F$2:$F$464,$C$2:$C$464),2,)} -> 51615 | V73: {=VLOOKUP(Q73&R73,IF({1,0},$B$2:$B$464&$F$2:$F$464,$D$2:$D$464),2,)} -> 结构一室
A74: =ROW()-1 -> 73 | B74: 晨曦 | C74: =IFERROR(VLOOKUP(B74,[1]工程研发事业部人员名单!B:D,2,0),"") -> 50030 | D74: =IFERROR(VLOOKUP(B74,[1]工程研发事业部人员名单!B:D,3,0),"") -> 总体室 | E74: 工程支持 | F74: =G74+H74+I74+J74 -> 12 | I74: 12 | M74: 内控工作 | N74: =VLOOKUP(E74,订单号!B:C,2,0) -> 10502 | O74: =VLOOKUP(C74,领导干部!B:B,1,0) -> #N/A | Q74: 牛福春 | R74: 168 | S74: {=VLOOKUP(Q74&R74,IF({1,0},$B$2:$B$464&$F$2:$F$464,$N$2:$N$464),2,)} -> #N/A | T74: {=VLOOKUP(Q74&R74,IF({1,0},$B$2:$B$464&$F$2:$F$464,$E$2:$E$464),2,)} -> CR929设计（2022年复材中心） | U74: {=VLOOKUP(Q74&R74,IF({1,0},$B$2:$B$464&$F$2:$F$464,$C$2:$C$464),2,)} -> 50710 | V74: {=VLOOKUP(Q74&R74,IF({1,0},$B$2:$B$464&$F$2:$F$464,$D$2:$D$464),2,)} -> 结构二室
A75: =ROW()-1 -> 74 | B75: 葛春生 | C75: =IFERROR(VLOOKUP(B75,[1]工程研发事业部人员名单!B:D,2,0),"") -> 51410 | D75: =IFERROR(VLOOKUP(B75,[1]工程研发事业部人员名单!B:D,3,0),"") -> 结构一室 | E75: 工程支持 | F75: =G75+H75+I75+J75 -> 12 | I75: 12 | M75: 内控工作 | N75: =VLOOKUP(E75,订单号!B:C,2,0) -> 10502 | O75: =VLOOKUP(C75,领导干部!B:B,1,0) -> #N/A | Q75: 牛建庄 | R75: 292 | S75: {=VLOOKUP(Q75&R75,IF({1,0},$B$2:$B$464&$F$2:$F$464,$N$2:$N$464),2,)} -> 10502 | T75: {=VLOOKUP(Q75&R75,IF({1,0},$B$2:$B$464&$F$2:$F$464,$E$2:$E$464),2,)} -> 工程支持 | U75: {=VLOOKUP(Q75&R75,IF({1,0},$B$2:$B$464&$F$2:$F$464,$C$2:$C$464),2,)} -> 17090 | V75: {=VLOOKUP(Q75&R75,IF({1,0},$B$2:$B$464&$F$2:$F$464,$D$2:$D$464),2,)} -> 联络工程室
A76: =ROW()-1 -> 75 | B76: 马岩 | C76: =IFERROR(VLOOKUP(B76,[1]工程研发事业部人员名单!B:D,2,0),"") -> 50730 | D76: =IFERROR(VLOOKUP(B76,[1]工程研发事业部人员名单!B:D,3,0),"") -> 结构一室 | E76: 工程支持 | F76: =G76+H76+I76+J76 -> 12 | I76: 12 | M76: 内控工作 | N76: =VLOOKUP(E76,订单号!B:C,2,0) -> 10502 | O76: =VLOOKUP(C76,领导干部!B:B,1,0) -> #N/A | Q76: 潘英 | R76: 162 | S76: {=VLOOKUP(Q76&R76,IF({1,0},$B$2:$B$464&$F$2:$F$464,$N$2:$N$464),2,)} -> #N/A | T76: {=VLOOKUP(Q76&R76,IF({1,0},$B$2:$B$464&$F$2:$F$464,$E$2:$E$464),2,)} -> 1号设计（2022年KTB） | U76: {=VLOOKUP(Q76&R76,IF({1,0},$B$2:$B$464&$F$2:$F$464,$C$2:$C$464),2,)} -> 50864 | V76: {=VLOOKUP(Q76&R76,IF({1,0},$B$2:$B$464&$F$2:$F$464,$D$2:$D$464),2,)} -> 综合技术室
A77: =ROW()-1 -> 76 | B77: 丛家勇 | C77: =IFERROR(VLOOKUP(B77,[1]工程研发事业部人员名单!B:D,2,0),"") -> 50281 | D77: =IFERROR(VLOOKUP(B77,[1]工程研发事业部人员名单!B:D,3,0),"") -> 结构一室 | E77: 工程支持 | F77: =G77+H77+I77+J77 -> 11.5 | I77: 11.5 | M77: 内控工作 | N77: =VLOOKUP(E77,订单号!B:C,2,0) -> 10502 | O77: =VLOOKUP(C77,领导干部!B:B,1,0) -> #N/A | Q77: 秦超 | R77: 170 | S77: {=VLOOKUP(Q77&R77,IF({1,0},$B$2:$B$464&$F$2:$F$464,$N$2:$N$464),2,)} -> #N/A | T77: {=VLOOKUP(Q77&R77,IF({1,0},$B$2:$B$464&$F$2:$F$464,$E$2:$E$464),2,)} -> CR929设计（2022年上飞院） | U77: {=VLOOKUP(Q77&R77,IF({1,0},$B$2:$B$464&$F$2:$F$464,$C$2:$C$464),2,)} -> 51591 | V77: {=VLOOKUP(Q77&R77,IF({1,0},$B$2:$B$464&$F$2:$F$464,$D$2:$D$464),2,)} -> 总体室
A78: =ROW()-1 -> 77 | B78: 魏士礼 | C78: =IFERROR(VLOOKUP(B78,[1]工程研发事业部人员名单!B:D,2,0),"") -> 22294 | D78: =IFERROR(VLOOKUP(B78,[1]工程研发事业部人员名单!B:D,3,0),"") -> 结构一室 | E78: 工程支持 | F78: =G78+H78+I78+J78 -> 11.5 | I78: 11.5 | M78: 内控工作 | N78: =VLOOKUP(E78,订单号!B:C,2,0) -> 10502 | O78: =VLOOKUP(C78,领导干部!B:B,1,0) -> #N/A | Q78: 曲汝文 | R78: 190 | S78: {=VLOOKUP(Q78&R78,IF({1,0},$B$2:$B$464&$F$2:$F$464,$N$2:$N$464),2,)} -> #N/A | T78: {=VLOOKUP(Q78&R78,IF({1,0},$B$2:$B$464&$F$2:$F$464,$E$2:$E$464),2,)} -> 1号设计（2022年KTB） | U78: {=VLOOKUP(Q78&R78,IF({1,0},$B$2:$B$464&$F$2:$F$464,$C$2:$C$464),2,)} -> 52133 | V78: {=VLOOKUP(Q78&R78,IF({1,0},$B$2:$B$464&$F$2:$F$464,$D$2:$D$464),2,)} -> 结构一室
... A109: =ROW()-1 -> 108 | B109: 赵书凯 | C109: =IFERROR(VLOOKUP(B109,[1]工程研发事业部人员名单!B:D,2,0),"") -> 50832 | D109: =IFERROR(VLOOKUP(B109,[1]工程研发事业部人员名单!B:D,3,0),"") -> 联络工程室 | E109: 工程支持 | F109: =G109+H109+I109+J109 -> 3 | I109: 3 | M109: 内控工作 | N109: =VLOOKUP(E109,订单号!B:C,2,0) -> 10502 | O109: =VLOOKUP(C109,领导干部!B:B,1,0) -> #N/A | Q109: 魏士礼 | R109: 200 | S109: {=VLOOKUP(Q109&R109,IF({1,0},$B$2:$B$464&$F$2:$F$464,$N$2:$N$464),2,)} -> YZ40000680 | T109: {=VLOOKUP(Q109&R109,IF({1,0},$B$2:$B$464&$F$2:$F$464,$E$2:$E$464),2,)} -> C919设计（2022年上飞院） | U109: {=VLOOKUP(Q109&R109,IF({1,0},$B$2:$B$464&$F$2:$F$464,$C$2:$C$464),2,)} -> 22294 | V109: {=VLOOKUP(Q109&R109,IF({1,0},$B$2:$B$464&$F$2:$F$464,$D$2:$D$464),2,)} -> 结构一室
A110: =ROW()-1 -> 109 | B110: 李守玺 | C110: =IFERROR(VLOOKUP(B110,[1]工程研发事业部人员名单!B:D,2,0),"") -> 25763 | D110: =IFERROR(VLOOKUP(B110,[1]工程研发事业部人员名单!B:D,3,0),"") -> 结构一室 | E110: 1号设计（2022年KTB） | F110: =G110+H110+I110+J110 -> 300 | I110: 300 | N110: =VLOOKUP(E110,订单号!B:C,2,0) -> #N/A | O110: =VLOOKUP(C110,领导干部!B:B,1,0) -> #N/A | Q110: 吴晓莉 | R110: 175 | S110: {=VLOOKUP(Q110&R110,IF({1,0},$B$2:$B$464&$F$2:$F$464,$N$2:$N$464),2,)} -> #N/A | T110: {=VLOOKUP(Q110&R110,IF({1,0},$B$2:$B$464&$F$2:$F$464,$E$2:$E$464),2,)} -> 1号设计（2022年KTB） | U110: {=VLOOKUP(Q110&R110,IF({1,0},$B$2:$B$464&$F$2:$F$464,$C$2:$C$464),2,)} -> 50872 | V110: {=VLOOKUP(Q110&R110,IF({1,0},$B$2:$B$464&$F$2:$F$464,$D$2:$D$464),2,)} -> 系统室
A111: =ROW()-1 -> 110 | B111: 康志明 | C111: =IFERROR(VLOOKUP(B111,[1]工程研发事业部人员名单!B:D,2,0),"") -> 25765 | D111: =IFERROR(VLOOKUP(B111,[1]工程研发事业部人员名单!B:D,3,0),"") -> 结构一室 | E111: 1号设计（2022年KTB） | F111: =G111+H111+I111+J111 -> 240 | I111: 240 | N111: =VLOOKUP(E111,订单号!B:C,2,0) -> #N/A | O111: =VLOOKUP(C111,领导干部!B:B,1,0) -> #N/A | Q111: 夏新鑫 | R111: 206 | S111: {=VLOOKUP(Q111&R111,IF({1,0},$B$2:$B$464&$F$2:$F$464,$N$2:$N$464),2,)} -> #N/A | T111: {=VLOOKUP(Q111&R111,IF({1,0},$B$2:$B$464&$F$2:$F$464,$E$2:$E$464),2,)} -> CR929设计（2022年复材中心） | U111: {=VLOOKUP(Q111&R111,IF({1,0},$B$2:$B$464&$F$2:$F$464,$C$2:$C$464),2,)} -> 50876 | V111: {=VLOOKUP(Q111&R111,IF({1,0},$B$2:$B$464&$F$2:$F$464,$D$2:$D$464),2,)} -> 工程项目室
A112: =ROW()-1 -> 111 | B112: 塔拉 | C112: =IFERROR(VLOOKUP(B112,[1]工程研发事业部人员名单!B:D,2,0),"") -> 25548 | D112: =IFERROR(VLOOKUP(B112,[1]工程研发事业部人员名单!B:D,3,0),"") -> 结构一室 | E112: 1号设计（2022年KTB） | F112: =G112+H112+I112+J112 -> 255 | I112: 255 | N112: =VLOOKUP(E112,订单号!B:C,2,0) -> #N/A | O112: =VLOOKUP(C112,领导干部!B:B,1,0) -> #N/A | Q112: 徐丹 | R112: 166 | S112: {=VLOOKUP(Q112&R112,IF({1,0},$B$2:$B$464&$F$2:$F$464,$N$2:$N$464),2,)} -> #N/A | T112: {=VLOOKUP(Q112&R112,IF({1,0},$B$2:$B$464&$F$2:$F$464,$E$2:$E$464),2,)} -> CR929设计（2022年复材中心） | U112: {=VLOOKUP(Q112&R112,IF({1,0},$B$2:$B$464&$F$2:$F$464,$C$2:$C$464),2,)} -> 51407 | V112: {=VLOOKUP(Q112&R112,IF({1,0},$B$2:$B$464&$F$2:$F$464,$D$2:$D$464),2,)} -> 结构二室
A113: =ROW()-1 -> 112 | B113: 杨春 | C113: =IFERROR(VLOOKUP(B113,[1]工程研发事业部人员名单!B:D,2,0),"") -> 51624 | D113: =IFERROR(VLOOKUP(B113,[1]工程研发事业部人员名单!B:D,3,0),"") -> 结构一室 | E113: 1号设计（2022年KTB） | F113: =G113+H113+I113+J113 -> 30 | I113: 30 | N113: =VLOOKUP(E113,订单号!B:C,2,0) -> #N/A | O113: =VLOOKUP(C113,领导干部!B:B,1,0) -> #N/A | Q113: 徐君升 | R113: 260 | S113: {=VLOOKUP(Q113&R113,IF({1,0},$B$2:$B$464&$F$2:$F$464,$N$2:$N$464),2,)} -> YZ40000680 | T113: {=VLOOKUP(Q113&R113,IF({1,0},$B$2:$B$464&$F$2:$F$464,$E$2:$E$464),2,)} -> C919设计（2022年上飞院） | U113: {=VLOOKUP(Q113&R113,IF({1,0},$B$2:$B$464&$F$2:$F$464,$C$2:$C$464),2,)} -> 50716 | V113: {=VLOOKUP(Q113&R113,IF({1,0},$B$2:$B$464&$F$2:$F$464,$D$2:$D$464),2,)} -> 强度室
A114: =ROW()-1 -> 113 | B114: 赵莉 | C114: =IFERROR(VLOOKUP(B114,[1]工程研发事业部人员名单!B:D,2,0),"") -> 50065 | D114: =IFERROR(VLOOKUP(B114,[1]工程研发事业部人员名单!B:D,3,0),"") -> 结构二室 | E114: 1号设计（2022年KTB） | F114: =G114+H114+I114+J114 -> 225 | I114: 225 | N114: =VLOOKUP(E114,订单号!B:C,2,0) -> #N/A | O114: =VLOOKUP(C114,领导干部!B:B,1,0) -> #N/A | Q114: 徐丽娜 | R114: 50 | S114: {=VLOOKUP(Q114&R114,IF({1,0},$B$2:$B$464&$F$2:$F$464,$N$2:$N$464),2,)} -> #N/A | T114: {=VLOOKUP(Q114&R114,IF({1,0},$B$2:$B$464&$F$2:$F$464,$E$2:$E$464),2,)} -> C919设计（2020年上飞院） | U114: {=VLOOKUP(Q114&R114,IF({1,0},$B$2:$B$464&$F$2:$F$464,$C$2:$C$464),2,)} -> 50079 | V114: {=VLOOKUP(Q114&R114,IF({1,0},$B$2:$B$464&$F$2:$F$464,$D$2:$D$464),2,)} -> 工程项目室
A115: =ROW()-1 -> 114 | B115: 李森 | C115: =IFERROR(VLOOKUP(B115,[1]工程研发事业部人员名单!B:D,2,0),"") -> 17238 | D115: =IFERROR(VLOOKUP(B115,[1]工程研发事业部人员名单!B:D,3,0),"") -> 结构二室 | E115: 1号设计（2022年KTB） | F115: =G115+H115+I115+J115 -> 260 | I115: 260 | N115: =VLOOKUP(E115,订单号!B:C,2,0) -> #N/A | O115: =VLOOKUP(C115,领导干部!B:B,1,0) -> #N/A | Q115: 许美娟 | R115: 120 | S115: {=VLOOKUP(Q115&R115,IF({1,0},$B$2:$B$464&$F$2:$F$464,$N$2:$N$464),2,)} -> #N/A | T115: {=VLOOKUP(Q115&R115,IF({1,0},$B$2:$B$464&$F$2:$F$464,$E$2:$E$464),2,)} -> 1号设计（2022年KTB） | U115: {=VLOOKUP(Q115&R115,IF({1,0},$B$2:$B$464&$F$2:$F$464,$C$2:$C$464),2,)} -> 51194 | V115: {=VLOOKUP(Q115&R115,IF({1,0},$B$2:$B$464&$F$2:$F$464,$D$2:$D$464),2,)} -> 强度室
A116: =ROW()-1 -> 115 | B116: 刘金晶 | C116: =IFERROR(VLOOKUP(B116,[1]工程研发事业部人员名单!B:D,2,0),"") -> 51641 | D116: =IFERROR(VLOOKUP(B116,[1]工程研发事业部人员名单!B:D,3,0),"") -> 结构二室 | E116: 1号设计（2022年KTB） | F116: =G116+H116+I116+J116 -> 220 | I116: 220 | N116: =VLOOKUP(E116,订单号!B:C,2,0) -> #N/A | O116: =VLOOKUP(C116,领导干部!B:B,1,0) -> #N/A | Q116: 闫峰 | R116: 146 | S116: {=VLOOKUP(Q116&R116,IF({1,0},$B$2:$B$464&$F$2:$F$464,$N$2:$N$464),2,)} -> 10502 | T116: {=VLOOKUP(Q116&R116,IF({1,0},$B$2:$B$464&$F$2:$F$464,$E$2:$E$464),2,)} -> 工程支持 | U116: {=VLOOKUP(Q116&R116,IF({1,0},$B$2:$B$464&$F$2:$F$464,$C$2:$C$464),2,)} -> 52027 | V116: {=VLOOKUP(Q116&R116,IF({1,0},$B$2:$B$464&$F$2:$F$464,$D$2:$D$464),2,)} -> 综合技术室
A117: =ROW()-1 -> 116 | B117: 郑配云 | C117: =IFERROR(VLOOKUP(B117,[1]工程研发事业部人员名单!B:D,2,0),"") -> 52029 | D117: =IFERROR(VLOOKUP(B117,[1]工程研发事业部人员名单!B:D,3,0),"") -> 结构二室 | E117: 1号设计（2022年KTB） | F117: =G117+H117+I117+J117 -> 235 | I117: 235 | N117: =VLOOKUP(E117,订单号!B:C,2,0) -> #N/A | O117: =VLOOKUP(C117,领导干部!B:B,1,0) -> #N/A | Q117: 闫洪乐 | R117: 120 | S117: {=VLOOKUP(Q117&R117,IF({1,0},$B$2:$B$464&$F$2:$F$464,$N$2:$N$464),2,)} -> #N/A | T117: {=VLOOKUP(Q117&R117,IF({1,0},$B$2:$B$464&$F$2:$F$464,$E$2:$E$464),2,)} -> CR929设计（2022年复材中心） | U117: {=VLOOKUP(Q117&R117,IF({1,0},$B$2:$B$464&$F$2:$F$464,$C$2:$C$464),2,)} -> 52347 | V117: {=VLOOKUP(Q117&R117,IF({1,0},$B$2:$B$464&$F$2:$F$464,$D$2:$D$464),2,)} -> 强度室
A118: =ROW()-1 -> 117 | B118: 刘朕 | C118: =IFERROR(VLOOKUP(B118,[1]工程研发事业部人员名单!B:D,2,0),"") -> 51190 | D118: =IFERROR(VLOOKUP(B118,[1]工程研发事业部人员名单!B:D,3,0),"") -> 结构二室 | E118: 1号设计（2022年KTB） | F118: =G118+H118+I118+J118 -> 200 | I118: 200 | N118: =VLOOKUP(E118,订单号!B:C,2,0) -> #N/A | O118: =VLOOKUP(C118,领导干部!B:B,1,0) -> #N/A | Q118: 杨春 | R118: 84 | S118: {=VLOOKUP(Q118&R118,IF({1,0},$B$2:$B$464&$F$2:$F$464,$N$2:$N$464),2,)} -> YZ40000680 | T118: {=VLOOKUP(Q118&R118,IF({1,0},$B$2:$B$464&$F$2:$F$464,$E$2:$E$464),2,)} -> C919设计（2022年上飞院） | U118: {=VLOOKUP(Q118&R118,IF({1,0},$B$2:$B$464&$F$2:$F$464,$C$2:$C$464),2,)} -> 51624 | V118: {=VLOOKUP(Q118&R118,IF({1,0},$B$2:$B$464&$F$2:$F$464,$D$2:$D$464),2,)} -> 结构一室
A119: =ROW()-1 -> 118 | B119: 张成 | C119: =IFERROR(VLOOKUP(B119,[1]工程研发事业部人员名单!B:D,2,0),"") -> 18548 | D119: =IFERROR(VLOOKUP(B119,[1]工程研发事业部人员名单!B:D,3,0),"") -> 结构二室 | E119: 1号设计（2022年KTB） | F119: =G119+H119+I119+J119 -> 260 | I119: 260 | N119: =VLOOKUP(E119,订单号!B:C,2,0) -> #N/A | O119: =VLOOKUP(C119,领导干部!B:B,1,0) -> #N/A | Q119: 杨会宁 | R119: 245 | S119: {=VLOOKUP(Q119&R119,IF({1,0},$B$2:$B$464&$F$2:$F$464,$N$2:$N$464),2,)} -> #N/A | T119: {=VLOOKUP(Q119&R119,IF({1,0},$B$2:$B$464&$F$2:$F$464,$E$2:$E$464),2,)} -> 1号设计（2022年KTB） | U119: {=VLOOKUP(Q119&R119,IF({1,0},$B$2:$B$464&$F$2:$F$464,$C$2:$C$464),2,)} -> 01728 | V119: {=VLOOKUP(Q119&R119,IF({1,0},$B$2:$B$464&$F$2:$F$464,$D$2:$D$464),2,)} -> 联络工程室
A120: =ROW()-1 -> 119 | B120: 杨会宁 | C120: =IFERROR(VLOOKUP(B120,[1]工程研发事业部人员名单!B:D,2,0),"") -> 01728 | D120: =IFERROR(VLOOKUP(B120,[1]工程研发事业部人员名单!B:D,3,0),"") -> 联络工程室 | E120: 1号设计（2022年KTB） | F120: =G120+H120+I120+J120 -> 245 | G120: 245 | N120: =VLOOKUP(E120,订单号!B:C,2,0) -> #N/A | O120: =VLOOKUP(C120,领导干部!B:B,1,0) -> #N/A | Q120: 杨珺涵 | R120: 270.25 | S120: {=VLOOKUP(Q120&R120,IF({1,0},$B$2:$B$464&$F$2:$F$464,$N$2:$N$464),2,)} -> 10502 | T120: {=VLOOKUP(Q120&R120,IF({1,0},$B$2:$B$464&$F$2:$F$464,$E$2:$E$464),2,)} -> 工程支持 | U120: {=VLOOKUP(Q120&R120,IF({1,0},$B$2:$B$464&$F$2:$F$464,$C$2:$C$464),2,)} -> 51570 | V120: {=VLOOKUP(Q120&R120,IF({1,0},$B$2:$B$464&$F$2:$F$464,$D$2:$D$464),2,)} -> 联络工程室
A121: =ROW()-1 -> 120 | B121: 孙永光 | C121: =IFERROR(VLOOKUP(B121,[1]工程研发事业部人员名单!B:D,2,0),"") -> 25601 | D121: =IFERROR(VLOOKUP(B121,[1]工程研发事业部人员名单!B:D,3,0),"") -> 联络工程室 | E121: 1号设计（2022年KTB） | F121: =G121+H121+I121+J121 -> 225 | G121: 225 | N121: =VLOOKUP(E121,订单号!B:C,2,0) -> #N/A | O121: =VLOOKUP(C121,领导干部!B:B,1,0) -> #N/A | Q121: 杨琼 | R121: 174.5 | S121: {=VLOOKUP(Q121&R121,IF({1,0},$B$2:$B$464&$F$2:$F$464,$N$2:$N$464),2,)} -> #N/A | T121: {=VLOOKUP(Q121&R121,IF({1,0},$B$2:$B$464&$F$2:$F$464,$E$2:$E$464),2,)} -> 1号设计（2022年KTB） | U121: {=VLOOKUP(Q121&R121,IF({1,0},$B$2:$B$464&$F$2:$F$464,$C$2:$C$464),2,)} -> 26828 | V121: {=VLOOKUP(Q121&R121,IF({1,0},$B$2:$B$464&$F$2:$F$464,$D$2:$D$464),2,)} -> 综合技术室
A122: =ROW()-1 -> 121 | B122: 赵婷 | C122: =IFERROR(VLOOKUP(B122,[1]工程研发事业部人员名单!B:D,2,0),"") -> 50702 | D122: =IFERROR(VLOOKUP(B122,[1]工程研发事业部人员名单!B:D,3,0),"") -> 总体室 | E122: 1号设计（2022年KTB） | F122: =G122+H122+I122+J122 -> 225 | I122: 225 | N122: =VLOOKUP(E122,订单号!B:C,2,0) -> #N/A | O122: =VLOOKUP(C122,领导干部!B:B,1,0) -> #N/A | Q122: 杨炎通 | R122: 300 | S122: {=VLOOKUP(Q122&R122,IF({1,0},$B$2:$B$464&$F$2:$F$464,$N$2:$N$464),2,)} -> #N/A | T122: {=VLOOKUP(Q122&R122,IF({1,0},$B$2:$B$464&$F$2:$F$464,$E$2:$E$464),2,)} -> 1号设计（2022年KTB） | U122: {=VLOOKUP(Q122&R122,IF({1,0},$B$2:$B$464&$F$2:$F$464,$C$2:$C$464),2,)} -> 51955 | V122: {=VLOOKUP(Q122&R122,IF({1,0},$B$2:$B$464&$F$2:$F$464,$D$2:$D$464),2,)} -> 结构一室
A123: =ROW()-1 -> 122 | B123: 杨琼 | C123: =IFERROR(VLOOKUP(B123,[1]工程研发事业部人员名单!B:D,2,0),"") -> 26828 | D123: =IFERROR(VLOOKUP(B123,[1]工程研发事业部人员名单!B:D,3,0),"") -> 综合技术室 | E123: 1号设计（2022年KTB） | F123: =G123+H123+I123+J123 -> 174.5 | G123: 174.5 | N123: =VLOOKUP(E123,订单号!B:C,2,0) -> #N/A | O123: =VLOOKUP(C123,领导干部!B:B,1,0) -> #N/A | Q123: 姚庆丰 | R123: 379.72 | S123: {=VLOOKUP(Q123&R123,IF({1,0},$B$2:$B$464&$F$2:$F$464,$N$2:$N$464),2,)} -> 10502 | T123: {=VLOOKUP(Q123&R123,IF({1,0},$B$2:$B$464&$F$2:$F$464,$E$2:$E$464),2,)} -> 工程支持 | U123: {=VLOOKUP(Q123&R123,IF({1,0},$B$2:$B$464&$F$2:$F$464,$C$2:$C$464),2,)} -> 18672 | V123: {=VLOOKUP(Q123&R123,IF({1,0},$B$2:$B$464&$F$2:$F$464,$D$2:$D$464),2,)} -> 联络工程室
A124: =ROW()-1 -> 123 | B124: 宋建毅 | C124: =IFERROR(VLOOKUP(B124,[1]工程研发事业部人员名单!B:D,2,0),"") -> 27100 | D124: =IFERROR(VLOOKUP(B124,[1]工程研发事业部人员名单!B:D,3,0),"") -> 综合技术室 | E124: 1号设计（2022年KTB） | F124: =G124+H124+I124+J124 -> 185 | G124: 185 | N124: =VLOOKUP(E124,订单号!B:C,2,0) -> #N/A | O124: =VLOOKUP(C124,领导干部!B:B,1,0) -> #N/A | Q124: 尤宏良 | R124: 218.3 | S124: {=VLOOKUP(Q124&R124,IF({1,0},$B$2:$B$464&$F$2:$F$464,$N$2:$N$464),2,)} -> #N/A | T124: {=VLOOKUP(Q124&R124,IF({1,0},$B$2:$B$464&$F$2:$F$464,$E$2:$E$464),2,)} -> 6号设计（2021年） | U124: {=VLOOKUP(Q124&R124,IF({1,0},$B$2:$B$464&$F$2:$F$464,$C$2:$C$464),2,)} -> 18550 | V124: {=VLOOKUP(Q124&R124,IF({1,0},$B$2:$B$464&$F$2:$F$464,$D$2:$D$464),2,)} -> 总体室
A125: =ROW()-1 -> 124 | B125: 李其鹏 | C125: =IFERROR(VLOOKUP(B125,[1]工程研发事业部人员名单!B:D,2,0),"") -> 51429 | D125: =IFERROR(VLOOKUP(B125,[1]工程研发事业部人员名单!B:D,3,0),"") -> 综合技术室 | E125: 1号设计（2022年KTB） | F125: =G125+H125+I125+J125 -> 80 | G125: 80 | N125: =VLOOKUP(E125,订单号!B:C,2,0) -> #N/A | O125: =VLOOKUP(C125,领导干部!B:B,1,0) -> #N/A | Q125: 于磊 | R125: 245 | S125: {=VLOOKUP(Q125&R125,IF({1,0},$B$2:$B$464&$F$2:$F$464,$N$2:$N$464),2,)} -> #N/A | T125: {=VLOOKUP(Q125&R125,IF({1,0},$B$2:$B$464&$F$2:$F$464,$E$2:$E$464),2,)} -> CR929设计（2022年上飞院） | U125: {=VLOOKUP(Q125&R125,IF({1,0},$B$2:$B$464&$F$2:$F$464,$C$2:$C$464),2,)} -> 51400 | V125: {=VLOOKUP(Q125&R125,IF({1,0},$B$2:$B$464&$F$2:$F$464,$D$2:$D$464),2,)} -> 结构一室
A126: =ROW()-1 -> 125 | B126: 宋凯 | C126: =IFERROR(VLOOKUP(B126,[1]工程研发事业部人员名单!B:D,2,0),"") -> 51951 | D126: =IFERROR(VLOOKUP(B126,[1]工程研发事业部人员名单!B:D,3,0),"") -> 系统室 | E126: 1号设计（2022年KTB） | F126: =G126+H126+I126+J126 -> 10 | G126: 10 | N126: =VLOOKUP(E126,订单号!B:C,2,0) -> #N/A | O126: =VLOOKUP(C126,领导干部!B:B,1,0) -> #N/A | Q126: 臧爱丽 | R126: 278.585 | S126: {=VLOOKUP(Q126&R126,IF({1,0},$B$2:$B$464&$F$2:$F$464,$N$2:$N$464),2,)} -> 10502 | T126: {=VLOOKUP(Q126&R126,IF({1,0},$B$2:$B$464&$F$2:$F$464,$E$2:$E$464),2,)} -> 工程支持 | U126: {=VLOOKUP(Q126&R126,IF({1,0},$B$2:$B$464&$F$2:$F$464,$C$2:$C$464),2,)} -> 51428 | V126: {=VLOOKUP(Q126&R126,IF({1,0},$B$2:$B$464&$F$2:$F$464,$D$2:$D$464),2,)} -> 联络工程室
A127: =ROW()-1 -> 126 | B127: 杨炎通 | C127: =IFERROR(VLOOKUP(B127,[1]工程研发事业部人员名单!B:D,2,0),"") -> 51955 | D127: =IFERROR(VLOOKUP(B127,[1]工程研发事业部人员名单!B:D,3,0),"") -> 结构一室 | E127: 1号设计（2022年KTB） | F127: =G127+H127+I127+J127 -> 300 | I127: 300 | N127: =VLOOKUP(E127,订单号!B:C,2,0) -> #N/A | O127: =VLOOKUP(C127,领导干部!B:B,1,0) -> #N/A | Q127: 张曾霞 | R127: 384.4 | S127: {=VLOOKUP(Q127&R127,IF({1,0},$B$2:$B$464&$F$2:$F$464,$N$2:$N$464),2,)} -> 10502 | T127: {=VLOOKUP(Q127&R127,IF({1,0},$B$2:$B$464&$F$2:$F$464,$E$2:$E$464),2,)} -> 工程支持 | U127: {=VLOOKUP(Q127&R127,IF({1,0},$B$2:$B$464&$F$2:$F$464,$C$2:$C$464),2,)} -> 27680 | V127: {=VLOOKUP(Q127&R127,IF({1,0},$B$2:$B$464&$F$2:$F$464,$D$2:$D$464),2,)} -> 联络工程室
A128: =ROW()-1 -> 127 | B128: 马壮 | C128: =IFERROR(VLOOKUP(B128,[1]工程研发事业部人员名单!B:D,2,0),"") -> 51640 | D128: =IFERROR(VLOOKUP(B128,[1]工程研发事业部人员名单!B:D,3,0),"") -> 结构一室 | E128: 1号设计（2022年KTB） | F128: =G128+H128+I128+J128 -> 300 | I128: 300 | N128: =VLOOKUP(E128,订单号!B:C,2,0) -> #N/A | O128: =VLOOKUP(C128,领导干部!B:B,1,0) -> #N/A | Q128: 张成 | R128: 260 | S128: {=VLOOKUP(Q128&R128,IF({1,0},$B$2:$B$464&$F$2:$F$464,$N$2:$N$464),2,)} -> #N/A | T128: {=VLOOKUP(Q128&R128,IF({1,0},$B$2:$B$464&$F$2:$F$464,$E$2:$E$464),2,)} -> 1号设计（2022年KTB） | U128: {=VLOOKUP(Q128&R128,IF({1,0},$B$2:$B$464&$F$2:$F$464,$C$2:$C$464),2,)} -> 18548 | V128: {=VLOOKUP(Q128&R128,IF({1,0},$B$2:$B$464&$F$2:$F$464,$D$2:$D$464),2,)} -> 结构二室
A129: =ROW()-1 -> 128 | B129: 罗贵骞 | C129: =IFERROR(VLOOKUP(B129,[1]工程研发事业部人员名单!B:D,2,0),"") -> 51186 | D129: =IFERROR(VLOOKUP(B129,[1]工程研发事业部人员名单!B:D,3,0),"") -> 结构二室 | E129: 1号设计（2022年KTB） | F129: =G129+H129+I129+J129 -> 300 | I129: 300 | N129: =VLOOKUP(E129,订单号!B:C,2,0) -> #N/A | O129: =VLOOKUP(C129,领导干部!B:B,1,0) -> #N/A | Q129: 张刚 | R129: 208 | S129: {=VLOOKUP(Q129&R129,IF({1,0},$B$2:$B$464&$F$2:$F$464,$N$2:$N$464),2,)} -> #N/A | T129: {=VLOOKUP(Q129&R129,IF({1,0},$B$2:$B$464&$F$2:$F$464,$E$2:$E$464),2,)} -> CR929设计（2022年复材中心） | U129: {=VLOOKUP(Q129&R129,IF({1,0},$B$2:$B$464&$F$2:$F$464,$C$2:$C$464),2,)} -> 50278 | V129: {=VLOOKUP(Q129&R129,IF({1,0},$B$2:$B$464&$F$2:$F$464,$D$2:$D$464),2,)} -> 结构二室
A130: =ROW()-1 -> 129 | B130: 骆美玲 | C130: =IFERROR(VLOOKUP(B130,[1]工程研发事业部人员名单!B:D,2,0),"") -> 50713 | D130: =IFERROR(VLOOKUP(B130,[1]工程研发事业部人员名单!B:D,3,0),"") -> 系统室 | E130: 1号设计（2022年KTB） | F130: =G130+H130+I130+J130 -> 85 | G130: 85 | N130: =VLOOKUP(E130,订单号!B:C,2,0) -> #N/A | O130: =VLOOKUP(C130,领导干部!B:B,1,0) -> #N/A | Q130: 张继斌 | R130: 205.3 | S130: {=VLOOKUP(Q130&R130,IF({1,0},$B$2:$B$464&$F$2:$F$464,$N$2:$N$464),2,)} -> #N/A | T130: {=VLOOKUP(Q130&R130,IF({1,0},$B$2:$B$464&$F$2:$F$464,$E$2:$E$464),2,)} -> 6号设计（2021年） | U130: {=VLOOKUP(Q130&R130,IF({1,0},$B$2:$B$464&$F$2:$F$464,$C$2:$C$464),2,)} -> 17243 | V130: {=VLOOKUP(Q130&R130,IF({1,0},$B$2:$B$464&$F$2:$F$464,$D$2:$D$464),2,)} -> 总体室
A131: =ROW()-1 -> 130 | B131: 吴晓莉 | C131: =IFERROR(VLOOKUP(B131,[1]工程研发事业部人员名单!B:D,2,0),"") -> 50872 | D131: =IFERROR(VLOOKUP(B131,[1]工程研发事业部人员名单!B:D,3,0),"") -> 系统室 | E131: 1号设计（2022年KTB） | F131: =G131+H131+I131+J131 -> 175 | G131: 175 | N131: =VLOOKUP(E131,订单号!B:C,2,0) -> #N/A | O131: =VLOOKUP(C131,领导干部!B:B,1,0) -> #N/A | Q131: 张文静 | R131: 100 | S131: {=VLOOKUP(Q131&R131,IF({1,0},$B$2:$B$464&$F$2:$F$464,$N$2:$N$464),2,)} -> #N/A | T131: {=VLOOKUP(Q131&R131,IF({1,0},$B$2:$B$464&$F$2:$F$464,$E$2:$E$464),2,)} -> 1号设计（2022年KTB） | U131: {=VLOOKUP(Q131&R131,IF({1,0},$B$2:$B$464&$F$2:$F$464,$C$2:$C$464),2,)} -> 22259 | V131: {=VLOOKUP(Q131&R131,IF({1,0},$B$2:$B$464&$F$2:$F$464,$D$2:$D$464),2,)} -> 强度室
A132: =ROW()-1 -> 131 | B132: 马佳 | C132: =IFERROR(VLOOKUP(B132,[1]工程研发事业部人员名单!B:D,2,0),"") -> 52236 | D132: =IFERROR(VLOOKUP(B132,[1]工程研发事业部人员名单!B:D,3,0),"") -> 结构一室 | E132: 1号设计（2022年KTB） | F132: =G132+H132+I132+J132 -> 300 | I132: 300 | N132: =VLOOKUP(E132,订单号!B:C,2,0) -> #N/A | O132: =VLOOKUP(C132,领导干部!B:B,1,0) -> #N/A | Q132: 张熙尧 | R132: 170 | S132: {=VLOOKUP(Q132&R132,IF({1,0},$B$2:$B$464&$F$2:$F$464,$N$2:$N$464),2,)} -> #N/A | T132: {=VLOOKUP(Q132&R132,IF({1,0},$B$2:$B$464&$F$2:$F$464,$E$2:$E$464),2,)} -> CR929设计（2022年复材中心） | U132: {=VLOOKUP(Q132&R132,IF({1,0},$B$2:$B$464&$F$2:$F$464,$C$2:$C$464),2,)} -> 52017 | V132: {=VLOOKUP(Q132&R132,IF({1,0},$B$2:$B$464&$F$2:$F$464,$D$2:$D$464),2,)} -> 结构一室
A133: =ROW()-1 -> 132 | B133: 曲汝文 | C133: =IFERROR(VLOOKUP(B133,[1]工程研发事业部人员名单!B:D,2,0),"") -> 52133 | D133: =IFERROR(VLOOKUP(B133,[1]工程研发事业部人员名单!B:D,3,0),"") -> 结构一室 | E133: 1号设计（2022年KTB） | F133: =G133+H133+I133+J133 -> 190 | I133: 190 | N133: =VLOOKUP(E133,订单号!B:C,2,0) -> #N/A | O133: =VLOOKUP(C133,领导干部!B:B,1,0) -> #N/A | Q133: 张秀丽 | R133: 150 | S133: {=VLOOKUP(Q133&R133,IF({1,0},$B$2:$B$464&$F$2:$F$464,$N$2:$N$464),2,)} -> #N/A | T133: {=VLOOKUP(Q133&R133,IF({1,0},$B$2:$B$464&$F$2:$F$464,$E$2:$E$464),2,)} -> CR929设计（2022年上飞院） | U133: {=VLOOKUP(Q133&R133,IF({1,0},$B$2:$B$464&$F$2:$F$464,$C$2:$C$464),2,)} -> 51165 | V133: {=VLOOKUP(Q133&R133,IF({1,0},$B$2:$B$464&$F$2:$F$464,$D$2:$D$464),2,)} -> 结构一室
A134: =ROW()-1 -> 133 | B134: 周弘扬 | C134: =IFERROR(VLOOKUP(B134,[1]工程研发事业部人员名单!B:D,2,0),"") -> 52124 | D134: =IFERROR(VLOOKUP(B134,[1]工程研发事业部人员名单!B:D,3,0),"") -> 结构一室 | E134: 1号设计（2022年KTB） | F134: =G134+H134+I134+J134 -> 245 | I134: 245 | N134: =VLOOKUP(E134,订单号!B:C,2,0) -> #N/A | O134: =VLOOKUP(C134,领导干部!B:B,1,0) -> #N/A | Q134: 张一峤 | R134: 470.58 | S134: {=VLOOKUP(Q134&R134,IF({1,0},$B$2:$B$464&$F$2:$F$464,$N$2:$N$464),2,)} -> 10502 | T134: {=VLOOKUP(Q134&R134,IF({1,0},$B$2:$B$464&$F$2:$F$464,$E$2:$E$464),2,)} -> 工程支持 | U134: {=VLOOKUP(Q134&R134,IF({1,0},$B$2:$B$464&$F$2:$F$464,$C$2:$C$464),2,)} -> 50853 | V134: {=VLOOKUP(Q134&R134,IF({1,0},$B$2:$B$464&$F$2:$F$464,$D$2:$D$464),2,)} -> 联络工程室
A135: =ROW()-1 -> 134 | B135: 陈磊 | C135: =IFERROR(VLOOKUP(B135,[1]工程研发事业部人员名单!B:D,2,0),"") -> 52180 | D135: =IFERROR(VLOOKUP(B135,[1]工程研发事业部人员名单!B:D,3,0),"") -> 结构一室 | E135: 1号设计（2022年KTB） | F135: =G135+H135+I135+J135 -> 252 | I135: 252 | N135: =VLOOKUP(E135,订单号!B:C,2,0) -> #N/A | O135: =VLOOKUP(C135,领导干部!B:B,1,0) -> #N/A | Q135: 张智浩 | R135: 320 | S135: {=VLOOKUP(Q135&R135,IF({1,0},$B$2:$B$464&$F$2:$F$464,$N$2:$N$464),2,)} -> #N/A | T135: {=VLOOKUP(Q135&R135,IF({1,0},$B$2:$B$464&$F$2:$F$464,$E$2:$E$464),2,)} -> CR929设计（2022年上飞院） | U135: {=VLOOKUP(Q135&R135,IF({1,0},$B$2:$B$464&$F$2:$F$464,$C$2:$C$464),2,)} -> 52063 | V135: {=VLOOKUP(Q135&R135,IF({1,0},$B$2:$B$464&$F$2:$F$464,$D$2:$D$464),2,)} -> 结构一室
...

Sheet 领导干部
B1: 胸卡号 | C1: 姓名
B2: 22287 | C2: 孟凡力
B3: 17242 | C3: 刘杰
B4: 01720 | C4: 李勇
B6: 51184 | C6: 毛磊凯
B7: 22296 | C7: 刘旭
B8: 51188 | C8: 吕国成
B9: 51202 | C9: 林树德
B10: 50709 | C10: 刘洋
B11: 22260 | C11: 宋凯（总体）
B12: 51162 | C12: 王大昱
B13: 26621 | C13: 王超

Sheet 订单号
B1: 1号-1.3设计 | C1: YZ40000401
B2: 1号-1.4项目 | C2: YZ40000413
B3: 5号5-2设计 | C3: YZ40000734
B4: 6号-2设计 | C4: YZ40000762
B5: 6号-3.1设计 | C5: YZ40000701
B6: 6号-3.2设计 | C6: YZ40000763
B7: 6号-3.3设计 | C7: YZ40000728
B8: 6号-4设计 | C8: YZ40000764
B9: 6号-5设计 | C9: YZ40000411
B10: 6号-6设计 | C10: YZ40000402
B11: WH1项目总体/系统/适航等其它专业 | C11: YZ-RD202428
B12: WH1项目结构强度综合 | C12: YZ-RD202428
... B32: 工程研发事业部 | C32: YZ40000724
B33: 工程支持 | C33: 10502
B34: 工信部强度手册 | C34: YZ40000481
B35: 哈工程课题 | C35: YZ40000487
B36: 坠撞课题研究
B37: SIA某无人机设计 | C37: YZ40000405
B38: 无人机论证与预研 | C38: YZ-RD202428
B39: 党建工作
B40: 培训工作
B41: 重点工作任务
B42: 临时工程支持

Sheet 提取订单号（不含领导干部）
A1: 姓名 | B1: 胸卡号 | C1: 专业室 | D1: 项目简称 | E1: 订单号 | F1: 是否领导干部
A2: 柴宝 | B2: 51944 | C2: 强度室 | D2: C929设计（2025年上飞院） | E2: YZ40000415 | F2: =VLOOKUP(B2,领导干部!B:B,1,0) -> #N/A
A3: 陈杰 | B3: 25600 | C3: 结构二室 | D3: WH1项目结构强度综合 | E3: YZ-RD202428 | F3: =VLOOKUP(B3,领导干部!B:B,1,0) -> #N/A
A4: 陈坤 | B4: 51576 | C4: 联络工程室 | D4: 工程支持 | E4: YZ40000419 | F4: =VLOOKUP(B4,领导干部!B:B,1,0) -> #N/A
A5: 陈磊 | B5: 52180 | C5: 结构一室 | D5: C929设计（2025年上飞院） | E5: YZ40000415 | F5: =VLOOKUP(B5,领导干部!B:B,1,0) -> #N/A
A6: 陈瑞东 | B6: 51181 | C6: 强度室 | D6: C929设计（2025年上飞院） | E6: YZ40000415 | F6: =VLOOKUP(B6,领导干部!B:B,1,0) -> #N/A
A7: 晨曦 | B7: 50030 | C7: 强度室 | D7: C919基本型设计（2025年上飞院） | E7: YZ40000419 | F7: =VLOOKUP(B7,领导干部!B:B,1,0) -> #N/A
A8: 褚永鑫 | B8: 22253 | C8: 联络工程室 | D8: 工程支持 | E8: YZ40000419 | F8: =VLOOKUP(B8,领导干部!B:B,1,0) -> #N/A
A9: 丛家勇 | B9: 50281 | C9: 结构一室 | D9: C929设计（2025年上飞院） | E9: YZ40000415 | F9: =VLOOKUP(B9,领导干部!B:B,1,0) -> #N/A
A10: 董晓莉 | B10: 51211 | C10: 结构一室 | D10: WH1项目结构强度综合 | E10: YZ-RD202428 | F10: =VLOOKUP(B10,领导干部!B:B,1,0) -> #N/A
A11: 杜洪雨 | B11: 51170 | C11: 结构二室 | D11: C929设计（2025年上飞院） | E11: YZ40000415 | F11: =VLOOKUP(B11,领导干部!B:B,1,0) -> #N/A
A12: 付强 | B12: 25549 | C12: 联络工程室 | D12: 工程支持 | E12: YZ40000419 | F12: =VLOOKUP(B12,领导干部!B:B,1,0) -> #N/A
A13: 付泉铭 | B13: 51555 | C13: 联络工程室 | D13: SIA无人机设计-2 | E13: YZ40000422 | F13: =VLOOKUP(B13,领导干部!B:B,1,0) -> #N/A
... A79: 万方 | B79: 51387 | C79: 系统室 | D79: C919基本型设计（2025年上飞院） | E79: YZ40000419 | F79: =VLOOKUP(B79,领导干部!B:B,1,0) -> #N/A
A80: 王超 | B80: 26621 | C80: 联络工程室 | D80: 培训工作 | E80: 0 | F80: =VLOOKUP(B80,领导干部!B:B,1,0) -> 26621
A81: 王琛 | B81: 22291 | C81: 综合技术室 | D81: C919高原型设计（2025年上飞院） | E81: YZ40000417 | F81: =VLOOKUP(B81,领导干部!B:B,1,0) -> #N/A
A82: 王呈呈 | B82: 51196 | C82: 强度室 | D82: WH1项目结构强度综合 | E82: YZ-RD202428 | F82: =VLOOKUP(B82,领导干部!B:B,1,0) -> #N/A
A83: 王川 | B83: 22250 | C83: 联络工程室 | D83: 工程支持 | E83: YZ-RD202428 | F83: =VLOOKUP(B83,领导干部!B:B,1,0) -> #N/A
A84: 王大昱 | B84: 51162 | C84: 工程项目室 /适航工程室 | D84: 培训工作 | E84: 0 | F84: =VLOOKUP(B84,领导干部!B:B,1,0) -> 51162
A85: 王健 | B85: 51784 | C85: 结构一室 | D85: C929设计（2025年上飞院） | E85: YZ40000415 | F85: =VLOOKUP(B85,领导干部!B:B,1,0) -> #N/A
A86: 王立庆 | B86: 27106 | C86: 联络工程室 | D86: 工程支持 | E86: YZ-RD202428 | F86: =VLOOKUP(B86,领导干部!B:B,1,0) -> #N/A
A87: 王连斌 | B87: 51396 | C87: 联络工程室 | D87: 工程支持 | E87: YZ-RD202428 | F87: =VLOOKUP(B87,领导干部!B:B,1,0) -> #N/A
A88: 王瑞龙 | B88: 26654 | C88: 联络工程室 | D88: SIA无人机设计-2 | E88: YZ40000422 | F88: =VLOOKUP(B88,领导干部!B:B,1,0) -> #N/A
A89: 王世清 | B89: 50317 | C89: 联络工程室 | D89: 工程支持 | E89: YZ-RD202428 | F89: =VLOOKUP(B89,领导干部!B:B,1,0) -> #N/A
A90: 王岩 | B90: 51175 | C90: 强度室 | D90: C929设计（2025年上飞院） | E90: YZ40000415 | F90: =VLOOKUP(B90,领导干部!B:B,1,0) -> #N/A
A91: 王艺霖 | B91: 25762 | C91: 结构二室 | D91: C929设计（2025年上飞院） | E91: YZ40000415 | F91: =VLOOKUP(B91,领导干部!B:B,1,0) -> #N/A
A92: 王勇 | B92: 51226 | C92: 综合技术室 | D92: 工程支持 | E92: YZ40000410 | F92: =VLOOKUP(B92,领导干部!B:B,1,0) -> #N/A
A93: 王哲 | B93: 25071 | C93: 结构一室 | D93: WH1项目结构强度综合 | E93: YZ-RD202428 | F93: =VLOOKUP(B93,领导干部!B:B,1,0) -> #N/A
A94: 韦杰琼 | B94: 25599 | C94: 联络工程室 | D94: WH1项目结构强度综合 | E94: YZ-RD202428 | F94: =VLOOKUP(B94,领导干部!B:B,1,0) -> #N/A
A95: 魏春生 | B95: 51389 | C95: 系统室 | D95: C919手册优化（2025年复材中心） | E95: YZ40000416 | F95: =VLOOKUP(B95,领导干部!B:B,1,0) -> #N/A
A96: 魏士礼 | B96: 22294 | C96: 结构一室 | D96: WH1项目结构强度综合 | E96: YZ-RD202428 | F96: =VLOOKUP(B96,领导干部!B:B,1,0) -> #N/A
... A150: 崔明慧 | B150: 14901 | C150: 联络工程室 | D150: C929设计（2025年复材中心） | E150: YZ40000418 | F150: =VLOOKUP(B150,领导干部!B:B,1,0) -> #N/A
A151: 孙红军 | B151: 02501 | C151: 综合技术室 | D151: 工程支持 | E151: YZ40000410 | F151: =VLOOKUP(B151,领导干部!B:B,1,0) -> #N/A
A152: 赵陈 | B152: 52123 | C152: 结构二室 | D152: #N/A | E152: YZ-RD202428 | F152: =VLOOKUP(B152,领导干部!B:B,1,0) -> #N/A
